Workbook

Sheet 00_Cover
A1: ="RAB dan Model Investasi — Agroforestri "&'02_Assumptions'!$C$6&" ha" -> RAB dan Model Investasi — Agroforestri 100 ha
A2: Mode dua penggerak: ubah luas kebun dan jumlah lokasi. Asumsi harga/biaya tetap dapat disesuaikan bila tersedia quotation baru.
A4: Tujuan
A5: Workbook ini menghitung seleksi lahan, pembukaan tanpa bakar, infrastruktur, bibit, alat dan mesin, input pertanian, HOK, pemeliharaan, sertifikasi, produksi, pendapatan, dan arus kas 10 tahun untuk kebun agroforestri terpadu.
A6: Model membandingkan satu lokasi dengan empat lokasi. Model ini adalah alat perencanaan investasi, bukan pengganti uji legal, tanah/air, desain teknik, diagnosis kesehatan tanaman, label pestisida, atau penawaran pemasok.
A7: Desain dasar memakai satu matriks areal efektif: kelapa, durian, dan pisang ditanam bersama; gamal, Indigofera, serai wangi, penutup tanah, dan strip biodiversitas tersebar di lorong/kontur. Tidak ada blok komoditas terpisah.
A9: Cara menggunakan
A10: 1 | B10: Untuk simulasi cepat, ubah hanya 02_Assumptions!C6 (luas) dan C8 (jumlah lokasi). Semua volume dan total mengikuti otomatis.
A11: 2 | B11: Jumlah lokasi dapat dipilih 1–4; biaya berbasis lokasi dan kebutuhan alat/staf dihitung ulang otomatis.
A12: 3 | B12: Harga satuan, upah, tarif sewa, dan biaya lain tetap terbuka sebagai asumsi opsional—ubah hanya bila memiliki dasar yang lebih baik.
A13: 4 | B13: Jangan mengetik ulang populasi, volume input, HOK, kru, atau total biaya: sel tersebut adalah hasil formula.
A14: 5 | B14: Ganti harga asumsi dengan sedikitnya tiga penawaran yang setara dan dokumentasikan pilihan.
A15: 6 | B15: Baca 15_Pemeriksaan dan peringatan sebelum memakai hasil investasi.
A16: 7 | B16: Buka 18_Panduan_Per_Sheet untuk paparan tujuan, cara membaca, input, keterkaitan, dan keputusan pada setiap sheet.
A18: Legenda warna
A19: Jingga dengan angka biru | B19: Dua penggerak utama: luas dan jumlah lokasi
A20: Kuning muda dengan angka biru | B20: Asumsi opsional (harga, tarif, dosis, produktivitas); sudah terisi dan tidak wajib diubah
A21: Hijau muda | B21: Rumus/hasil otomatis—jangan ditimpa
A22: Catatan jingga/merah | B22: Risiko, batasan, atau konfirmasi wajib
A23: Total hijau | B23: Subtotal atau hasil utama
A26: Pengecualian dan kondisi utama
A27: Akuisisi/sewa lahan masih Rp0 sampai tersedia calon lahan dan uji legal/valuasi.
A28: PPN, pajak badan, pembiayaan, penyusutan, pajak transaksi tanah, dan pabrik pengolahan tidak termasuk.
A29: Proyek mengasumsikan lahan pertanian terdegradasi/non-hutan. Konversi hutan alam, kawasan lindung, atau HCV adalah Tidak Layak.
A30: Input sintetis berhenti setelah fase transisi yang ditentukan; klaim organik memerlukan penetapan LSO.
A31: Pendapatan tingkat kebun dan tanpa premi. Pendapatan nanas/tambahan hanya masuk bila diaktifkan; manfaat penutup tanah tidak dimonetisasi.
A32: Harga adalah asumsi perencanaan 2026. Baris berkeyakinan rendah memerlukan penawaran; hasil biologis memerlukan validasi lapangan.

Sheet Panduan_Per_Sheet
A1: Panduan Membaca Setiap Sheet
A2: Panduan ini memakai mode dua penggerak: luas kebun dan jumlah lokasi. Asumsi harga/biaya tetap bisa diubah secara opsional; semua output lainnya mengikuti formula.
A5: Alur penggunaan yang disarankan
A6: 1 | B6: Orientasi | C6: 00_Cover → 18_Panduan_Per_Sheet → 01_Dashboard | D6: Pahami ruang lingkup, batasan, cara kerja model, dan posisi ekonomi awal sebelum mengubah angka.
A7: 2 | B7: Tetapkan dasar | C7: 02_Assumptions → 03_Land_Screening → 04_Planting_Design | D7: Masukkan penggerak proyek, saring calon lahan, lalu periksa desain populasi agroforestri terpadu.
A8: 3 | B8: Bangun anggaran | C8: 05_Workplan_Labor → 06_Equipment_Tools → 07_Agri_Inputs → 08_CAPEX_RAB → 09_OPEX_10Y → 14_Certification_ESG → 17_Model_Fleksibel → 20_Operasi_Efisien | D8: Validasi volume kerja, alat, input, investasi, biaya tahunan, kewajiban sertifikasi, dan kebutuhan tambahan.
A9: 4 | B9: Uji hasil dan putuskan | C9: 10_Production_Revenue → 11_Cash_Flow → 19_Optimasi_10Tahun → 21_Pendapatan_Tambahan → 13_Sensitivity → 15_Checks → 16/22_Sources | D9: Nilai produksi, arus kas, biaya fragmentasi, ketahanan skenario, integritas rumus, dan kekuatan bukti.
A11: No. | B11: Nama sheet | C11: Tujuan/fungsi | D11: Cara membaca | E11: Input dan keterkaitan | F11: Keputusan/peringatan
A12: 1 | B12: 00_Cover | C12: Halaman pembuka dan batas penggunaan model. | D12: Baca tujuan, konsep agroforestri terpadu, legenda warna, cara penggunaan, dan pengecualian. Sheet ini menjelaskan apa yang dihitung dan apa yang belum termasuk. | E12: Tidak ada perhitungan utama yang perlu diubah di sini. Cover mengarahkan pengguna ke asumsi, pemeriksaan, sumber, dan panduan. | F12: Pastikan seluruh pengguna menyepakati ruang lingkup sebelum menggunakan angka untuk persetujuan investasi.
A13: 2 | B13: 01_Dashboard | C13: Ringkasan eksekutif investasi dan operasi. | D13: Mulai dari luas bruto/efektif, investasi awal, pendanaan puncak, NPV/IRR, populasi, dan kru puncak. Lanjutkan ke grafik pendapatan, arus kas tahunan, arus kas kumulatif, serta perbandingan satu dan empat lokasi. | E13: Menarik hasil dari 02, 04, 05, 08, 09, 10, 11, dan 12. Tidak untuk diisi manual. | F13: NPV negatif atau pengembalian lewat Tahun 10 menunjukkan kebutuhan optimasi desain, produktivitas, harga, pasar, atau horizon—bukan alasan menghapus drainase, biosekuriti, atau mutu bibit.
A14: 3 | B14: 02_Assumptions | C14: Pusat kendali seluruh penggerak model. | D14: Baca per kelompok: proyek/finansial, luas, kepadatan, harga bibit dan hasil, tenaga kerja, produktivitas, input, sertifikasi, serta faktor skenario. Sel kuning dengan angka biru adalah input; sel hijau adalah rumus tertaut. | E14: Luas bruto, area efektif, jumlah lokasi, kerapatan, harga, upah, inflasi, dosis, survival, yield, dan fase sintetis mengubah hampir seluruh sheet. | F14: Ganti asumsi berkeyakinan rendah dengan hasil survei, uji laboratorium, kontrak pembeli, dan penawaran pemasok. Hindari menimpa sel formula.
A15: 4 | B15: 03_Land_Screening | C15: Menyeleksi calon lahan dan menghentikan lokasi berisiko tinggi. | D15: Isi skor 1–5 hanya jika tersedia bukti. Bandingkan skor berbobot calon A–D, lalu periksa gerbang legal, HCV/hutan, banjir, air, penyakit pisang, dan lereng. Bagian terakhir menunjukkan proses uji tuntas empat minggu. | E15: Skor dan status calon lahan diisi pengguna. Hasilnya menjadi dasar sebelum biaya pembukaan, survei detail, dan desain final dikeluarkan. | F15: Setiap gerbang Tidak Layak mengalahkan skor agregat. Tidak ada calon yang boleh dianggap siap hanya karena nilai totalnya tinggi.
A16: 5 | B16: 04_Planting_Design | C16: Mengubah luas menjadi populasi dan kebutuhan bibit dalam satu matriks agroforestri. | D16: Periksa area efektif, kerapatan dan populasi kelapa, durian, pisang, gamal, Indigofera, serai wangi, penutup tanah, serta opsi. Lihat kebutuhan cadangan, bibit dibeli, tanaman hidup, harga, dan total pengadaan. | E16: Mengikuti luas efektif, kerapatan, cadangan bibit, survival, dan harga dari 02 serta opsi dari 17. Mengalir ke HOK, input, CAPEX, produksi, dan revenue. | F16: Populasi adalah rancangan awal. Finalisasi jarak dan posisi di lapangan berdasarkan kontur, cahaya, air, akses, dan ukuran tajuk dewasa; bukan membagi kebun menjadi blok komoditas.
A17: 6 | B17: 05_Workplan_Labor | C17: Menghitung urutan pekerjaan, HOK, durasi, dan kebutuhan kru. | D17: Baca pekerjaan Tahun 0 dari asesmen sampai penanaman, kemudian HOK bulanan dan pemeliharaan tahunan. Total HOK dibagi hari kerja untuk memperoleh kru rata-rata; kru puncak memasukkan faktor kebutuhan puncak. | E17: Jumlah pekerjaan mengikuti luas, populasi, unit infrastruktur, dan lokasi. HOK/unit, upah, hari kerja, serta faktor puncak berasal dari 02 dan baris tambahan dari 17. | F17: Gunakan untuk rencana rekrutmen, kontraktor, mobilisasi, dan kalender kerja. Pastikan tarif kontraktor yang sudah termasuk tenaga tidak dihitung kembali sebagai HOK langsung.
A18: 7 | B18: 06_Equipment_Tools | C18: Merinci alat produksi, mesin, kendaraan, APD, dan penggantian. | D18: Untuk setiap item, lihat kategori, fungsi, jumlah per 100 ha, jumlah minimum per lokasi, unit, harga, total satu/empat lokasi, umur pakai, siklus penggantian, dan kenaikan akibat lokasi tambahan. | E18: Jumlah mengikuti luas dan lokasi; harga serta umur pakai dapat diubah. Total alat mengalir ke CAPEX dan penggantian/perawatan OPEX. | F18: Tentukan beli atau sewa berdasarkan jam pakai, dukungan servis, akses suku cadang, dan risiko alat menganggur. Validasi spesifikasi dengan kondisi lereng, jalan, dan air.
A19: 8 | B19: 07_Agri_Inputs | C19: Menghitung input pertanian per tahun secara terperinci. | D19: Baca komoditas, jenis input, alasan penggunaan, dosis, frekuensi, harga, serta jumlah dan biaya Tahun 1–10. Baris total merangkum kebutuhan input tahunan seluruh sistem agroforestri. | E19: Volume mengikuti luas/populasi yang memenuhi syarat, tanaman hidup, dosis, frekuensi, fase umur, inflasi, dan penghentian input sintetis. Opsi aktif dari 17 ikut masuk. | F19: Dosis adalah allowance perencanaan. Uji tanah, daun, air, riwayat lahan, diagnosis OPT, label resmi, masa tunggu, dan standar organik harus menentukan aplikasi nyata.
A20: 9 | B20: 08_CAPEX_RAB | C20: Menggabungkan seluruh investasi awal proyek. | D20: Telaah per tahap: lahan/asesmen, survei, persiapan, tanah, jalan/drainase, batas, fasilitas, mobilisasi, penanaman, alat, sistem, dan cadangan. Bandingkan total satu lokasi, empat lokasi, dan skenario terpilih. | E20: Menarik jumlah dan harga dari 02, 04, 05, 06, 14, dan 17. Jumlah lokasi menggandakan komponen yang minimum per lokasi atau mengikuti perimeter/mobilisasi. | F20: Biaya lahan masih Rp0 sampai ada objek nyata. Gunakan BOQ teknik dan sedikitnya tiga quotation untuk item material; cegah duplikasi tenaga, alat, atau fasilitas.
A21: 10 | B21: 09_OPEX_10Y | C21: Menghitung biaya operasional nominal selama 10 tahun. | D21: Baca total tahunan menurut staf tetap, HOK, input, perawatan, penggantian alat, pengendalian gulma, panen, sertifikasi, serta biaya tambahan. Bagian staf menunjukkan jabatan dan perbedaan kebutuhan satu/empat lokasi. | E21: Mengikuti upah, inflasi, jumlah lokasi, HOK, input, aset, panen, sertifikasi, dan baris tambahan aktif. Menjadi pengurang pada arus kas. | F21: Bedakan biaya tetap, biaya berbasis luas, biaya berbasis lokasi, dan biaya variabel panen. Gunakan angka nominal untuk kebutuhan kas dan jangan mencampurnya dengan harga riil tanpa penyesuaian.
A22: 11 | B22: 10_Production_Revenue | C22: Memproyeksikan hasil dan pendapatan tiap komoditas. | D22: Untuk pisang, kelapa, durian, dan opsi tambahan, baca populasi hidup, hasil per tanaman/rumpun menurut umur, harga tingkat kebun, pendapatan per tahun, serta biaya panen variabel. | E22: Mengikuti tanaman hidup dari 04/17, kurva hasil, harga, eskalasi, survival, dan status aktif. Total pendapatan masuk ke 11; biaya panen masuk ke OPEX. | F22: Tidak ada premi organik dalam kasus dasar. Konfirmasi varietas, naungan, pola produksi, mutu, kehilangan panen, kapasitas pasar, dan kontrak offtake sebelum mengandalkan proyeksi.
A23: 12 | B23: 11_Cash_Flow | C23: Mengukur kebutuhan kas dan kelayakan finansial proyek. | D23: Arus kas proyek = pendapatan dikurangi OPEX dan CAPEX. Baca arus kas tahunan, kumulatif, NPV pada tingkat diskonto, IRR bila tersedia, tahun pengembalian, pendanaan puncak, dan rasio manfaat-biaya terdiskonto. | E23: Menarik CAPEX dari 08, OPEX dari 09, revenue dari 10, dan tingkat diskonto dari 02. Semua perubahan penggerak utama mengalir ke hasil ini. | F23: Gunakan NPV untuk keputusan ekonomi dan pendanaan puncak untuk kebutuhan modal. Jika arus kas tidak berganti tanda secara valid, IRR dapat tidak bermakna; jangan memaksakan interpretasi.
... A34: 22 | B34: 22_Sumber_Optimasi | C34: Mendokumentasikan bukti dan tingkat keyakinan seluruh pengungkit optimasi. | D34: Cari ID OPT/ASM dari sheet 20–21, baca URL, cara penerapan, dan validasi wajib. | E34: Tidak ada rumus utama; tambahkan hasil quotation, kontrak, demplot, dan MRV. | F34: ASM-QUOTE/RISK/PILOT bukan fakta pasar dan tidak boleh dipakai sebagai approval final.
A36: Prinsip penggunaan setelah optimasi
A37: Target untung Tahun 10 dibangun dari penghematan yang dapat ditelusuri dan pendapatan yang dikenai biaya, mass balance, serta haircut risiko. Untuk keputusan bankable, nolkan pendanaan yang belum dikontrak, ganti quotation rendah-keyakinan, dan jalankan kembali 19_Optimasi_10Tahun serta 15_Checks.

Sheet 01_Dashboard
A1: ="Ringkasan Investasi Agroforestri "&'02_Assumptions'!$C$6&" ha — "&'02_Assumptions'!$C$8&" lokasi" -> Ringkasan Investasi Agroforestri 100 ha — 1 lokasi
A2: Cukup ubah dua penggerak pada 02_Assumptions: luas kebun dan jumlah lokasi. Harga/biaya dapat disesuaikan secara opsional; seluruh KPI mengikuti rumus.
A4: Keluaran skenario optimasi aktif
A5: Luas bruto / efektif | E5: Investasi awal optimasi | I5: Pendanaan puncak optimasi
A6: ='02_Assumptions'!$C$6 -> 100 | E6: ='19_Optimasi_10Tahun'!$C$6 -> 14576030480 | I6: ='19_Optimasi_10Tahun'!$C$13 -> 1.7456171e+10
A7: ='02_Assumptions'!$C$6*'02_Assumptions'!$C$7 -> 88 | E7: ="Skenario: "&'02_Assumptions'!$C$8&" lokasi" -> Skenario: 1 lokasi | I7: =IF(ISNUMBER('19_Optimasi_10Tahun'!$C$14),"Balik modal: Tahun "&'19_Optimasi_10Tahun'!$C$14,"Balik modal: "&'19_Optimasi_10Tahun'!$C$14) -> Balik modal: Tahun 10
A9: NPV / IRR optimasi | E9: Pohon kelapa / durian | I9: Rumpun pisang awal / kru puncak T0
A10: ='19_Optimasi_10Tahun'!$C$11 -> -9.4097266e+09 | E10: ='04_Planting_Design'!$D$8 -> 7304 | I10: ='04_Planting_Design'!$H$8 -> 44000
A11: ='19_Optimasi_10Tahun'!$C$12 -> 0.009061345 | E11: ='04_Planting_Design'!$F$8 -> 2640 | I11: ='05_Workplan_Labor'!$Z$27 -> 70.060267
A13: Model otomatis: matriks agroforestri, nanas, penutup tanah legum, input pertanian, kompos internal, PHT, alat beli/sewa, tenaga kerja, kemitraan, dan diversifikasi kelapa mengikuti luas serta jumlah lokasi.
A15: Titik keputusan
A16: Konfigurasi yang disarankan | B16: Satu lokasi berdekatan seluas 100 ha | C16: Empat lokasi menduplikasi perimeter, sarana, alat, staf, dan logistik
A17: Persetujuan lahan | B17: Belum ada calon lahan yang dinyatakan siap | C17: Selesaikan uji legal, HCV/sosial, tanah, air, lereng, banjir, dan penyakit pisang
A18: Jalur organik | B18: Masa transisi, bukan klaim langsung | C18: Input sintetis berhenti sesuai pengaturan; LSO menentukan kelayakan
A19: Disiplin pendapatan | B19: Tanpa premi organik; opsi hanya masuk bila aktif | C19: Pastikan offtake tingkat kebun dan spesifikasi mutu sebelum keputusan akhir
A20: Penggerak nilai terbesar | B20: Durian mulai T5 | C20: Juga asumsi biologis dan harga yang paling berisiko
A21: Penggerak survival yang dapat dikendalikan | B21: Drainase, air, bibit bebas penyakit, QC pembibitan, dan sulaman | C21: Jangan mengurangi pengendali tersebut demi memperbaiki NPV
A24: Pendapatan tahunan dan arus kas skenario optimasi
A25: Tahun | B25: Total pendapatan | C25: Arus kas proyek | D25: Arus kas kumulatif
A26: Y1 | B26: ='19_Optimasi_10Tahun'!$C$18 -> 5263368000 | C26: ='19_Optimasi_10Tahun'!$C$21 -> 370949900 | D26: ='19_Optimasi_10Tahun'!$C$22 -> -14205080580
A27: Y2 | B27: ='19_Optimasi_10Tahun'!$D$18 -> 4844326080 | C27: ='19_Optimasi_10Tahun'!$D$21 -> -36793954 | D27: ='19_Optimasi_10Tahun'!$D$22 -> -1.4241875e+10
A28: Y3 | B28: ='19_Optimasi_10Tahun'!$E$18 -> 3.3874715e+09 | C28: ='19_Optimasi_10Tahun'!$E$21 -> -7.9396498e+08 | D28: ='19_Optimasi_10Tahun'!$E$22 -> -1.503584e+10
A29: Y4 | B29: ='19_Optimasi_10Tahun'!$F$18 -> 2.7035314e+09 | C29: ='19_Optimasi_10Tahun'!$F$21 -> -1.2737051e+09 | D29: ='19_Optimasi_10Tahun'!$F$22 -> -1.6309545e+10
A30: Y5 | B30: ='19_Optimasi_10Tahun'!$G$18 -> 3.2155436e+09 | C30: ='19_Optimasi_10Tahun'!$G$21 -> -1.1466268e+09 | D30: ='19_Optimasi_10Tahun'!$G$22 -> -1.7456171e+10
A31: Y6 | B31: ='19_Optimasi_10Tahun'!$H$18 -> 4.5804146e+09 | C31: ='19_Optimasi_10Tahun'!$H$21 -> 2.357133e+08 | D31: ='19_Optimasi_10Tahun'!$H$22 -> -1.7220458e+10
A32: Y7 | B32: ='19_Optimasi_10Tahun'!$I$18 -> 6.6688587e+09 | C32: ='19_Optimasi_10Tahun'!$I$21 -> 2.0758383e+09 | D32: ='19_Optimasi_10Tahun'!$I$22 -> -1.514462e+10
A33: Y8 | B33: ='19_Optimasi_10Tahun'!$J$18 -> 8.8586285e+09 | C33: ='19_Optimasi_10Tahun'!$J$21 -> 3.7019262e+09 | D33: ='19_Optimasi_10Tahun'!$J$22 -> -1.1442694e+10
A34: Y9 | B34: ='19_Optimasi_10Tahun'!$K$18 -> 1.0917408e+10 | C34: ='19_Optimasi_10Tahun'!$K$21 -> 5.7209427e+09 | D34: ='19_Optimasi_10Tahun'!$K$22 -> -5.7217508e+09
A35: Y10 | B35: ='19_Optimasi_10Tahun'!$L$18 -> 1.2630618e+10 | C35: ='19_Optimasi_10Tahun'!$L$21 -> 7.0597476e+09 | D35: ='19_Optimasi_10Tahun'!$L$22 -> 1.3379968e+09
A38: Pembanding baseline 1 lokasi dan 4 lokasi — sebelum paket optimasi
A39: Ukuran | B39: 1 lokasi | C39: 4 lokasi | D39: Selisih | E39: Makna
A40: Investasi awal | B40: ='12_Scenario_1v4'!$B$5 -> 15268150480 | C40: ='12_Scenario_1v4'!$C$5 -> 2.3875151e+10 | D40: =C40-B40 -> 8.6070007e+09 | E40: Duplikasi sarana
A41: OPEX 10 tahun | B41: ='12_Scenario_1v4'!$B$7 -> 4.8615696e+10 | C41: ='12_Scenario_1v4'!$C$7 -> 6.2902563e+10 | D41: =C41-B41 -> 1.4286867e+10 | E41: Tambahan staf/logistik
A42: NPV | B42: ='12_Scenario_1v4'!$B$8 -> -1.1872485e+10 | C42: ='12_Scenario_1v4'!$C$8 -> -2.8601005e+10 | D42: =C42-B42 -> -1.672852e+10 | E42: Hasil keputusan
A43: Pendanaan puncak | B43: ='12_Scenario_1v4'!$B$11 -> 1.9597093e+10 | C43: ='12_Scenario_1v4'!$C$11 -> 3.6542781e+10 | D43: =C43-B43 -> 1.6945688e+10 | E43: Kebutuhan kas
A46: Skenario Optimasi 10 Tahun — baca bersama 19_Optimasi_10Tahun
A47: Ukuran | B47: Model utama + nanas | C47: Optimasi | D47: Perubahan | E47: Penjelasan | G47: ='19_Optimasi_10Tahun'!G5 -> HASIL: Untung nominal T10, tetapi NPV masih negatif pada 12%.
A48: Investasi awal T0 | B48: ='19_Optimasi_10Tahun'!B6 -> 15268150480 | C48: ='19_Optimasi_10Tahun'!C6 -> 14576030480 | D48: ='19_Optimasi_10Tahun'!D6 -> -692120000 | E48: Kas awal
A49: CAPEX 10 tahun | B49: ='19_Optimasi_10Tahun'!B7 -> 15954280480 | C49: ='19_Optimasi_10Tahun'!C7 -> 1.5050791e+10 | D49: ='19_Optimasi_10Tahun'!D7 -> -9.0348962e+08 | E49: Seluruh investasi T0–T10
A50: OPEX 10 tahun | B50: ='19_Optimasi_10Tahun'!B8 -> 4.8615696e+10 | C50: ='19_Optimasi_10Tahun'!C8 -> 4.6681381e+10 | D50: ='19_Optimasi_10Tahun'!D8 -> -1.9343152e+09 | E50: Biaya operasi setelah efisiensi
A51: Pendapatan 10 tahun | B51: ='19_Optimasi_10Tahun'!B9 -> 6.1685534e+10 | C51: ='19_Optimasi_10Tahun'!C9 -> 6.3070169e+10 | D51: ='19_Optimasi_10Tahun'!D9 -> 1.3846348e+09 | E51: Termasuk diversifikasi konservatif
A52: Arus kas kumulatif T10 | B52: ='19_Optimasi_10Tahun'!B10 -> -2.8844428e+09 | C52: ='19_Optimasi_10Tahun'!C10 -> 1.3379968e+09 | D52: ='19_Optimasi_10Tahun'!D10 -> 4.2224396e+09 | E52: Untung/rugi nominal sampai T10
A53: NPV 12% | B53: ='19_Optimasi_10Tahun'!B11 -> -1.1872485e+10 | C53: ='19_Optimasi_10Tahun'!C11 -> -9.4097266e+09 | D53: ='19_Optimasi_10Tahun'!D11 -> 2.4627582e+09 | E53: Nilai waktu uang
A54: IRR | B54: ='19_Optimasi_10Tahun'!B12 -> -0.019621504 | C54: ='19_Optimasi_10Tahun'!C12 -> 0.009061345 | D54: ='19_Optimasi_10Tahun'!D12 -> 0.028682849 | E54: Tingkat imbal hasil
A55: Pendanaan puncak | B55: ='19_Optimasi_10Tahun'!B13 -> 1.9597093e+10 | C55: ='19_Optimasi_10Tahun'!C13 -> 1.7456171e+10 | D55: ='19_Optimasi_10Tahun'!D13 -> -2.1409218e+09 | E55: Kebutuhan modal maksimum
A56: Tahun pengembalian | B56: ='19_Optimasi_10Tahun'!B14 -> Beyond Y10 | C56: ='19_Optimasi_10Tahun'!C14 -> 10 | D56: ='19_Optimasi_10Tahun'!D14 -> - | E56: Kumulatif pertama ≥0
A58: Uji ketahanan laba — tidak semua pendapatan program boleh dianggap bankable
A59: Kasus uji | B59: Kas kumulatif T10 | C59: Margin | D59: Status | E59: Implikasi
A60: Expected-value | B60: ='19_Optimasi_10Tahun'!B48 -> 1.3379968e+09 | C60: ='19_Optimasi_10Tahun'!C48 -> 0.021214415 | D60: ='19_Optimasi_10Tahun'!D48 -> POSITIF | E60: Memakai expected funding dan karbon setelah haircut
A61: Tanpa hibah masyarakat & karbon | B61: ='19_Optimasi_10Tahun'!B49 -> 1.270818e+09 | C61: ='19_Optimasi_10Tahun'!C49 -> 0.020149273 | D61: ='19_Optimasi_10Tahun'!D49 -> POSITIF | E61: Layak dibaca sebelum award/MRV
A62: Tanpa hibah, karbon & efisiensi fasilitas | B62: ='19_Optimasi_10Tahun'!B50 -> 1.045818e+09 | C62: ='19_Optimasi_10Tahun'!C50 -> 0.016581818 | D62: ='19_Optimasi_10Tahun'!D50 -> POSITIF | E62: Tidak mengakui penghematan BOQ rendah-keyakinan
A63: Core tanpa diversifikasi kelapa grade-B | B63: ='19_Optimasi_10Tahun'!B51 -> 3.8769409e+08 | C63: ='19_Optimasi_10Tahun'!C51 -> 0.0061470279 | D63: ='19_Optimasi_10Tahun'!D51 -> POSITIF | E63: Kebun tanpa ketergantungan pengolahan grade-B
A65: Catatan bankable: nanas, Pueraria/Arachis, kompos, kacang tanah, dan produk kelapa wajib melalui demplot, quotation, serta offtake. Laba nominal positif bukan berarti NPV positif; target buffer 5% masih memerlukan tambahan efisiensi atau margin yang dapat dibuktikan.

Sheet 02_Assumptions
A1: Pusat Penggerak dan Asumsi Model
A2: Simulasi utama cukup dengan C6 (luas kebun) dan C8 (jumlah lokasi). Harga, upah, tarif, dosis, dan produktivitas tetap dapat diedit secara opsional; populasi, volume, HOK, kru, biaya, produksi, dan arus kas dihitung otomatis.
A4: A. Proyek, finansial, dan skenario
A5: Kelompok | B5: Variabel | C5: Nilai | D5: Satuan | E5: ID sumber | F5: Tingkat keyakinan | G5: Catatan
A6: Proyek | B6: Luas bruto | C6: 100 | D6: ha | E6: USR | F6: High | G6: PENGGERAK UTAMA — ubah luas di sini
A7: Proyek | B7: Proporsi areal efektif | C7: 0.88 | D7: % bruto | E7: ASM | F7: Medium | G7: Standar desain; tidak perlu diubah untuk simulasi luas/lokasi
A8: Skenario | B8: Jumlah lokasi terpilih | C8: 1 | D8: site | E8: USR | F8: High | G8: PENGGERAK UTAMA — pilih 1 sampai 4 lokasi
A9: Tenaga kerja | B9: Hari kerja per bulan | C9: 25 | D9: hari | E9: USR | F9: High | G9: Dapat diubah menjadi 22
A10: Waktu | B10: Tahun dasar harga | C10: 2026 | D10: tahun | E10: SYS | F10: High | G10: Nominal 2026
A11: Keuangan | B11: Inflasi biaya | C11: 0.04 | D11: %/tahun | E11: ASM | F11: Medium | G11: Asumsi perencanaan; bukan forecast resmi
A12: Keuangan | B12: Eskalasi harga jual | C12: 0.03 | D12: %/tahun | E12: ASM | F12: Low | G12: Konservatif; kontrak offtake tetap diperlukan
A13: Keuangan | B13: Tingkat diskonto | C13: 0.12 | D13: % nominal | E13: ASM | F13: Medium | G13: Untuk NPV proyek tanpa utang
A14: Keuangan | B14: Cadangan CAPEX | C14: 0.1 | D14: % subtotal | E14: ASM | F14: Medium | G14: Tidak diterapkan pada akuisisi lahan
A15: Keuangan | B15: Cadangan OPEX | C15: 0.05 | D15: % subtotal | E15: ASM | F15: Medium | G15: Cadangan operasional
A16: Lahan | B16: Harga akuisisi/sewa lahan | C16: 0 | D16: Rp/ha | E16: OPEN | F16: Low | G16: Dikosongkan: wajib diisi setelah title & valuation due diligence
A17: Organik | B17: Lama fase input sintetis | C17: 2 | D17: tahun | E17: USR | F17: Medium | G17: Urea/ZA/SP-36/KCl/NPK dan pestisida sintetis berhenti setelah tahun ini
... A19: Pendapatan | B19: Premi harga organik | C19: 0 | D19: % | E19: ASM | F19: Low | G19: Tidak diasumsikan sebelum ada kontrak pembeli
A22: B. Matriks tanam agroforestri terpadu — tanpa blok komoditas
A23: Kelompok | B23: Variabel | C23: Nilai | D23: Satuan | E23: ID sumber | F23: Tingkat keyakinan | G23: Catatan
A24: Area | B24: Areal agroforestri efektif | C24: =$C$6*$C$7 -> 88 | D24: ha efektif | E24: RUMUS | F24: Tinggi | G24: Seluruh tanaman utama dan tanaman sela berada pada matriks areal yang sama
A25: Area | B25: Jalan, sempadan, sarana, dan area non-tanam | C25: =$C$6-$C$24 -> 12 | D25: ha | E25: RUMUS | F25: Tinggi | G25: Luas bruto dikurangi areal agroforestri efektif
A26: Kerapatan | B26: Kelapa genjah terpadu | C26: 83 | D26: pohon/ha efektif | E26: DES | F26: Sedang | G26: Tersebar dalam lorong mengikuti kontur dan ruang tajuk dewasa
A27: Kerapatan | B27: Durian okulasi terpadu | C27: 30 | D27: pohon/ha efektif | E27: DES | F27: Sedang | G27: Campuran varietas untuk penyerbukan dan sebaran risiko
A28: Kerapatan | B28: Pisang awal terpadu | C28: 500 | D28: rumpun/ha efektif | E28: S02 | F28: Sedang | G28: Dikurangi bertahap ketika tajuk permanen menutup
A29: Kerapatan | B29: Gamal terpadu | C29: 150 | D29: stek/ha efektif | E29: DES | F29: Sedang | G29: Pagar hidup, biomassa, dan pengikat nitrogen
A30: Kerapatan | B30: Indigofera terpadu | C30: 300 | D30: bibit/ha efektif | E30: DES | F30: Sedang | G30: Biomassa dan habitat; perlu pemangkasan
A31: Kerapatan | B31: Serai wangi terpadu | C31: 400 | D31: anakan/ha efektif | E31: DES | F31: Sedang | G31: Strip kontur dan tepi; bukan jaminan pengendalian hama
A32: Ekologi | B32: Proporsi penutup tanah hidup | C32: 0.65 | D32: % areal efektif | E32: DES | F32: Rendah | G32: Arachis, kacang tunggak, Crotalaria atau campuran setempat
A33: Ekologi | B33: Proporsi strip biodiversitas | C33: 0.02 | D33: % areal efektif | E33: DES | F33: Rendah | G33: Tanaman berbunga bertahap di lorong dan margin
A34: Pengadaan | B34: Cadangan bibit dan sulaman | C34: 0.1 | D34: % kebutuhan | E34: S13 | F34: Sedang | G34: Jumlah dibeli di atas populasi lapangan
A35: Desain | B35: Porsi lorong untuk opsi tanaman sela komersial | C35: 0.1 | D35: % areal efektif | E35: DES | F35: Rendah | G35: Nanas/komoditas tambahan hanya ditempatkan pada lorong yang cukup cahaya
A38: C. Survival, marketable yield, dan harga jual
A39: Kelompok | B39: Input | C39: Nilai | D39: Unit | E39: Source ID | F39: Confidence | G39: Catatan
A40: Survival | B40: Kelapa setelah sulaman | C40: 0.95 | D40: % | E40: ASM | F40: Medium | G40: Target sesudah gap filling tahun pertama
A41: Survival | B41: Durian setelah sulaman | C41: 0.9 | D41: % | E41: ASM | F41: Medium | G41: Drainase dan Phytophthora menentukan
A42: Survival | B42: Pisang | C42: 0.92 | D42: % | E42: ASM | F42: Medium | G42: Bibit kultur jaringan + biosecurity
A43: Packout | B43: Kelapa marketable | C43: 0.9 | D43: % | E43: ASM | F43: Low | G43: Setelah sortasi
A44: Packout | B44: Durian marketable | C44: 0.85 | D44: % | E44: ASM | F44: Low | G44: Gradeable fruit
A45: Packout | B45: Pisang marketable | C45: 0.85 | D45: % | E45: ASM | F45: Low | G45: Reject, damage, size loss
A46: Price | B46: Harga kelapa farmgate | C46: 3000 | D46: Rp/butir | E46: S04 | F46: Medium | G46: Tanpa premium kelapa aromatik
A47: Price | B47: Harga durian farmgate | C47: 35000 | D47: Rp/kg | E47: S06 | F47: Low | G47: Base konservatif; kualitas dan musim sangat menentukan
A48: Price | B48: Harga pisang farmgate | C48: 6000 | D48: Rp/kg | E48: S05 | F48: Medium | G48: Benchmark Cavendish di tingkat kebun
A51: D. Harga bibit, tenaga kerja, dan payroll
A52: Kelompok | B52: Input | C52: Nilai | D52: Unit | E52: Source ID | F52: Confidence | G52: Catatan
A53: Seedling | B53: Bibit kelapa genjah bersertifikat | C53: 65000 | D53: Rp/bibit | E53: S13/S15 | F53: Low | G53: Allowance bulk; wajib quotation dan verifikasi varietas
A54: Seedling | B54: Bibit durian okulasi/grafting | C54: 75000 | D54: Rp/bibit | E54: S15 | F54: Low | G54: Varietas lokal unggul/Bawor; certified source
A55: Seedling | B55: Pisang kultur jaringan | C55: 15000 | D55: Rp/bibit | E55: S16 | F55: Medium | G55: Disease-free batch + acclimatization
A56: Seedling | B56: Stek/bibit gamal | C56: 2500 | D56: Rp/unit | E56: S15 | F56: Medium | G56: Bulk estimate
A57: Seedling | B57: Bibit Indigofera | C57: 3000 | D57: Rp/unit | E57: S15 | F57: Medium | G57: Bulk estimate
A58: Seedling | B58: Anakan serai wangi | C58: 1500 | D58: Rp/unit | E58: S15 | F58: Low | G58: Bulk nursery allowance
A59: Ecology | B59: Cover crop & insectary strip | C59: 1200000 | D59: Rp/ha net | E59: ASM | F59: Low | G59: Arachis/cowpea/Crotalaria/flowering strips
A60: Labor | B60: Upah HOK umum (loaded) | C60: 120000 | D60: Rp/HOK | E60: S07 | F60: Medium | G60: UMK/25 hari + THR/BPJS/alat makan allowance
A61: Labor | B61: Upah HOK terampil | C61: 180000 | D61: Rp/HOK | E61: ASM | F61: Low | G61: Operator, graft handling, survey assistant
A62: Labor | B62: UMK Banyumas 2026 | C62: 2474599 | D62: Rp/bulan | E62: S07 | F62: High | G62: Official decree
A63: Payroll | B63: Beban THR/BPJS/benefit | C63: 0.15 | D63: % salary | E63: ASM | F63: Medium | G63: Planning allowance
A66: E. Harga agri-input (delivered to farm)
A67: Kelompok | B67: Input | C67: Nilai | D67: Unit | E67: Source ID | F67: Confidence | G67: Catatan
A68: Fertilizer | B68: Urea non-subsidi | C68: 8000 | D68: Rp/kg | E68: S10 | F68: Low | G68: Delivered allowance; procure by tender
A69: Fertilizer | B69: ZA non-subsidi | C69: 5000 | D69: Rp/kg | E69: S10 | F69: Low | G69: Delivered allowance
A70: Fertilizer | B70: SP-36 non-subsidi | C70: 10000 | D70: Rp/kg | E70: S10 | F70: Low | G70: Retail benchmark; bulk quote may differ
A71: Fertilizer | B71: KCl/MOP | C71: 8000 | D71: Rp/kg | E71: S10 | F71: Low | G71: Delivered allowance
A72: Fertilizer | B72: Phonska/NPK 15-15-15 | C72: 10000 | D72: Rp/kg | E72: S10 | F72: Low | G72: Non-subsidized
A73: Organic | B73: Kompos matang | C73: 1000 | D73: Rp/kg | E73: S11 | F73: Low | G73: Rp1,000,000/t delivered
A74: Organic | B74: Pupuk kandang terfermentasi | C74: 900 | D74: Rp/kg | E74: S11 | F74: Low | G74: Bulk only; verify maturity/pathogen
A75: Amendment | B75: Dolomit | C75: 1500 | D75: Rp/kg | E75: ASM | F75: Low | G75: Only after lime requirement test
A76: Organic | B76: Rock phosphate | C76: 3000 | D76: Rp/kg | E76: ASM | F76: Low | G76: Must be accepted by LSO
A77: Organic | B77: K/Mg mineral input approved | C77: 8000 | D77: Rp/kg | E77: ASM | F77: Low | G77: Final product only with LSO approval
A78: Biological | B78: Trichoderma/Gliocladium | C78: 35000 | D78: Rp/kg | E78: S02 | F78: Low | G78: Cultured carrier/compost formulation
A79: Biological | B79: Beauveria/Metarhizium | C79: 120000 | D79: Rp/kg | E79: ASM | F79: Low | G79: Bioinsecticide; viable CFU must be specified
... A88: Chemical | B88: Registered insecticide contingency | C88: 300000 | D88: Rp/L | E88: ASM | F88: Low | G88: Only diagnosed, registered, label-compliant; transition years
A91: F. Harga satuan survei, infrastruktur, dan operasi
A92: Kelompok | B92: Input | C92: Nilai | D92: Unit | E92: Source ID | F92: Confidence | G92: Catatan
A93: Survey | B93: Drone orthomosaic | C93: 250000 | D93: Rp/ha | E93: S08 | F93: Medium | G93: 100 ha price benchmark
A94: Survey | B94: Boundary/topo/hydrology field survey | C94: 350000 | D94: Rp/ha | E94: ASM | F94: Low | G94: Allowance; scope and accuracy to quote
A95: Lab | B95: Comprehensive soil analysis | C95: 800000 | D95: Rp/sample | E95: S09 | F95: Medium | G95: Composite package plus preparation/freight
A96: Lab | B96: Soil sampling density | C96: 2.5 | D96: ha/sample | E96: ASM | F96: Medium | G96: 40 composites for one site; higher for split sites
A97: Land prep | B97: Selective clearing equipment/contractor | C97: 6000000 | D97: Rp/ha | E97: S13 | F97: Low | G97: Zero burning; manual HOK calculated separately
A98: Road | B98: Main/collection road | C98: 350000 | D98: Rp/m | E98: ASM | F98: Low | G98: Graded & compacted; geotech quote required
A99: Road | B99: Field track | C99: 120000 | D99: Rp/m | E99: ASM | F99: Low | G99: All-weather standard not assumed
A100: Drainage | B100: Field drain | C100: 45000 | D100: Rp/m | E100: ASM | F100: Low | G100: Final length from hydrology design
A101: Boundary | B101: Fence/live boundary | C101: 75000 | D101: Rp/m | E101: ASM | F101: Low | G101: Single square 100 ha perimeter ~4 km
A102: Drainage | B102: Culvert/cross-drain | C102: 12000000 | D102: Rp/unit | E102: ASM | F102: Low | G102: Installed allowance
A103: Facility | B103: Basecamp/office | C103: 350000000 | D103: Rp/site | E103: ASM | F103: Low | G103: Modular; four sites duplicate facilities
A104: Facility | B104: Nursery/warehouse | C104: 250000000 | D104: Rp/site | E104: ASM | F104: Low | G104: Acclimatization and storage
... A118: Monitoring | B118: Annual GIS/drone monitoring | C118: 150000 | D118: Rp/ha | E118: S08 | F118: Medium | G118: Orthomosaic/field verification allowance
A121: G. Kurva hasil dan populasi pisang yang dipertahankan
A122: Ukuran | B122: T1 | C122: T2 | D122: T3 | E122: T4 | F122: T5 | G122: T6 | H122: T7 | I122: T8 | J122: T9 | K122: T10
A123: Pisang: faktor rumpun dipertahankan | B123: 1 | C123: 0.9 | D123: 0.7 | E123: 0.45 | F123: 0.25 | G123: 0.15 | H123: 0.1 | I123: 0.1 | J123: 0.1 | K123: 0.1
A124: Pisang: kg layak jual/rumpun | B124: 18 | C124: 20 | D124: 20 | E124: 19 | F124: 18 | G124: 18 | H124: 18 | I124: 18 | J124: 18 | K124: 18
A125: Kelapa: butir/pohon | B125: 0 | C125: 0 | D125: 15 | E125: 35 | F125: 60 | G125: 80 | H125: 100 | I125: 110 | J125: 110 | K125: 110
A126: Durian okulasi: kg/pohon | B126: 0 | C126: 0 | D126: 0 | E126: 0 | F126: 10 | G126: 25 | H126: 45 | I126: 65 | J126: 85 | K126: 100
A129: H. Dosis pupuk per tanaman — input formula
A130: Dosis (kg/tanaman/tahun) | B130: T1 | C130: T2 | D130: T3 | E130: T4 | F130: T5 | G130: T6 | H130: T7 | I130: T8 | J130: T9 | K130: T10
A131: Pisang Urea | B131: 0.233 | C131: 0.233 | D131: 0.233 | E131: 0.233 | F131: 0.233 | G131: 0.233 | H131: 0.233 | I131: 0.233 | J131: 0.233 | K131: 0.233
A132: Pisang SP-36 | B132: 0.1 | C132: 0.1 | D132: 0.1 | E132: 0.1 | F132: 0.1 | G132: 0.1 | H132: 0.1 | I132: 0.1 | J132: 0.1 | K132: 0.1
A133: Pisang KCl | B133: 0.1 | C133: 0.1 | D133: 0.1 | E133: 0.1 | F133: 0.1 | G133: 0.1 | H133: 0.1 | I133: 0.1 | J133: 0.1 | K133: 0.1
A134: Kelapa Urea | B134: 0.25 | C134: 0.35 | D134: 0 | E134: 0 | F134: 0 | G134: 0 | H134: 0 | I134: 0 | J134: 0 | K134: 0
A135: Kelapa ZA | B135: 0.15 | C135: 0.2 | D135: 0 | E135: 0 | F135: 0 | G135: 0 | H135: 0 | I135: 0 | J135: 0 | K135: 0
A136: Kelapa SP-36 | B136: 0.2 | C136: 0.25 | D136: 0 | E136: 0 | F136: 0 | G136: 0 | H136: 0 | I136: 0 | J136: 0 | K136: 0
A137: Kelapa KCl | B137: 0.25 | C137: 0.35 | D137: 0 | E137: 0 | F137: 0 | G137: 0 | H137: 0 | I137: 0 | J137: 0 | K137: 0
...

Sheet 03_Land_Screening
A1: Seleksi Lahan dan Gerbang Kesiapan
A2: Digunakan sebelum pembukaan lahan untuk membandingkan calon lokasi berdasarkan bukti legal, sosial, lingkungan, tanah, air, akses, penyakit, dan pasar. Gerbang Tidak Layak selalu mengesampingkan skor total yang terlihat menarik.
A4: A. Skor seleksi berbobot
A5: Kriteria | B5: Bobot | C5: Minimum | D5: Bukti wajib | E5: Calon A | F5: Calon B | G5: Calon C | H5: Calon D | I5: Penanggung jawab | J5: Waktu | K5: Hubungan tidak layak
A6: Legal title, overlap, land-use conformity | B6: 0.2 | C6: 4 | D6: Certificates, spatial plan, dispute/community check | I6: Legal | J6: W1-2 | K6: Any unresolved conflict = No-Go
A7: E&S, protected area, HCV/forest status | B7: 0.15 | C7: 4 | D7: Official maps + field HCV/social verification | I7: ESG | J7: W1-3 | K7: Natural forest/protected/HCV clearing = No-Go
A8: Soil depth, texture, pH, CEC, organic C | B8: 0.15 | C8: 3 | D8: 40+ composite samples, pits, laboratory | I8: Agronomist | J8: W2-3 | K8: Severe rooting constraint may be No-Go
A9: Drainage, flood, water table | B9: 0.1 | C9: 4 | D9: Topography, pits, flood history, hydrology | I9: Engineer | J9: W2-3 | K9: Chronic flood/waterlogging = No-Go
A10: Dry-season water reliability | B10: 0.1 | C10: 4 | D10: Source yield, rights, dry-season test, water quality | I10: Engineer | J10: W2-3 | K10: No reliable establishment water = No-Go
A11: Slope, erosion, mechanization | B11: 0.08 | C11: 3 | D11: DEM/topo, slope classes, access | I11: GIS/Engineer | J11: W2-3 | K11: >25% on material area = reject/very limited
A12: Banana disease history/biosecurity | B12: 0.07 | C12: 4 | D12: Fusarium/blood disease history, soil movement risk | I12: Plant Health | J12: W2-3 | K12: Known severe history without isolation = No-Go
A13: Access, power, labor, logistics | B13: 0.06 | C13: 3 | D13: Road seasonality, distance, labor survey | I13: Ops | J13: W1-3 | K13: May materially change CAPEX/OPEX
A14: Market/offtake and postharvest route | B14: 0.05 | C14: 3 | D14: Buyer interviews, grades, transport loss | I14: Commercial | J14: W2-4 | K14: Low score requires contracted solution
A15: Contiguity/expansion and security | B15: 0.04 | C15: 3 | D15: Boundary survey, neighboring uses, theft/fire risk | I15: Ops | J15: W1-3 | K15: Split sites duplicate cost
A16: Skor kesiapan berbobot | E16: =IF(COUNT(E6:E15)=10,SUMPRODUCT($B$6:$B$15,E6:E15)/5,"Input scores") -> Input scores | F16: =IF(COUNT(F6:F15)=10,SUMPRODUCT($B$6:$B$15,F6:F15)/5,"Input scores") -> Input scores | G16: =IF(COUNT(G6:G15)=10,SUMPRODUCT($B$6:$B$15,G6:G15)/5,"Input scores") -> Input scores | H16: =IF(COUNT(H6:H15)=10,SUMPRODUCT($B$6:$B$15,H6:H15)/5,"Input scores") -> Input scores
A19: B. Gerbang Tidak Layak yang wajib
A20: Gerbang | B20: Tolak/hentikan jika | C20: Bukti | D20: Mitigasi diperbolehkan? | E20: Pemilik keputusan | F20: Sebelum biaya | G20: Status | H20: Catatan
A21: Tenure | B21: Unresolved ownership, overlap, encumbrance, community conflict | C21: Legal report + consultation | D21: No, resolve first | E21: Investment committee | F21: Before survey | G21: OPEN
A22: Forest/HCV | B22: Natural forest, protected area, critical habitat conversion | C22: Official + HCV assessment | D22: No clearing | E22: Board/ESG | F22: Before clearing | G22: OPEN
A23: Flood/drainage | B23: Chronic flood or water table incompatible with durian/banana | C23: Hydrology/topo | D23: Only if engineered and economic | E23: Agronomist/engineer | F23: Before design | G23: OPEN
A24: Water | B24: No legal/reliable dry-season source | C24: Yield/quality/right test | D24: Alternative source must be proven | E24: Ops | F24: Before planting | G24: OPEN
A25: Banana disease | B25: Severe Fusarium/blood disease history with uncontrollable pathways | C25: Plant health survey | D25: Quarantine block only if approved | E25: Plant health lead | F25: Before banana procurement | G25: OPEN
A26: Slope/erosion | B26: Material planting area >25% slope/unstable | C26: Topographic/geotech | D26: Exclude area or reject | E26: Engineer | F26: Before clearing | G26: OPEN
A29: C. Proses keputusan lahan empat minggu
A30: Minggu | B30: Aktivitas | C30: Keluaran | D30: Orang | E30: Durasi | F30: Tautan anggaran | G30: Keputusan
A31: 1 | B31: Desktop shortlist + legal data room | C31: 2-4 candidates, document gaps | D31: 4 | E31: 5 days | F31: CAPEX Assessment | G31: Shortlist
A32: 2 | B32: Reconnaissance, community, drone/boundary | C32: Orthomosaic, access, red flags | D32: 8 | E32: 5-7 days | F32: CAPEX Survey | G32: Drop clear No-Go
A33: 3 | B33: Soil, pits, infiltration, water, HCV | C33: Lab samples and field evidence | D33: 10 | E33: 5-7 days | F33: CAPEX Survey | G33: Conditional Go
A34: 4 | B34: Scoring, master concept, vendor BOQ | C34: Go/No-Go memo + negotiation cap | D34: 6 | E34: 5 days | F34: CAPEX Design | G34: Investment decision

Sheet 04_Planting_Design
A1: Desain Populasi dan Pengadaan Bibit
A2: Luas efektif dan standar kerapatan otomatis menjadi populasi, bibit, tanaman hidup, serta biaya. Untuk simulasi luas/lokasi, jangan ketik ulang angka pada sheet ini.
A4: A. Populasi lapangan dalam matriks terpadu
A5: Lapisan/area | B5: Area (ha) | C5: Kelapa/ha | D5: Kelapa | E5: Durian/ha | F5: Durian | G5: Pisang/ha | H5: Pisang | I5: Gamal | J5: Indigofera | K5: Serai wangi | L5: Nanas | M5: Penutup tanah (ha) | N5: Keterangan | O5: Aktif
A6: Agroforestri terpadu | B6: ='02_Assumptions'!$C$24 -> 88 | C6: ='02_Assumptions'!$C$26 -> 83 | D6: =$B6*$C6*'02_Assumptions'!$C$150 -> 7304 | E6: ='02_Assumptions'!$C$27 -> 30 | F6: =$B6*$E6*'02_Assumptions'!$C$151 -> 2640 | G6: ='02_Assumptions'!$C$28 -> 500 | H6: =$B6*$G6*'02_Assumptions'!$C$152 -> 44000 | I6: =$B6*'02_Assumptions'!$C$29*'02_Assumptions'!$C$153 -> 13200 | J6: =$B6*'02_Assumptions'!$C$30*'02_Assumptions'!$C$154 -> 26400 | K6: =$B6*'02_Assumptions'!$C$31*'02_Assumptions'!$C$155 -> 35200 | L6: ='17_Model_Fleksibel'!$E$6 -> 220000 | M6: ='17_Model_Fleksibel'!$E$7 -> 57.2 | N6: Semua komoditas berada pada areal yang sama | O6: 1
A7: Area non-tanam | B7: ='02_Assumptions'!$C$25 -> 12 | C7: 0 | D7: 0 | E7: 0 | F7: 0 | G7: 0 | H7: 0 | I7: 0 | J7: 0 | K7: 0 | L7: 0 | M7: 0 | N7: Jalan, sempadan, sarana, dan area lindung | O7: 0
A8: TOTAL | B8: =SUM(B6:B7) -> 100 | D8: =SUM(D6:D7) -> 7304 | F8: =SUM(F6:F7) -> 2640 | H8: =SUM(H6:H7) -> 44000 | I8: =SUM(I6:I7) -> 13200 | J8: =SUM(J6:J7) -> 26400 | K8: =SUM(K6:K7) -> 35200 | L8: =SUM(L6:L7) -> 220000 | M8: =SUM(M6:M7) -> 57.2
A11: B. Pengadaan bibit termasuk cadangan sulaman
A12: Bibit | B12: Kebutuhan lapangan | C12: Cadangan | D12: Jumlah dibeli | E12: Satuan | F12: Harga/satuan | G12: Total | H12: Catatan
A13: Kelapa genjah | B13: =$D$8 -> 7304 | C13: ='02_Assumptions'!$C$34 -> 0.1 | D13: =$B13*(1+$C13) -> 8034.4 | E13: bibit | F13: ='02_Assumptions'!$C$53 -> 65000 | G13: =$D13*$F13 -> 5.22236e+08 | H13: Varietas bersertifikat dan sesuai elevasi serta pasar
A14: Durian okulasi | B14: =$F$8 -> 2640 | C14: ='02_Assumptions'!$C$34 -> 0.1 | D14: =$B14*(1+$C14) -> 2904 | E14: bibit | F14: ='02_Assumptions'!$C$54 -> 75000 | G14: =$D14*$F14 -> 2.178e+08 | H14: Campuran varietas untuk penyerbukan dan sebaran risiko
A15: Pisang kultur jaringan | B15: =$H$8 -> 44000 | C15: ='02_Assumptions'!$C$34 -> 0.1 | D15: =$B15*(1+$C15) -> 48400 | E15: bibit | F15: ='02_Assumptions'!$C$55 -> 15000 | G15: =$D15*$F15 -> 7.26e+08 | H15: Karantina batch dan aklimatisasi
A16: Gamal | B16: =$I$8 -> 13200 | C16: ='02_Assumptions'!$C$34 -> 0.1 | D16: =$B16*(1+$C16) -> 14520 | E16: stek | F16: ='02_Assumptions'!$C$56 -> 2500 | G16: =$D16*$F16 -> 36300000 | H16: Pagar hidup dan biomassa
A17: Indigofera | B17: =$J$8 -> 26400 | C17: ='02_Assumptions'!$C$34 -> 0.1 | D17: =$B17*(1+$C17) -> 29040 | E17: bibit | F17: ='02_Assumptions'!$C$57 -> 3000 | G17: =$D17*$F17 -> 87120000 | H17: Dipangkas agar tidak menaungi
A18: Serai wangi | B18: =$K$8 -> 35200 | C18: ='02_Assumptions'!$C$34 -> 0.1 | D18: =$B18*(1+$C18) -> 38720 | E18: anakan | F18: ='02_Assumptions'!$C$58 -> 1500 | G18: =$D18*$F18 -> 58080000 | H18: Strip kontur dan batas
A19: TOTAL PENGADAAN BIBIT TERMASUK OPSI | G19: =SUM(G13:G18)+'17_Model_Fleksibel'!$I$18 -> 2.151776e+09
A22: C. Populasi hidup untuk model hasil
A23: Komoditas | B23: Populasi lapangan | C23: Survival | D23: Tanaman hidup
A24: Kelapa | B24: =D8 -> 7304 | C24: ='02_Assumptions'!$C$40 -> 0.95 | D24: =B24*C24 -> 6938.8
A25: Durian | B25: =F8 -> 2640 | C25: ='02_Assumptions'!$C$41 -> 0.9 | D25: =B25*C25 -> 2376
A26: Pisang | B26: =H8 -> 44000 | C26: ='02_Assumptions'!$C$42 -> 0.92 | D26: =B26*C26 -> 40480
A29: D. Fungsi tanaman pendukung dan aturan desain
A30: Tanaman/elemen | B30: Fungsi | C30: Posisi | D30: Pengelolaan | E30: Risiko | F30: Pendapatan dasar | G30: Keputusan | H30: Catatan
A31: Gamal (Gliricidia) | B31: Pengikat N, pagar hidup, biomassa | C31: Lorong, kontur, dan batas | D31: Pangkas 3–4 kali/tahun | E31: Kompetisi cahaya/akar | F31: 0 | G31: Masuk | H31: Tidak dianggap sebagai pestisida
A32: Indigofera | B32: Pengikat N, biomassa, habitat | C32: Lorong tersebar | D32: Pangkas dan benamkan biomassa | E32: Dapat menjadi semak | F32: 0 | G32: Masuk | H32: Potensi pakan bila ada ternak
A33: Serai wangi | B33: Strip aromatik dan pengendali erosi | C33: Tepi drainase dan kontur | D33: Panen/pangkas berkala | E33: Tidak menjamin hama hilang | F33: 0 | G33: Masuk | H33: Pendapatan nol tanpa penyulingan/offtake
A34: Arachis/kacang tunggak/Crotalaria | B34: Penutup tanah, N, pengendali erosi | C34: Lorong terbuka | D34: Rotasi; cegah lilitan pada pohon | E34: Rodensia/kompetisi | F34: 0 | G34: Masuk | H34: Campuran spesifik lokasi
A35: Strip tanaman berbunga | B35: Habitat musuh alami | C35: 1–2% margin dan lorong | D35: Penaburan bertahap | E35: Dapat menjadi inang hama | F35: 0 | G35: Masuk | H35: Pilih jenis setempat
A36: Sempadan riparian/HCV | B36: Perlindungan air dan biodiversitas | C36: Area non-tanam | D36: Tandai, pantau, tanpa pembukaan | E36: Mengurangi areal efektif | F36: 0 | G36: Wajib | H36: Termasuk dalam area non-tanam

Sheet 05_Workplan_Labor
A1: Rencana Kerja, HOK, Durasi, dan Kebutuhan Kru
A2: HOK, durasi, biaya tenaga kerja, kru rata-rata, dan kru puncak dihitung otomatis dari luas dan jumlah lokasi. Upah tetap dapat diedit pada 02_Assumptions.
A4: A. Pekerjaan Tahun 0: dari uji tuntas sampai pembentukan tanaman
A5: Tahap | B5: Aktivitas | C5: Mulai | D5: Selesai | E5: Basis | F5: Jumlah 1 lokasi | G5: Jumlah 4 lokasi | H5: HOK/unit | I5: HOK 1 lokasi | J5: HOK 4 lokasi | K5: Biaya langsung 1 lokasi | L5: Biaya langsung 4 lokasi | M5: Peralatan/catatan | N5: M1 | O5: M2 | P5: M3 | Q5: M4 | R5: M5 | S5: M6 | T5: M7 | U5: M8 | V5: M9 | W5: M10 | X5: M11 | Y5: M12 | Z5: Crew selected
A6: Assessment | B6: Desktop shortlist & GIS | C6: 1 | D6: 1 | E6: lot | F6: 1 | G6: 1 | H6: 30 | I6: =F6*H6 -> 30 | J6: =G6*H6 -> 30 | K6: =0 -> 0 | L6: =0 -> 0 | M6: Professional service | N6: =IF(AND(1>=$C6,1<=$D6),($I6+($J6-$I6)*('02_Assumptions'!$C$8-1)/3)/($D6-$C6+1),0) -> 30 | O6: =IF(AND(2>=$C6,2<=$D6),($I6+($J6-$I6)*('02_Assumptions'!$C$8-1)/3)/($D6-$C6+1),0) -> 0 | P6: =IF(AND(3>=$C6,3<=$D6),($I6+($J6-$I6)*('02_Assumptions'!$C$8-1)/3)/($D6-$C6+1),0) -> 0 | Q6: =IF(AND(4>=$C6,4<=$D6),($I6+($J6-$I6)*('02_Assumptions'!$C$8-1)/3)/($D6-$C6+1),0) -> 0 | R6: =IF(AND(5>=$C6,5<=$D6),($I6+($J6-$I6)*('02_Assumptions'!$C$8-1)/3)/($D6-$C6+1),0) -> 0 | S6: =IF(AND(6>=$C6,6<=$D6),($I6+($J6-$I6)*('02_Assumptions'!$C$8-1)/3)/($D6-$C6+1),0) -> 0 | T6: =IF(AND(7>=$C6,7<=$D6),($I6+($J6-$I6)*('02_Assumptions'!$C$8-1)/3)/($D6-$C6+1),0) -> 0 | U6: =IF(AND(8>=$C6,8<=$D6),($I6+($J6-$I6)*('02_Assumptions'!$C$8-1)/3)/($D6-$C6+1),0) -> 0 | V6: =IF(AND(9>=$C6,9<=$D6),($I6+($J6-$I6)*('02_Assumptions'!$C$8-1)/3)/($D6-$C6+1),0) -> 0 | W6: =IF(AND(10>=$C6,10<=$D6),($I6+($J6-$I6)*('02_Assumptions'!$C$8-1)/3)/($D6-$C6+1),0) -> 0 | X6: =IF(AND(11>=$C6,11<=$D6),($I6+($J6-$I6)*('02_Assumptions'!$C$8-1)/3)/($D6-$C6+1),0) -> 0 | Y6: =IF(AND(12>=$C6,12<=$D6),($I6+($J6-$I6)*('02_Assumptions'!$C$8-1)/3)/($D6-$C6+1),0) -> 0 | Z6: =(I6+(J6-I6)*('02_Assumptions'!$C$8-1)/3)/(D6-C6+1)/'02_Assumptions'!$C$9 -> 1.2
A7: Assessment | B7: Legal/tenure due diligence | C7: 1 | D7: 2 | E7: site | F7: 1 | G7: 4 | H7: 40 | I7: =F7*H7 -> 40 | J7: =G7*H7 -> 160 | K7: =0 -> 0 | L7: =0 -> 0 | M7: Legal fee in CAPEX | N7: =IF(AND(1>=$C7,1<=$D7),($I7+($J7-$I7)*('02_Assumptions'!$C$8-1)/3)/($D7-$C7+1),0) -> 20 | O7: =IF(AND(2>=$C7,2<=$D7),($I7+($J7-$I7)*('02_Assumptions'!$C$8-1)/3)/($D7-$C7+1),0) -> 20 | P7: =IF(AND(3>=$C7,3<=$D7),($I7+($J7-$I7)*('02_Assumptions'!$C$8-1)/3)/($D7-$C7+1),0) -> 0 | Q7: =IF(AND(4>=$C7,4<=$D7),($I7+($J7-$I7)*('02_Assumptions'!$C$8-1)/3)/($D7-$C7+1),0) -> 0 | R7: =IF(AND(5>=$C7,5<=$D7),($I7+($J7-$I7)*('02_Assumptions'!$C$8-1)/3)/($D7-$C7+1),0) -> 0 | S7: =IF(AND(6>=$C7,6<=$D7),($I7+($J7-$I7)*('02_Assumptions'!$C$8-1)/3)/($D7-$C7+1),0) -> 0 | T7: =IF(AND(7>=$C7,7<=$D7),($I7+($J7-$I7)*('02_Assumptions'!$C$8-1)/3)/($D7-$C7+1),0) -> 0 | U7: =IF(AND(8>=$C7,8<=$D7),($I7+($J7-$I7)*('02_Assumptions'!$C$8-1)/3)/($D7-$C7+1),0) -> 0 | V7: =IF(AND(9>=$C7,9<=$D7),($I7+($J7-$I7)*('02_Assumptions'!$C$8-1)/3)/($D7-$C7+1),0) -> 0 | W7: =IF(AND(10>=$C7,10<=$D7),($I7+($J7-$I7)*('02_Assumptions'!$C$8-1)/3)/($D7-$C7+1),0) -> 0 | X7: =IF(AND(11>=$C7,11<=$D7),($I7+($J7-$I7)*('02_Assumptions'!$C$8-1)/3)/($D7-$C7+1),0) -> 0 | Y7: =IF(AND(12>=$C7,12<=$D7),($I7+($J7-$I7)*('02_Assumptions'!$C$8-1)/3)/($D7-$C7+1),0) -> 0 | Z7: =(I7+(J7-I7)*('02_Assumptions'!$C$8-1)/3)/(D7-C7+1)/'02_Assumptions'!$C$9 -> 0.8
A8: Assessment | B8: Reconnaissance & community check | C8: 1 | D8: 2 | E8: site | F8: 1 | G8: 4 | H8: 30 | I8: =F8*H8 -> 30 | J8: =G8*H8 -> 120 | K8: =0 -> 0 | L8: =0 -> 0 | M8: Travel package in CAPEX | N8: =IF(AND(1>=$C8,1<=$D8),($I8+($J8-$I8)*('02_Assumptions'!$C$8-1)/3)/($D8-$C8+1),0) -> 15 | O8: =IF(AND(2>=$C8,2<=$D8),($I8+($J8-$I8)*('02_Assumptions'!$C$8-1)/3)/($D8-$C8+1),0) -> 15 | P8: =IF(AND(3>=$C8,3<=$D8),($I8+($J8-$I8)*('02_Assumptions'!$C$8-1)/3)/($D8-$C8+1),0) -> 0 | Q8: =IF(AND(4>=$C8,4<=$D8),($I8+($J8-$I8)*('02_Assumptions'!$C$8-1)/3)/($D8-$C8+1),0) -> 0 | R8: =IF(AND(5>=$C8,5<=$D8),($I8+($J8-$I8)*('02_Assumptions'!$C$8-1)/3)/($D8-$C8+1),0) -> 0 | S8: =IF(AND(6>=$C8,6<=$D8),($I8+($J8-$I8)*('02_Assumptions'!$C$8-1)/3)/($D8-$C8+1),0) -> 0 | T8: =IF(AND(7>=$C8,7<=$D8),($I8+($J8-$I8)*('02_Assumptions'!$C$8-1)/3)/($D8-$C8+1),0) -> 0 | U8: =IF(AND(8>=$C8,8<=$D8),($I8+($J8-$I8)*('02_Assumptions'!$C$8-1)/3)/($D8-$C8+1),0) -> 0 | V8: =IF(AND(9>=$C8,9<=$D8),($I8+($J8-$I8)*('02_Assumptions'!$C$8-1)/3)/($D8-$C8+1),0) -> 0 | W8: =IF(AND(10>=$C8,10<=$D8),($I8+($J8-$I8)*('02_Assumptions'!$C$8-1)/3)/($D8-$C8+1),0) -> 0 | X8: =IF(AND(11>=$C8,11<=$D8),($I8+($J8-$I8)*('02_Assumptions'!$C$8-1)/3)/($D8-$C8+1),0) -> 0 | Y8: =IF(AND(12>=$C8,12<=$D8),($I8+($J8-$I8)*('02_Assumptions'!$C$8-1)/3)/($D8-$C8+1),0) -> 0 | Z8: =(I8+(J8-I8)*('02_Assumptions'!$C$8-1)/3)/(D8-C8+1)/'02_Assumptions'!$C$9 -> 0.6
A9: Survey | B9: Drone/boundary/topo survey | C9: 2 | D9: 3 | E9: ha | F9: ='02_Assumptions'!$C$6 -> 100 | G9: ='02_Assumptions'!$C$6 -> 100 | H9: 0.2 | I9: =F9*H9 -> 20 | J9: =G9*H9 -> 20 | K9: =0 -> 0 | L9: =0 -> 0 | M9: Professional service | N9: =IF(AND(1>=$C9,1<=$D9),($I9+($J9-$I9)*('02_Assumptions'!$C$8-1)/3)/($D9-$C9+1),0) -> 0 | O9: =IF(AND(2>=$C9,2<=$D9),($I9+($J9-$I9)*('02_Assumptions'!$C$8-1)/3)/($D9-$C9+1),0) -> 10 | P9: =IF(AND(3>=$C9,3<=$D9),($I9+($J9-$I9)*('02_Assumptions'!$C$8-1)/3)/($D9-$C9+1),0) -> 10 | Q9: =IF(AND(4>=$C9,4<=$D9),($I9+($J9-$I9)*('02_Assumptions'!$C$8-1)/3)/($D9-$C9+1),0) -> 0 | R9: =IF(AND(5>=$C9,5<=$D9),($I9+($J9-$I9)*('02_Assumptions'!$C$8-1)/3)/($D9-$C9+1),0) -> 0 | S9: =IF(AND(6>=$C9,6<=$D9),($I9+($J9-$I9)*('02_Assumptions'!$C$8-1)/3)/($D9-$C9+1),0) -> 0 | T9: =IF(AND(7>=$C9,7<=$D9),($I9+($J9-$I9)*('02_Assumptions'!$C$8-1)/3)/($D9-$C9+1),0) -> 0 | U9: =IF(AND(8>=$C9,8<=$D9),($I9+($J9-$I9)*('02_Assumptions'!$C$8-1)/3)/($D9-$C9+1),0) -> 0 | V9: =IF(AND(9>=$C9,9<=$D9),($I9+($J9-$I9)*('02_Assumptions'!$C$8-1)/3)/($D9-$C9+1),0) -> 0 | W9: =IF(AND(10>=$C9,10<=$D9),($I9+($J9-$I9)*('02_Assumptions'!$C$8-1)/3)/($D9-$C9+1),0) -> 0 | X9: =IF(AND(11>=$C9,11<=$D9),($I9+($J9-$I9)*('02_Assumptions'!$C$8-1)/3)/($D9-$C9+1),0) -> 0 | Y9: =IF(AND(12>=$C9,12<=$D9),($I9+($J9-$I9)*('02_Assumptions'!$C$8-1)/3)/($D9-$C9+1),0) -> 0 | Z9: =(I9+(J9-I9)*('02_Assumptions'!$C$8-1)/3)/(D9-C9+1)/'02_Assumptions'!$C$9 -> 0.4
A10: Survey | B10: Soil composite sampling | C10: 2 | D10: 3 | E10: sample | F10: ='02_Assumptions'!$C$6/'02_Assumptions'!$C$96 -> 40 | G10: ='02_Assumptions'!$C$6/'02_Assumptions'!$C$96+12 -> 52 | H10: 1 | I10: =F10*H10 -> 40 | J10: =G10*H10 -> 52 | K10: =0 -> 0 | L10: =0 -> 0 | M10: Lab/survey package | N10: =IF(AND(1>=$C10,1<=$D10),($I10+($J10-$I10)*('02_Assumptions'!$C$8-1)/3)/($D10-$C10+1),0) -> 0 | O10: =IF(AND(2>=$C10,2<=$D10),($I10+($J10-$I10)*('02_Assumptions'!$C$8-1)/3)/($D10-$C10+1),0) -> 20 | P10: =IF(AND(3>=$C10,3<=$D10),($I10+($J10-$I10)*('02_Assumptions'!$C$8-1)/3)/($D10-$C10+1),0) -> 20 | Q10: =IF(AND(4>=$C10,4<=$D10),($I10+($J10-$I10)*('02_Assumptions'!$C$8-1)/3)/($D10-$C10+1),0) -> 0 | R10: =IF(AND(5>=$C10,5<=$D10),($I10+($J10-$I10)*('02_Assumptions'!$C$8-1)/3)/($D10-$C10+1),0) -> 0 | S10: =IF(AND(6>=$C10,6<=$D10),($I10+($J10-$I10)*('02_Assumptions'!$C$8-1)/3)/($D10-$C10+1),0) -> 0 | T10: =IF(AND(7>=$C10,7<=$D10),($I10+($J10-$I10)*('02_Assumptions'!$C$8-1)/3)/($D10-$C10+1),0) -> 0 | U10: =IF(AND(8>=$C10,8<=$D10),($I10+($J10-$I10)*('02_Assumptions'!$C$8-1)/3)/($D10-$C10+1),0) -> 0 | V10: =IF(AND(9>=$C10,9<=$D10),($I10+($J10-$I10)*('02_Assumptions'!$C$8-1)/3)/($D10-$C10+1),0) -> 0 | W10: =IF(AND(10>=$C10,10<=$D10),($I10+($J10-$I10)*('02_Assumptions'!$C$8-1)/3)/($D10-$C10+1),0) -> 0 | X10: =IF(AND(11>=$C10,11<=$D10),($I10+($J10-$I10)*('02_Assumptions'!$C$8-1)/3)/($D10-$C10+1),0) -> 0 | Y10: =IF(AND(12>=$C10,12<=$D10),($I10+($J10-$I10)*('02_Assumptions'!$C$8-1)/3)/($D10-$C10+1),0) -> 0 | Z10: =(I10+(J10-I10)*('02_Assumptions'!$C$8-1)/3)/(D10-C10+1)/'02_Assumptions'!$C$9 -> 0.8
A11: Safeguard | B11: E&S/HCV baseline | C11: 2 | D11: 3 | E11: site | F11: 1 | G11: 4 | H11: 60 | I11: =F11*H11 -> 60 | J11: =G11*H11 -> 240 | K11: =0 -> 0 | L11: =0 -> 0 | M11: Consultant package | N11: =IF(AND(1>=$C11,1<=$D11),($I11+($J11-$I11)*('02_Assumptions'!$C$8-1)/3)/($D11-$C11+1),0) -> 0 | O11: =IF(AND(2>=$C11,2<=$D11),($I11+($J11-$I11)*('02_Assumptions'!$C$8-1)/3)/($D11-$C11+1),0) -> 30 | P11: =IF(AND(3>=$C11,3<=$D11),($I11+($J11-$I11)*('02_Assumptions'!$C$8-1)/3)/($D11-$C11+1),0) -> 30 | Q11: =IF(AND(4>=$C11,4<=$D11),($I11+($J11-$I11)*('02_Assumptions'!$C$8-1)/3)/($D11-$C11+1),0) -> 0 | R11: =IF(AND(5>=$C11,5<=$D11),($I11+($J11-$I11)*('02_Assumptions'!$C$8-1)/3)/($D11-$C11+1),0) -> 0 | S11: =IF(AND(6>=$C11,6<=$D11),($I11+($J11-$I11)*('02_Assumptions'!$C$8-1)/3)/($D11-$C11+1),0) -> 0 | T11: =IF(AND(7>=$C11,7<=$D11),($I11+($J11-$I11)*('02_Assumptions'!$C$8-1)/3)/($D11-$C11+1),0) -> 0 | U11: =IF(AND(8>=$C11,8<=$D11),($I11+($J11-$I11)*('02_Assumptions'!$C$8-1)/3)/($D11-$C11+1),0) -> 0 | V11: =IF(AND(9>=$C11,9<=$D11),($I11+($J11-$I11)*('02_Assumptions'!$C$8-1)/3)/($D11-$C11+1),0) -> 0 | W11: =IF(AND(10>=$C11,10<=$D11),($I11+($J11-$I11)*('02_Assumptions'!$C$8-1)/3)/($D11-$C11+1),0) -> 0 | X11: =IF(AND(11>=$C11,11<=$D11),($I11+($J11-$I11)*('02_Assumptions'!$C$8-1)/3)/($D11-$C11+1),0) -> 0 | Y11: =IF(AND(12>=$C11,12<=$D11),($I11+($J11-$I11)*('02_Assumptions'!$C$8-1)/3)/($D11-$C11+1),0) -> 0 | Z11: =(I11+(J11-I11)*('02_Assumptions'!$C$8-1)/3)/(D11-C11+1)/'02_Assumptions'!$C$9 -> 1.2
A12: Land prep | B12: HCV marking & exclusion | C12: 3 | D12: 4 | E12: ha | F12: ='02_Assumptions'!$C$6 -> 100 | G12: ='02_Assumptions'!$C$6 -> 100 | H12: 2 | I12: =F12*H12 -> 200 | J12: =G12*H12 -> 200 | K12: =I12*'02_Assumptions'!$C$60 -> 24000000 | L12: =J12*'02_Assumptions'!$C$60 -> 24000000 | M12: Direct field crew | N12: =IF(AND(1>=$C12,1<=$D12),($I12+($J12-$I12)*('02_Assumptions'!$C$8-1)/3)/($D12-$C12+1),0) -> 0 | O12: =IF(AND(2>=$C12,2<=$D12),($I12+($J12-$I12)*('02_Assumptions'!$C$8-1)/3)/($D12-$C12+1),0) -> 0 | P12: =IF(AND(3>=$C12,3<=$D12),($I12+($J12-$I12)*('02_Assumptions'!$C$8-1)/3)/($D12-$C12+1),0) -> 100 | Q12: =IF(AND(4>=$C12,4<=$D12),($I12+($J12-$I12)*('02_Assumptions'!$C$8-1)/3)/($D12-$C12+1),0) -> 100 | R12: =IF(AND(5>=$C12,5<=$D12),($I12+($J12-$I12)*('02_Assumptions'!$C$8-1)/3)/($D12-$C12+1),0) -> 0 | S12: =IF(AND(6>=$C12,6<=$D12),($I12+($J12-$I12)*('02_Assumptions'!$C$8-1)/3)/($D12-$C12+1),0) -> 0 | T12: =IF(AND(7>=$C12,7<=$D12),($I12+($J12-$I12)*('02_Assumptions'!$C$8-1)/3)/($D12-$C12+1),0) -> 0 | U12: =IF(AND(8>=$C12,8<=$D12),($I12+($J12-$I12)*('02_Assumptions'!$C$8-1)/3)/($D12-$C12+1),0) -> 0 | V12: =IF(AND(9>=$C12,9<=$D12),($I12+($J12-$I12)*('02_Assumptions'!$C$8-1)/3)/($D12-$C12+1),0) -> 0 | W12: =IF(AND(10>=$C12,10<=$D12),($I12+($J12-$I12)*('02_Assumptions'!$C$8-1)/3)/($D12-$C12+1),0) -> 0 | X12: =IF(AND(11>=$C12,11<=$D12),($I12+($J12-$I12)*('02_Assumptions'!$C$8-1)/3)/($D12-$C12+1),0) -> 0 | Y12: =IF(AND(12>=$C12,12<=$D12),($I12+($J12-$I12)*('02_Assumptions'!$C$8-1)/3)/($D12-$C12+1),0) -> 0 | Z12: =(I12+(J12-I12)*('02_Assumptions'!$C$8-1)/3)/(D12-C12+1)/'02_Assumptions'!$C$9 -> 4
A13: Land prep | B13: Selective zero-burn clearing | C13: 4 | D13: 6 | E13: ha | F13: ='02_Assumptions'!$C$6 -> 100 | G13: ='02_Assumptions'!$C$6 -> 100 | H13: 18 | I13: =F13*H13 -> 1800 | J13: =G13*H13 -> 1800 | K13: =I13*'02_Assumptions'!$C$60 -> 216000000 | L13: =J13*'02_Assumptions'!$C$60 -> 216000000 | M13: Manual crew; machines contracted separately | N13: =IF(AND(1>=$C13,1<=$D13),($I13+($J13-$I13)*('02_Assumptions'!$C$8-1)/3)/($D13-$C13+1),0) -> 0 | O13: =IF(AND(2>=$C13,2<=$D13),($I13+($J13-$I13)*('02_Assumptions'!$C$8-1)/3)/($D13-$C13+1),0) -> 0 | P13: =IF(AND(3>=$C13,3<=$D13),($I13+($J13-$I13)*('02_Assumptions'!$C$8-1)/3)/($D13-$C13+1),0) -> 0 | Q13: =IF(AND(4>=$C13,4<=$D13),($I13+($J13-$I13)*('02_Assumptions'!$C$8-1)/3)/($D13-$C13+1),0) -> 600 | R13: =IF(AND(5>=$C13,5<=$D13),($I13+($J13-$I13)*('02_Assumptions'!$C$8-1)/3)/($D13-$C13+1),0) -> 600 | S13: =IF(AND(6>=$C13,6<=$D13),($I13+($J13-$I13)*('02_Assumptions'!$C$8-1)/3)/($D13-$C13+1),0) -> 600 | T13: =IF(AND(7>=$C13,7<=$D13),($I13+($J13-$I13)*('02_Assumptions'!$C$8-1)/3)/($D13-$C13+1),0) -> 0 | U13: =IF(AND(8>=$C13,8<=$D13),($I13+($J13-$I13)*('02_Assumptions'!$C$8-1)/3)/($D13-$C13+1),0) -> 0 | V13: =IF(AND(9>=$C13,9<=$D13),($I13+($J13-$I13)*('02_Assumptions'!$C$8-1)/3)/($D13-$C13+1),0) -> 0 | W13: =IF(AND(10>=$C13,10<=$D13),($I13+($J13-$I13)*('02_Assumptions'!$C$8-1)/3)/($D13-$C13+1),0) -> 0 | X13: =IF(AND(11>=$C13,11<=$D13),($I13+($J13-$I13)*('02_Assumptions'!$C$8-1)/3)/($D13-$C13+1),0) -> 0 | Y13: =IF(AND(12>=$C13,12<=$D13),($I13+($J13-$I13)*('02_Assumptions'!$C$8-1)/3)/($D13-$C13+1),0) -> 0 | Z13: =(I13+(J13-I13)*('02_Assumptions'!$C$8-1)/3)/(D13-C13+1)/'02_Assumptions'!$C$9 -> 24
A14: Land prep | B14: Biomass chipping/stacking/mulch | C14: 4 | D14: 7 | E14: ha | F14: ='02_Assumptions'!$C$6 -> 100 | G14: ='02_Assumptions'!$C$6 -> 100 | H14: 8 | I14: =F14*H14 -> 800 | J14: =G14*H14 -> 800 | K14: =I14*'02_Assumptions'!$C$60 -> 96000000 | L14: =J14*'02_Assumptions'!$C$60 -> 96000000 | M14: No burning | N14: =IF(AND(1>=$C14,1<=$D14),($I14+($J14-$I14)*('02_Assumptions'!$C$8-1)/3)/($D14-$C14+1),0) -> 0 | O14: =IF(AND(2>=$C14,2<=$D14),($I14+($J14-$I14)*('02_Assumptions'!$C$8-1)/3)/($D14-$C14+1),0) -> 0 | P14: =IF(AND(3>=$C14,3<=$D14),($I14+($J14-$I14)*('02_Assumptions'!$C$8-1)/3)/($D14-$C14+1),0) -> 0 | Q14: =IF(AND(4>=$C14,4<=$D14),($I14+($J14-$I14)*('02_Assumptions'!$C$8-1)/3)/($D14-$C14+1),0) -> 200 | R14: =IF(AND(5>=$C14,5<=$D14),($I14+($J14-$I14)*('02_Assumptions'!$C$8-1)/3)/($D14-$C14+1),0) -> 200 | S14: =IF(AND(6>=$C14,6<=$D14),($I14+($J14-$I14)*('02_Assumptions'!$C$8-1)/3)/($D14-$C14+1),0) -> 200 | T14: =IF(AND(7>=$C14,7<=$D14),($I14+($J14-$I14)*('02_Assumptions'!$C$8-1)/3)/($D14-$C14+1),0) -> 200 | U14: =IF(AND(8>=$C14,8<=$D14),($I14+($J14-$I14)*('02_Assumptions'!$C$8-1)/3)/($D14-$C14+1),0) -> 0 | V14: =IF(AND(9>=$C14,9<=$D14),($I14+($J14-$I14)*('02_Assumptions'!$C$8-1)/3)/($D14-$C14+1),0) -> 0 | W14: =IF(AND(10>=$C14,10<=$D14),($I14+($J14-$I14)*('02_Assumptions'!$C$8-1)/3)/($D14-$C14+1),0) -> 0 | X14: =IF(AND(11>=$C14,11<=$D14),($I14+($J14-$I14)*('02_Assumptions'!$C$8-1)/3)/($D14-$C14+1),0) -> 0 | Y14: =IF(AND(12>=$C14,12<=$D14),($I14+($J14-$I14)*('02_Assumptions'!$C$8-1)/3)/($D14-$C14+1),0) -> 0 | Z14: =(I14+(J14-I14)*('02_Assumptions'!$C$8-1)/3)/(D14-C14+1)/'02_Assumptions'!$C$9 -> 8
A15: Layout | B15: Staking rows/contours | C15: 5 | D15: 7 | E15: ha net | F15: ='02_Assumptions'!$C$6*'02_Assumptions'!$C$7 -> 88 | G15: ='02_Assumptions'!$C$6*'02_Assumptions'!$C$7 -> 88 | H15: 5 | I15: =F15*H15 -> 440 | J15: =G15*H15 -> 440 | K15: =I15*'02_Assumptions'!$C$60 -> 52800000 | L15: =J15*'02_Assumptions'!$C$60 -> 52800000 | M15: Survey pegs/rope | N15: =IF(AND(1>=$C15,1<=$D15),($I15+($J15-$I15)*('02_Assumptions'!$C$8-1)/3)/($D15-$C15+1),0) -> 0 | O15: =IF(AND(2>=$C15,2<=$D15),($I15+($J15-$I15)*('02_Assumptions'!$C$8-1)/3)/($D15-$C15+1),0) -> 0 | P15: =IF(AND(3>=$C15,3<=$D15),($I15+($J15-$I15)*('02_Assumptions'!$C$8-1)/3)/($D15-$C15+1),0) -> 0 | Q15: =IF(AND(4>=$C15,4<=$D15),($I15+($J15-$I15)*('02_Assumptions'!$C$8-1)/3)/($D15-$C15+1),0) -> 0 | R15: =IF(AND(5>=$C15,5<=$D15),($I15+($J15-$I15)*('02_Assumptions'!$C$8-1)/3)/($D15-$C15+1),0) -> 146.66667 | S15: =IF(AND(6>=$C15,6<=$D15),($I15+($J15-$I15)*('02_Assumptions'!$C$8-1)/3)/($D15-$C15+1),0) -> 146.66667 | T15: =IF(AND(7>=$C15,7<=$D15),($I15+($J15-$I15)*('02_Assumptions'!$C$8-1)/3)/($D15-$C15+1),0) -> 146.66667 | U15: =IF(AND(8>=$C15,8<=$D15),($I15+($J15-$I15)*('02_Assumptions'!$C$8-1)/3)/($D15-$C15+1),0) -> 0 | V15: =IF(AND(9>=$C15,9<=$D15),($I15+($J15-$I15)*('02_Assumptions'!$C$8-1)/3)/($D15-$C15+1),0) -> 0 | W15: =IF(AND(10>=$C15,10<=$D15),($I15+($J15-$I15)*('02_Assumptions'!$C$8-1)/3)/($D15-$C15+1),0) -> 0 | X15: =IF(AND(11>=$C15,11<=$D15),($I15+($J15-$I15)*('02_Assumptions'!$C$8-1)/3)/($D15-$C15+1),0) -> 0 | Y15: =IF(AND(12>=$C15,12<=$D15),($I15+($J15-$I15)*('02_Assumptions'!$C$8-1)/3)/($D15-$C15+1),0) -> 0 | Z15: =(I15+(J15-I15)*('02_Assumptions'!$C$8-1)/3)/(D15-C15+1)/'02_Assumptions'!$C$9 -> 5.8666667
A16: Soil | B16: Spread compost/manure/dolomite | C16: 6 | D16: 8 | E16: ha net | F16: ='02_Assumptions'!$C$6*'02_Assumptions'!$C$7 -> 88 | G16: ='02_Assumptions'!$C$6*'02_Assumptions'!$C$7 -> 88 | H16: 8 | I16: =F16*H16 -> 704 | J16: =G16*H16 -> 704 | K16: =I16*'02_Assumptions'!$C$60 -> 84480000 | L16: =J16*'02_Assumptions'!$C$60 -> 84480000 | M16: Tractor + hand spread | N16: =IF(AND(1>=$C16,1<=$D16),($I16+($J16-$I16)*('02_Assumptions'!$C$8-1)/3)/($D16-$C16+1),0) -> 0 | O16: =IF(AND(2>=$C16,2<=$D16),($I16+($J16-$I16)*('02_Assumptions'!$C$8-1)/3)/($D16-$C16+1),0) -> 0 | P16: =IF(AND(3>=$C16,3<=$D16),($I16+($J16-$I16)*('02_Assumptions'!$C$8-1)/3)/($D16-$C16+1),0) -> 0 | Q16: =IF(AND(4>=$C16,4<=$D16),($I16+($J16-$I16)*('02_Assumptions'!$C$8-1)/3)/($D16-$C16+1),0) -> 0 | R16: =IF(AND(5>=$C16,5<=$D16),($I16+($J16-$I16)*('02_Assumptions'!$C$8-1)/3)/($D16-$C16+1),0) -> 0 | S16: =IF(AND(6>=$C16,6<=$D16),($I16+($J16-$I16)*('02_Assumptions'!$C$8-1)/3)/($D16-$C16+1),0) -> 234.66667 | T16: =IF(AND(7>=$C16,7<=$D16),($I16+($J16-$I16)*('02_Assumptions'!$C$8-1)/3)/($D16-$C16+1),0) -> 234.66667 | U16: =IF(AND(8>=$C16,8<=$D16),($I16+($J16-$I16)*('02_Assumptions'!$C$8-1)/3)/($D16-$C16+1),0) -> 234.66667 | V16: =IF(AND(9>=$C16,9<=$D16),($I16+($J16-$I16)*('02_Assumptions'!$C$8-1)/3)/($D16-$C16+1),0) -> 0 | W16: =IF(AND(10>=$C16,10<=$D16),($I16+($J16-$I16)*('02_Assumptions'!$C$8-1)/3)/($D16-$C16+1),0) -> 0 | X16: =IF(AND(11>=$C16,11<=$D16),($I16+($J16-$I16)*('02_Assumptions'!$C$8-1)/3)/($D16-$C16+1),0) -> 0 | Y16: =IF(AND(12>=$C16,12<=$D16),($I16+($J16-$I16)*('02_Assumptions'!$C$8-1)/3)/($D16-$C16+1),0) -> 0 | Z16: =(I16+(J16-I16)*('02_Assumptions'!$C$8-1)/3)/(D16-C16+1)/'02_Assumptions'!$C$9 -> 9.3866667
A17: Planting | B17: Tree holes 60x60x60 | C17: 6 | D17: 8 | E17: hole | F17: ='04_Planting_Design'!$D$8+'04_Planting_Design'!$F$8 -> 9944 | G17: ='04_Planting_Design'!$D$8+'04_Planting_Design'!$F$8 -> 9944 | H17: 0.08 | I17: =F17*H17 -> 795.52 | J17: =G17*H17 -> 795.52 | K17: =I17*'02_Assumptions'!$C$60 -> 95462400 | L17: =J17*'02_Assumptions'!$C$60 -> 95462400 | M17: Earth auger + manual finishing | N17: =IF(AND(1>=$C17,1<=$D17),($I17+($J17-$I17)*('02_Assumptions'!$C$8-1)/3)/($D17-$C17+1),0) -> 0 | O17: =IF(AND(2>=$C17,2<=$D17),($I17+($J17-$I17)*('02_Assumptions'!$C$8-1)/3)/($D17-$C17+1),0) -> 0 | P17: =IF(AND(3>=$C17,3<=$D17),($I17+($J17-$I17)*('02_Assumptions'!$C$8-1)/3)/($D17-$C17+1),0) -> 0 | Q17: =IF(AND(4>=$C17,4<=$D17),($I17+($J17-$I17)*('02_Assumptions'!$C$8-1)/3)/($D17-$C17+1),0) -> 0 | R17: =IF(AND(5>=$C17,5<=$D17),($I17+($J17-$I17)*('02_Assumptions'!$C$8-1)/3)/($D17-$C17+1),0) -> 0 | S17: =IF(AND(6>=$C17,6<=$D17),($I17+($J17-$I17)*('02_Assumptions'!$C$8-1)/3)/($D17-$C17+1),0) -> 265.17333 | T17: =IF(AND(7>=$C17,7<=$D17),($I17+($J17-$I17)*('02_Assumptions'!$C$8-1)/3)/($D17-$C17+1),0) -> 265.17333 | U17: =IF(AND(8>=$C17,8<=$D17),($I17+($J17-$I17)*('02_Assumptions'!$C$8-1)/3)/($D17-$C17+1),0) -> 265.17333 | V17: =IF(AND(9>=$C17,9<=$D17),($I17+($J17-$I17)*('02_Assumptions'!$C$8-1)/3)/($D17-$C17+1),0) -> 0 | W17: =IF(AND(10>=$C17,10<=$D17),($I17+($J17-$I17)*('02_Assumptions'!$C$8-1)/3)/($D17-$C17+1),0) -> 0 | X17: =IF(AND(11>=$C17,11<=$D17),($I17+($J17-$I17)*('02_Assumptions'!$C$8-1)/3)/($D17-$C17+1),0) -> 0 | Y17: =IF(AND(12>=$C17,12<=$D17),($I17+($J17-$I17)*('02_Assumptions'!$C$8-1)/3)/($D17-$C17+1),0) -> 0 | Z17: =(I17+(J17-I17)*('02_Assumptions'!$C$8-1)/3)/(D17-C17+1)/'02_Assumptions'!$C$9 -> 10.606933
A18: Planting | B18: Banana holes 40x40x40 | C18: 6 | D18: 9 | E18: hole | F18: ='04_Planting_Design'!$H$8 -> 44000 | G18: ='04_Planting_Design'!$H$8 -> 44000 | H18: 0.025 | I18: =F18*H18 -> 1100 | J18: =G18*H18 -> 1100 | K18: =I18*'02_Assumptions'!$C$60 -> 132000000 | L18: =J18*'02_Assumptions'!$C$60 -> 132000000 | M18: Auger/manual | N18: =IF(AND(1>=$C18,1<=$D18),($I18+($J18-$I18)*('02_Assumptions'!$C$8-1)/3)/($D18-$C18+1),0) -> 0 | O18: =IF(AND(2>=$C18,2<=$D18),($I18+($J18-$I18)*('02_Assumptions'!$C$8-1)/3)/($D18-$C18+1),0) -> 0 | P18: =IF(AND(3>=$C18,3<=$D18),($I18+($J18-$I18)*('02_Assumptions'!$C$8-1)/3)/($D18-$C18+1),0) -> 0 | Q18: =IF(AND(4>=$C18,4<=$D18),($I18+($J18-$I18)*('02_Assumptions'!$C$8-1)/3)/($D18-$C18+1),0) -> 0 | R18: =IF(AND(5>=$C18,5<=$D18),($I18+($J18-$I18)*('02_Assumptions'!$C$8-1)/3)/($D18-$C18+1),0) -> 0 | S18: =IF(AND(6>=$C18,6<=$D18),($I18+($J18-$I18)*('02_Assumptions'!$C$8-1)/3)/($D18-$C18+1),0) -> 275 | T18: =IF(AND(7>=$C18,7<=$D18),($I18+($J18-$I18)*('02_Assumptions'!$C$8-1)/3)/($D18-$C18+1),0) -> 275 | U18: =IF(AND(8>=$C18,8<=$D18),($I18+($J18-$I18)*('02_Assumptions'!$C$8-1)/3)/($D18-$C18+1),0) -> 275 | V18: =IF(AND(9>=$C18,9<=$D18),($I18+($J18-$I18)*('02_Assumptions'!$C$8-1)/3)/($D18-$C18+1),0) -> 275 | W18: =IF(AND(10>=$C18,10<=$D18),($I18+($J18-$I18)*('02_Assumptions'!$C$8-1)/3)/($D18-$C18+1),0) -> 0 | X18: =IF(AND(11>=$C18,11<=$D18),($I18+($J18-$I18)*('02_Assumptions'!$C$8-1)/3)/($D18-$C18+1),0) -> 0 | Y18: =IF(AND(12>=$C18,12<=$D18),($I18+($J18-$I18)*('02_Assumptions'!$C$8-1)/3)/($D18-$C18+1),0) -> 0 | Z18: =(I18+(J18-I18)*('02_Assumptions'!$C$8-1)/3)/(D18-C18+1)/'02_Assumptions'!$C$9 -> 11
A19: Planting | B19: Plant coconut & durian | C19: 8 | D19: 10 | E19: plant | F19: ='04_Planting_Design'!$D$8+'04_Planting_Design'!$F$8 -> 9944 | G19: ='04_Planting_Design'!$D$8+'04_Planting_Design'!$F$8 -> 9944 | H19: 0.04 | I19: =F19*H19 -> 397.76 | J19: =G19*H19 -> 397.76 | K19: =I19*'02_Assumptions'!$C$60 -> 47731200 | L19: =J19*'02_Assumptions'!$C$60 -> 47731200 | M19: Handle graft union carefully | N19: =IF(AND(1>=$C19,1<=$D19),($I19+($J19-$I19)*('02_Assumptions'!$C$8-1)/3)/($D19-$C19+1),0) -> 0 | O19: =IF(AND(2>=$C19,2<=$D19),($I19+($J19-$I19)*('02_Assumptions'!$C$8-1)/3)/($D19-$C19+1),0) -> 0 | P19: =IF(AND(3>=$C19,3<=$D19),($I19+($J19-$I19)*('02_Assumptions'!$C$8-1)/3)/($D19-$C19+1),0) -> 0 | Q19: =IF(AND(4>=$C19,4<=$D19),($I19+($J19-$I19)*('02_Assumptions'!$C$8-1)/3)/($D19-$C19+1),0) -> 0 | R19: =IF(AND(5>=$C19,5<=$D19),($I19+($J19-$I19)*('02_Assumptions'!$C$8-1)/3)/($D19-$C19+1),0) -> 0 | S19: =IF(AND(6>=$C19,6<=$D19),($I19+($J19-$I19)*('02_Assumptions'!$C$8-1)/3)/($D19-$C19+1),0) -> 0 | T19: =IF(AND(7>=$C19,7<=$D19),($I19+($J19-$I19)*('02_Assumptions'!$C$8-1)/3)/($D19-$C19+1),0) -> 0 | U19: =IF(AND(8>=$C19,8<=$D19),($I19+($J19-$I19)*('02_Assumptions'!$C$8-1)/3)/($D19-$C19+1),0) -> 132.58667 | V19: =IF(AND(9>=$C19,9<=$D19),($I19+($J19-$I19)*('02_Assumptions'!$C$8-1)/3)/($D19-$C19+1),0) -> 132.58667 | W19: =IF(AND(10>=$C19,10<=$D19),($I19+($J19-$I19)*('02_Assumptions'!$C$8-1)/3)/($D19-$C19+1),0) -> 132.58667 | X19: =IF(AND(11>=$C19,11<=$D19),($I19+($J19-$I19)*('02_Assumptions'!$C$8-1)/3)/($D19-$C19+1),0) -> 0 | Y19: =IF(AND(12>=$C19,12<=$D19),($I19+($J19-$I19)*('02_Assumptions'!$C$8-1)/3)/($D19-$C19+1),0) -> 0 | Z19: =(I19+(J19-I19)*('02_Assumptions'!$C$8-1)/3)/(D19-C19+1)/'02_Assumptions'!$C$9 -> 5.3034667
A20: Planting | B20: Plant banana | C20: 8 | D20: 10 | E20: plant | F20: ='04_Planting_Design'!$H$8 -> 44000 | G20: ='04_Planting_Design'!$H$8 -> 44000 | H20: 0.015 | I20: =F20*H20 -> 660 | J20: =G20*H20 -> 660 | K20: =I20*'02_Assumptions'!$C$60 -> 79200000 | L20: =J20*'02_Assumptions'!$C$60 -> 79200000 | M20: Two planting waves | N20: =IF(AND(1>=$C20,1<=$D20),($I20+($J20-$I20)*('02_Assumptions'!$C$8-1)/3)/($D20-$C20+1),0) -> 0 | O20: =IF(AND(2>=$C20,2<=$D20),($I20+($J20-$I20)*('02_Assumptions'!$C$8-1)/3)/($D20-$C20+1),0) -> 0 | P20: =IF(AND(3>=$C20,3<=$D20),($I20+($J20-$I20)*('02_Assumptions'!$C$8-1)/3)/($D20-$C20+1),0) -> 0 | Q20: =IF(AND(4>=$C20,4<=$D20),($I20+($J20-$I20)*('02_Assumptions'!$C$8-1)/3)/($D20-$C20+1),0) -> 0 | R20: =IF(AND(5>=$C20,5<=$D20),($I20+($J20-$I20)*('02_Assumptions'!$C$8-1)/3)/($D20-$C20+1),0) -> 0 | S20: =IF(AND(6>=$C20,6<=$D20),($I20+($J20-$I20)*('02_Assumptions'!$C$8-1)/3)/($D20-$C20+1),0) -> 0 | T20: =IF(AND(7>=$C20,7<=$D20),($I20+($J20-$I20)*('02_Assumptions'!$C$8-1)/3)/($D20-$C20+1),0) -> 0 | U20: =IF(AND(8>=$C20,8<=$D20),($I20+($J20-$I20)*('02_Assumptions'!$C$8-1)/3)/($D20-$C20+1),0) -> 220 | V20: =IF(AND(9>=$C20,9<=$D20),($I20+($J20-$I20)*('02_Assumptions'!$C$8-1)/3)/($D20-$C20+1),0) -> 220 | W20: =IF(AND(10>=$C20,10<=$D20),($I20+($J20-$I20)*('02_Assumptions'!$C$8-1)/3)/($D20-$C20+1),0) -> 220 | X20: =IF(AND(11>=$C20,11<=$D20),($I20+($J20-$I20)*('02_Assumptions'!$C$8-1)/3)/($D20-$C20+1),0) -> 0 | Y20: =IF(AND(12>=$C20,12<=$D20),($I20+($J20-$I20)*('02_Assumptions'!$C$8-1)/3)/($D20-$C20+1),0) -> 0 | Z20: =(I20+(J20-I20)*('02_Assumptions'!$C$8-1)/3)/(D20-C20+1)/'02_Assumptions'!$C$9 -> 8.8
A21: Ecology | B21: Plant gamal/indigofera/serai | C21: 8 | D21: 10 | E21: plant | F21: ='04_Planting_Design'!$I$8+'04_Planting_Design'!$J$8+'04_Planting_Design'!$K$8 -> 74800 | G21: ='04_Planting_Design'!$I$8+'04_Planting_Design'!$J$8+'04_Planting_Design'!$K$8 -> 74800 | H21: 0.006 | I21: =F21*H21 -> 448.8 | J21: =G21*H21 -> 448.8 | K21: =I21*'02_Assumptions'!$C$60 -> 53856000 | L21: =J21*'02_Assumptions'!$C$60 -> 53856000 | M21: Support species | N21: =IF(AND(1>=$C21,1<=$D21),($I21+($J21-$I21)*('02_Assumptions'!$C$8-1)/3)/($D21-$C21+1),0) -> 0 | O21: =IF(AND(2>=$C21,2<=$D21),($I21+($J21-$I21)*('02_Assumptions'!$C$8-1)/3)/($D21-$C21+1),0) -> 0 | P21: =IF(AND(3>=$C21,3<=$D21),($I21+($J21-$I21)*('02_Assumptions'!$C$8-1)/3)/($D21-$C21+1),0) -> 0 | Q21: =IF(AND(4>=$C21,4<=$D21),($I21+($J21-$I21)*('02_Assumptions'!$C$8-1)/3)/($D21-$C21+1),0) -> 0 | R21: =IF(AND(5>=$C21,5<=$D21),($I21+($J21-$I21)*('02_Assumptions'!$C$8-1)/3)/($D21-$C21+1),0) -> 0 | S21: =IF(AND(6>=$C21,6<=$D21),($I21+($J21-$I21)*('02_Assumptions'!$C$8-1)/3)/($D21-$C21+1),0) -> 0 | T21: =IF(AND(7>=$C21,7<=$D21),($I21+($J21-$I21)*('02_Assumptions'!$C$8-1)/3)/($D21-$C21+1),0) -> 0 | U21: =IF(AND(8>=$C21,8<=$D21),($I21+($J21-$I21)*('02_Assumptions'!$C$8-1)/3)/($D21-$C21+1),0) -> 149.6 | V21: =IF(AND(9>=$C21,9<=$D21),($I21+($J21-$I21)*('02_Assumptions'!$C$8-1)/3)/($D21-$C21+1),0) -> 149.6 | W21: =IF(AND(10>=$C21,10<=$D21),($I21+($J21-$I21)*('02_Assumptions'!$C$8-1)/3)/($D21-$C21+1),0) -> 149.6 | X21: =IF(AND(11>=$C21,11<=$D21),($I21+($J21-$I21)*('02_Assumptions'!$C$8-1)/3)/($D21-$C21+1),0) -> 0 | Y21: =IF(AND(12>=$C21,12<=$D21),($I21+($J21-$I21)*('02_Assumptions'!$C$8-1)/3)/($D21-$C21+1),0) -> 0 | Z21: =(I21+(J21-I21)*('02_Assumptions'!$C$8-1)/3)/(D21-C21+1)/'02_Assumptions'!$C$9 -> 5.984
A22: Water | B22: Install/commission irrigation | C22: 6 | D22: 9 | E22: site | F22: 1 | G22: 4 | H22: 120 | I22: =F22*H22 -> 120 | J22: =G22*H22 -> 480 | K22: =I22*'02_Assumptions'!$C$60 -> 14400000 | L22: =J22*'02_Assumptions'!$C$60 -> 57600000 | M22: Portable pumps, tanks, mainline | N22: =IF(AND(1>=$C22,1<=$D22),($I22+($J22-$I22)*('02_Assumptions'!$C$8-1)/3)/($D22-$C22+1),0) -> 0 | O22: =IF(AND(2>=$C22,2<=$D22),($I22+($J22-$I22)*('02_Assumptions'!$C$8-1)/3)/($D22-$C22+1),0) -> 0 | P22: =IF(AND(3>=$C22,3<=$D22),($I22+($J22-$I22)*('02_Assumptions'!$C$8-1)/3)/($D22-$C22+1),0) -> 0 | Q22: =IF(AND(4>=$C22,4<=$D22),($I22+($J22-$I22)*('02_Assumptions'!$C$8-1)/3)/($D22-$C22+1),0) -> 0 | R22: =IF(AND(5>=$C22,5<=$D22),($I22+($J22-$I22)*('02_Assumptions'!$C$8-1)/3)/($D22-$C22+1),0) -> 0 | S22: =IF(AND(6>=$C22,6<=$D22),($I22+($J22-$I22)*('02_Assumptions'!$C$8-1)/3)/($D22-$C22+1),0) -> 30 | T22: =IF(AND(7>=$C22,7<=$D22),($I22+($J22-$I22)*('02_Assumptions'!$C$8-1)/3)/($D22-$C22+1),0) -> 30 | U22: =IF(AND(8>=$C22,8<=$D22),($I22+($J22-$I22)*('02_Assumptions'!$C$8-1)/3)/($D22-$C22+1),0) -> 30 | V22: =IF(AND(9>=$C22,9<=$D22),($I22+($J22-$I22)*('02_Assumptions'!$C$8-1)/3)/($D22-$C22+1),0) -> 30 | W22: =IF(AND(10>=$C22,10<=$D22),($I22+($J22-$I22)*('02_Assumptions'!$C$8-1)/3)/($D22-$C22+1),0) -> 0 | X22: =IF(AND(11>=$C22,11<=$D22),($I22+($J22-$I22)*('02_Assumptions'!$C$8-1)/3)/($D22-$C22+1),0) -> 0 | Y22: =IF(AND(12>=$C22,12<=$D22),($I22+($J22-$I22)*('02_Assumptions'!$C$8-1)/3)/($D22-$C22+1),0) -> 0 | Z22: =(I22+(J22-I22)*('02_Assumptions'!$C$8-1)/3)/(D22-C22+1)/'02_Assumptions'!$C$9 -> 1.2
A23: Planting | B23: Gap filling/sulaman | C23: 10 | D23: 12 | E23: ha net | F23: ='02_Assumptions'!$C$6*'02_Assumptions'!$C$7 -> 88 | G23: ='02_Assumptions'!$C$6*'02_Assumptions'!$C$7 -> 88 | H23: 8 | I23: =F23*H23 -> 704 | J23: =G23*H23 -> 704 | K23: =I23*'02_Assumptions'!$C$60 -> 84480000 | L23: =J23*'02_Assumptions'!$C$60 -> 84480000 | M23: Use reserved seedlings | N23: =IF(AND(1>=$C23,1<=$D23),($I23+($J23-$I23)*('02_Assumptions'!$C$8-1)/3)/($D23-$C23+1),0) -> 0 | O23: =IF(AND(2>=$C23,2<=$D23),($I23+($J23-$I23)*('02_Assumptions'!$C$8-1)/3)/($D23-$C23+1),0) -> 0 | P23: =IF(AND(3>=$C23,3<=$D23),($I23+($J23-$I23)*('02_Assumptions'!$C$8-1)/3)/($D23-$C23+1),0) -> 0 | Q23: =IF(AND(4>=$C23,4<=$D23),($I23+($J23-$I23)*('02_Assumptions'!$C$8-1)/3)/($D23-$C23+1),0) -> 0 | R23: =IF(AND(5>=$C23,5<=$D23),($I23+($J23-$I23)*('02_Assumptions'!$C$8-1)/3)/($D23-$C23+1),0) -> 0 | S23: =IF(AND(6>=$C23,6<=$D23),($I23+($J23-$I23)*('02_Assumptions'!$C$8-1)/3)/($D23-$C23+1),0) -> 0 | T23: =IF(AND(7>=$C23,7<=$D23),($I23+($J23-$I23)*('02_Assumptions'!$C$8-1)/3)/($D23-$C23+1),0) -> 0 | U23: =IF(AND(8>=$C23,8<=$D23),($I23+($J23-$I23)*('02_Assumptions'!$C$8-1)/3)/($D23-$C23+1),0) -> 0 | V23: =IF(AND(9>=$C23,9<=$D23),($I23+($J23-$I23)*('02_Assumptions'!$C$8-1)/3)/($D23-$C23+1),0) -> 0 | W23: =IF(AND(10>=$C23,10<=$D23),($I23+($J23-$I23)*('02_Assumptions'!$C$8-1)/3)/($D23-$C23+1),0) -> 234.66667 | X23: =IF(AND(11>=$C23,11<=$D23),($I23+($J23-$I23)*('02_Assumptions'!$C$8-1)/3)/($D23-$C23+1),0) -> 234.66667 | Y23: =IF(AND(12>=$C23,12<=$D23),($I23+($J23-$I23)*('02_Assumptions'!$C$8-1)/3)/($D23-$C23+1),0) -> 234.66667 | Z23: =(I23+(J23-I23)*('02_Assumptions'!$C$8-1)/3)/(D23-C23+1)/'02_Assumptions'!$C$9 -> 9.3866667
A24: Ecology | B24: Sow cover crops/insectary | C24: 8 | D24: 11 | E24: ha net | F24: ='02_Assumptions'!$C$6*'02_Assumptions'!$C$7 -> 88 | G24: ='02_Assumptions'!$C$6*'02_Assumptions'!$C$7 -> 88 | H24: 6 | I24: =F24*H24 -> 528 | J24: =G24*H24 -> 528 | K24: =I24*'02_Assumptions'!$C$60 -> 63360000 | L24: =J24*'02_Assumptions'!$C$60 -> 63360000 | M24: Staggered strips | N24: =IF(AND(1>=$C24,1<=$D24),($I24+($J24-$I24)*('02_Assumptions'!$C$8-1)/3)/($D24-$C24+1),0) -> 0 | O24: =IF(AND(2>=$C24,2<=$D24),($I24+($J24-$I24)*('02_Assumptions'!$C$8-1)/3)/($D24-$C24+1),0) -> 0 | P24: =IF(AND(3>=$C24,3<=$D24),($I24+($J24-$I24)*('02_Assumptions'!$C$8-1)/3)/($D24-$C24+1),0) -> 0 | Q24: =IF(AND(4>=$C24,4<=$D24),($I24+($J24-$I24)*('02_Assumptions'!$C$8-1)/3)/($D24-$C24+1),0) -> 0 | R24: =IF(AND(5>=$C24,5<=$D24),($I24+($J24-$I24)*('02_Assumptions'!$C$8-1)/3)/($D24-$C24+1),0) -> 0 | S24: =IF(AND(6>=$C24,6<=$D24),($I24+($J24-$I24)*('02_Assumptions'!$C$8-1)/3)/($D24-$C24+1),0) -> 0 | T24: =IF(AND(7>=$C24,7<=$D24),($I24+($J24-$I24)*('02_Assumptions'!$C$8-1)/3)/($D24-$C24+1),0) -> 0 | U24: =IF(AND(8>=$C24,8<=$D24),($I24+($J24-$I24)*('02_Assumptions'!$C$8-1)/3)/($D24-$C24+1),0) -> 132 | V24: =IF(AND(9>=$C24,9<=$D24),($I24+($J24-$I24)*('02_Assumptions'!$C$8-1)/3)/($D24-$C24+1),0) -> 132 | W24: =IF(AND(10>=$C24,10<=$D24),($I24+($J24-$I24)*('02_Assumptions'!$C$8-1)/3)/($D24-$C24+1),0) -> 132 | X24: =IF(AND(11>=$C24,11<=$D24),($I24+($J24-$I24)*('02_Assumptions'!$C$8-1)/3)/($D24-$C24+1),0) -> 132 | Y24: =IF(AND(12>=$C24,12<=$D24),($I24+($J24-$I24)*('02_Assumptions'!$C$8-1)/3)/($D24-$C24+1),0) -> 0 | Z24: =(I24+(J24-I24)*('02_Assumptions'!$C$8-1)/3)/(D24-C24+1)/'02_Assumptions'!$C$9 -> 5.28
A25: Maintenance | B25: Initial weeding/scouting/mulch | C25: 9 | D25: 12 | E25: ha net | F25: ='02_Assumptions'!$C$6*'02_Assumptions'!$C$7 -> 88 | G25: ='02_Assumptions'!$C$6*'02_Assumptions'!$C$7 -> 88 | H25: 12 | I25: =F25*H25 -> 1056 | J25: =G25*H25 -> 1056 | K25: =I25*'02_Assumptions'!$C$60 -> 126720000 | L25: =J25*'02_Assumptions'!$C$60 -> 126720000 | M25: Survival protection | N25: =IF(AND(1>=$C25,1<=$D25),($I25+($J25-$I25)*('02_Assumptions'!$C$8-1)/3)/($D25-$C25+1),0) -> 0 | O25: =IF(AND(2>=$C25,2<=$D25),($I25+($J25-$I25)*('02_Assumptions'!$C$8-1)/3)/($D25-$C25+1),0) -> 0 | P25: =IF(AND(3>=$C25,3<=$D25),($I25+($J25-$I25)*('02_Assumptions'!$C$8-1)/3)/($D25-$C25+1),0) -> 0 | Q25: =IF(AND(4>=$C25,4<=$D25),($I25+($J25-$I25)*('02_Assumptions'!$C$8-1)/3)/($D25-$C25+1),0) -> 0 | R25: =IF(AND(5>=$C25,5<=$D25),($I25+($J25-$I25)*('02_Assumptions'!$C$8-1)/3)/($D25-$C25+1),0) -> 0 | S25: =IF(AND(6>=$C25,6<=$D25),($I25+($J25-$I25)*('02_Assumptions'!$C$8-1)/3)/($D25-$C25+1),0) -> 0 | T25: =IF(AND(7>=$C25,7<=$D25),($I25+($J25-$I25)*('02_Assumptions'!$C$8-1)/3)/($D25-$C25+1),0) -> 0 | U25: =IF(AND(8>=$C25,8<=$D25),($I25+($J25-$I25)*('02_Assumptions'!$C$8-1)/3)/($D25-$C25+1),0) -> 0 | V25: =IF(AND(9>=$C25,9<=$D25),($I25+($J25-$I25)*('02_Assumptions'!$C$8-1)/3)/($D25-$C25+1),0) -> 264 | W25: =IF(AND(10>=$C25,10<=$D25),($I25+($J25-$I25)*('02_Assumptions'!$C$8-1)/3)/($D25-$C25+1),0) -> 264 | X25: =IF(AND(11>=$C25,11<=$D25),($I25+($J25-$I25)*('02_Assumptions'!$C$8-1)/3)/($D25-$C25+1),0) -> 264 | Y25: =IF(AND(12>=$C25,12<=$D25),($I25+($J25-$I25)*('02_Assumptions'!$C$8-1)/3)/($D25-$C25+1),0) -> 264 | Z25: =(I25+(J25-I25)*('02_Assumptions'!$C$8-1)/3)/(D25-C25+1)/'02_Assumptions'!$C$9 -> 10.56
A26: TOTAL BIAYA TENAGA LAPANG LANGSUNG | K26: =SUM(K6:K25) -> 1170489600 | L26: =SUM(L6:L25) -> 1213689600
A27: HOK BULANAN — SKENARIO TERPILIH | N27: =SUM(N6:N25) -> 65 | O27: =SUM(O6:O25) -> 95 | P27: =SUM(P6:P25) -> 160 | Q27: =SUM(Q6:Q25) -> 900 | R27: =SUM(R6:R25) -> 946.66667 | S27: =SUM(S6:S25) -> 1751.5067 | T27: =SUM(T6:T25) -> 1151.5067 | U27: =SUM(U6:U25) -> 1439.0267 | ... Y27: =SUM(Y6:Y25) -> 498.66667 | Z27: =MAX(N27:Y27)/'02_Assumptions'!$C$9 -> 70.060267
A30: B. Kebutuhan HOK pemeliharaan tahunan — HOK panen sudah masuk biaya per unit
A31: Aktivitas | B31: T1 | C31: T2 | D31: T3 | E31: T4 | F31: T5 | G31: T6 | H31: T7 | I31: T8 | J31: T9 | K31: T10 | L31: Satuan
A32: Weeding/groundcover management | B32: 28 | C32: 26 | D32: 24 | E32: 22 | F32: 20 | G32: 18 | H32: 16 | I32: 15 | J32: 15 | K32: 15 | L32: HOK/ha
A33: Banana suckering & sanitation | B33: 18 | C33: 16.2 | D33: 12.6 | E33: 8.1 | F33: 4.5 | G33: 2.7 | H33: 1.8 | I33: 1.8 | J33: 1.8 | K33: 1.8 | L33: HOK/ha
A34: Fertilizer/compost application | B34: 10 | C34: 10 | D34: 11 | E34: 11 | F34: 12 | G34: 12 | H34: 13 | I34: 13 | J34: 13 | K34: 13 | L34: HOK/ha
A35: Tree training/pruning | B35: 6 | C35: 8 | D35: 10 | E35: 12 | F35: 13 | G35: 14 | H35: 15 | I35: 16 | J35: 16 | K35: 16 | L35: HOK/ha
A36: Plant health scouting/biosecurity | B36: 10 | C36: 10 | D36: 10 | E36: 10 | F36: 10 | G36: 10 | H36: 10 | I36: 10 | J36: 10 | K36: 10 | L36: HOK/ha
A37: Supplemental irrigation | B37: 8 | C37: 7 | D37: 6 | E37: 5 | F37: 4 | G37: 4 | H37: 4 | I37: 4 | J37: 4 | K37: 4 | L37: HOK/ha
A38: Gap filling/replanting | B38: 8 | C38: 4 | D38: 2 | E38: 1 | F38: 1 | G38: 1 | H38: 1 | I38: 1 | J38: 1 | K38: 1 | L38: HOK/ha
A39: Manual road/drain upkeep | B39: 4 | C39: 4 | D39: 4 | E39: 4 | F39: 4 | G39: 4 | H39: 4 | I39: 4 | J39: 4 | K39: 4 | L39: HOK/ha
A40: Mapping/biodiversity field monitoring | B40: 3 | C40: 3 | D40: 3 | E40: 3 | F40: 3 | G40: 3 | H40: 3 | I40: 3 | J40: 3 | K40: 3 | L40: HOK/ha
A41: TOTAL HOK PROYEK | B41: =SUM(B32:B40)*'02_Assumptions'!$C$6*'02_Assumptions'!$C$7 -> 8360 | C41: =SUM(C32:C40)*'02_Assumptions'!$C$6*'02_Assumptions'!$C$7 -> 7761.6 | D41: =SUM(D32:D40)*'02_Assumptions'!$C$6*'02_Assumptions'!$C$7 -> 7268.8 | E41: =SUM(E32:E40)*'02_Assumptions'!$C$6*'02_Assumptions'!$C$7 -> 6696.8 | F41: =SUM(F32:F40)*'02_Assumptions'!$C$6*'02_Assumptions'!$C$7 -> 6292 | G41: =SUM(G32:G40)*'02_Assumptions'!$C$6*'02_Assumptions'!$C$7 -> 6045.6 | H41: =SUM(H32:H40)*'02_Assumptions'!$C$6*'02_Assumptions'!$C$7 -> 5966.4 | I41: =SUM(I32:I40)*'02_Assumptions'!$C$6*'02_Assumptions'!$C$7 -> 5966.4 | ... K41: =SUM(K32:K40)*'02_Assumptions'!$C$6*'02_Assumptions'!$C$7 -> 5966.4 | L41: HOK/year
A42: Rata-rata kru lapang | B42: =B41/'02_Assumptions'!$C$9/12 -> 27.866667 | C42: =C41/'02_Assumptions'!$C$9/12 -> 25.872 | D42: =D41/'02_Assumptions'!$C$9/12 -> 24.229333 | E42: =E41/'02_Assumptions'!$C$9/12 -> 22.322667 | F42: =F41/'02_Assumptions'!$C$9/12 -> 20.973333 | G42: =G41/'02_Assumptions'!$C$9/12 -> 20.152 | H42: =H41/'02_Assumptions'!$C$9/12 -> 19.888 | I42: =I41/'02_Assumptions'!$C$9/12 -> 19.888 | ... K42: =K41/'02_Assumptions'!$C$9/12 -> 19.888 | L42: people
A43: Kru lapang puncak (1,35×) | B43: =B42*1.35 -> 37.62 | C43: =C42*1.35 -> 34.9272 | D43: =D42*1.35 -> 32.7096 | E43: =E42*1.35 -> 30.1356 | F43: =F42*1.35 -> 28.314 | G43: =G42*1.35 -> 27.2052 | H43: =H42*1.35 -> 26.8488 | I43: =I42*1.35 -> 26.8488 | ... K43: =K42*1.35 -> 26.8488 | L43: people

Sheet 06_Equipment_Tools
A1: Peralatan, Mesin, Kendaraan, dan APD
A2: Jumlah alat dihitung otomatis dari luas dan jumlah lokasi. Harga satuan tetap terbuka; metode beli/sewa dipilih otomatis pada 20_Operasi_Efisien.
A4: Kategori | B4: Barang | C4: Spesifikasi/penggunaan | D4: Jumlah 1 lokasi | E4: Jumlah 4 lokasi | F4: Metode | G4: Satuan | H4: Harga satuan | I4: Total 1 lokasi | J4: Total 4 lokasi | K4: Umur manfaat | L4: Penggantian/perawatan | M4: Dasar/keyakinan | N4: Aktif | O4: Dasar per 100 ha | P4: Kenaikan per lokasi ekstra | Q4: Minimum per lokasi
A5: Hand tools | B5: Cangkul heavy duty | C5: Soil work and circle weeding | D5: =IF($N5=0,0,ROUNDUP(MAX($O5*'02_Assumptions'!$C$6/100,$Q5),0)) -> 120 | E5: =IF($N5=0,0,ROUNDUP(MAX($O5*'02_Assumptions'!$C$6/100*(1+$P5*3),$Q5*4),0)) -> 140 | F5: Buy | G5: unit | H5: 180000 | I5: =$D5*$H5 -> 21600000 | J5: =$E5*$H5 -> 25200000 | K5: 3 | L5: Replace 35% every 3y | M5: Peak planting crew / Medium | N5: 1 | O5: 120 | P5: 0.055555556 | Q5: 0
A6: Hand tools | B6: Sekop | C6: Hole finishing/compost | D6: =IF($N6=0,0,ROUNDUP(MAX($O6*'02_Assumptions'!$C$6/100,$Q6),0)) -> 80 | E6: =IF($N6=0,0,ROUNDUP(MAX($O6*'02_Assumptions'!$C$6/100*(1+$P6*3),$Q6*4),0)) -> 100 | F6: Buy | G6: unit | H6: 200000 | I6: =$D6*$H6 -> 16000000 | J6: =$E6*$H6 -> 20000000 | K6: 3 | L6: Replace 35% every 3y | M6: Crew allocation / Medium | N6: 1 | O6: 80 | P6: 0.083333333 | Q6: 0
A7: Hand tools | B7: Garpu tanah | C7: Compost/mulch | D7: =IF($N7=0,0,ROUNDUP(MAX($O7*'02_Assumptions'!$C$6/100,$Q7),0)) -> 40 | E7: =IF($N7=0,0,ROUNDUP(MAX($O7*'02_Assumptions'!$C$6/100*(1+$P7*3),$Q7*4),0)) -> 50 | F7: Buy | G7: unit | H7: 250000 | I7: =$D7*$H7 -> 10000000 | J7: =$E7*$H7 -> 12500000 | K7: 4 | L7: Replace as damaged | M7: Crew allocation / Medium | N7: 1 | O7: 40 | P7: 0.083333333 | Q7: 0
A8: Hand tools | B8: Linggis | C8: Rocky soil/markers | D8: =IF($N8=0,0,ROUNDUP(MAX($O8*'02_Assumptions'!$C$6/100,$Q8),0)) -> 30 | E8: =IF($N8=0,0,ROUNDUP(MAX($O8*'02_Assumptions'!$C$6/100*(1+$P8*3),$Q8*4),0)) -> 40 | F8: Buy | G8: unit | H8: 250000 | I8: =$D8*$H8 -> 7500000 | J8: =$E8*$H8 -> 10000000 | K8: 5 | L8: Replace as damaged | M8: Crew allocation / Medium | N8: 1 | O8: 30 | P8: 0.11111111 | Q8: 0
A9: Hand tools | B9: Parang/sabit | C9: Slashing/sanitation | D9: =IF($N9=0,0,ROUNDUP(MAX($O9*'02_Assumptions'!$C$6/100,$Q9),0)) -> 120 | E9: =IF($N9=0,0,ROUNDUP(MAX($O9*'02_Assumptions'!$C$6/100*(1+$P9*3),$Q9*4),0)) -> 140 | F9: Buy | G9: unit | H9: 150000 | I9: =$D9*$H9 -> 18000000 | J9: =$E9*$H9 -> 21000000 | K9: 2 | L9: Replace 50% every 2y | M9: Peak crew / Medium | N9: 1 | O9: 120 | P9: 0.055555556 | Q9: 0
A10: Hand tools | B10: Gergaji pangkas | C10: Tree training | D10: =IF($N10=0,0,ROUNDUP(MAX($O10*'02_Assumptions'!$C$6/100,$Q10),0)) -> 20 | E10: =IF($N10=0,0,ROUNDUP(MAX($O10*'02_Assumptions'!$C$6/100*(1+$P10*3),$Q10*4),0)) -> 28 | F10: Buy | G10: unit | H10: 350000 | I10: =$D10*$H10 -> 7000000 | J10: =$E10*$H10 -> 9800000 | K10: 4 | L10: Sharpen annually | M10: 1 per field team / Medium | N10: 1 | O10: 20 | P10: 0.13333333 | Q10: 0
A11: Hand tools | B11: Gunting pangkas | C11: Sanitary pruning | D11: =IF($N11=0,0,ROUNDUP(MAX($O11*'02_Assumptions'!$C$6/100,$Q11),0)) -> 40 | E11: =IF($N11=0,0,ROUNDUP(MAX($O11*'02_Assumptions'!$C$6/100*(1+$P11*3),$Q11*4),0)) -> 50 | F11: Buy | G11: unit | H11: 250000 | I11: =$D11*$H11 -> 10000000 | J11: =$E11*$H11 -> 12500000 | K11: 3 | L11: Disinfect between blocks | M11: 1 per small team / Medium | N11: 1 | O11: 40 | P11: 0.083333333 | Q11: 0
A12: Hand tools | B12: Pole pruner | C12: Coconut/durian canopy | D12: =IF($N12=0,0,ROUNDUP(MAX($O12*'02_Assumptions'!$C$6/100,$Q12),0)) -> 20 | E12: =IF($N12=0,0,ROUNDUP(MAX($O12*'02_Assumptions'!$C$6/100*(1+$P12*3),$Q12*4),0)) -> 28 | F12: Buy | G12: unit | H12: 1500000 | I12: =$D12*$H12 -> 30000000 | J12: =$E12*$H12 -> 42000000 | K12: 5 | L12: Inspect poles annually | M12: 1 per 5 ha / Low | N12: 1 | O12: 20 | P12: 0.13333333 | Q12: 0
A13: Hand tools | B13: Tugal/manual auger | C13: Support plants/cover | D13: =IF($N13=0,0,ROUNDUP(MAX($O13*'02_Assumptions'!$C$6/100,$Q13),0)) -> 60 | E13: =IF($N13=0,0,ROUNDUP(MAX($O13*'02_Assumptions'!$C$6/100*(1+$P13*3),$Q13*4),0)) -> 72 | F13: Buy | G13: unit | H13: 300000 | I13: =$D13*$H13 -> 18000000 | J13: =$E13*$H13 -> 21600000 | K13: 4 | L13: Replace as damaged | M13: Planting crew / Medium | N13: 1 | O13: 60 | P13: 0.066666667 | Q13: 0
A14: Hand tools | B14: Angkong 100 L | C14: Material and harvest movement | D14: =IF($N14=0,0,ROUNDUP(MAX($O14*'02_Assumptions'!$C$6/100,$Q14),0)) -> 40 | E14: =IF($N14=0,0,ROUNDUP(MAX($O14*'02_Assumptions'!$C$6/100*(1+$P14*3),$Q14*4),0)) -> 48 | F14: Buy | G14: unit | H14: 1200000 | I14: =$D14*$H14 -> 48000000 | J14: =$E14*$H14 -> 57600000 | K14: 4 | L14: Wheel/bearing annual | M14: 1 per 2-3 workers / Medium | N14: 1 | O14: 40 | P14: 0.066666667 | Q14: 0
A15: Measurement | B15: Tape/rope/staking kit | C15: Layout | D15: =IF($N15=0,0,ROUNDUP(MAX($O15*'02_Assumptions'!$C$6/100,$Q15),0)) -> 20 | E15: =IF($N15=0,0,ROUNDUP(MAX($O15*'02_Assumptions'!$C$6/100*(1+$P15*3),$Q15*4),0)) -> 24 | F15: Buy | G15: set | H15: 250000 | I15: =$D15*$H15 -> 5000000 | J15: =$E15*$H15 -> 6000000 | K15: 3 | L15: Annual replenishment | M15: Layout teams / Medium | N15: 1 | O15: 20 | P15: 0.066666667 | Q15: 0
A16: Measurement | B16: Soil auger | C16: Composite samples | D16: =IF($N16=0,0,ROUNDUP(MAX($O16*'02_Assumptions'!$C$6/100,$Q16),0)) -> 4 | E16: =IF($N16=0,0,ROUNDUP(MAX($O16*'02_Assumptions'!$C$6/100*(1+$P16*3),$Q16*4),0)) -> 8 | F16: Buy | G16: unit | H16: 3000000 | I16: =$D16*$H16 -> 12000000 | J16: =$E16*$H16 -> 24000000 | K16: 8 | L16: Clean between sites | M16: 1-2 per site / Medium | N16: 1 | O16: 4 | P16: 0.33333333 | Q16: 0
... A38: Contracted | B38: Survey drone/LiDAR | C38: Orthomosaic/topo | D38: =IF($N38=0,0,ROUNDUP(MAX($O38*'02_Assumptions'!$C$6/100,$Q38),0)) -> 0 | E38: =IF($N38=0,0,ROUNDUP(MAX($O38*'02_Assumptions'!$C$6/100*(1+$P38*3),$Q38*4),0)) -> 0 | F38: Outsource | G38: ha | H38: 0 | I38: =$D38*$H38 -> 0 | J38: =$E38*$H38 -> 0 | K38: 0 | L38: Annual monitoring separate | M38: Specialist service | N38: 0 | O38: 0 | P38: 0 | Q38: 0
A39: TOTAL AWAL PERALATAN DAN MESIN | I39: =SUM(I5:I38)+SUM(I42:I51) -> 2287100000 | J39: =SUM(J5:J38)+SUM(J42:J51) -> 4365600000
A41: Baris tambahan peralatan
A42: Tambahan | B42: Peralatan tambahan 1 | C42: Isi spesifikasi | D42: =IF($N42=0,0,ROUNDUP(MAX($O42*'02_Assumptions'!$C$6/100,$Q42),0)) -> 0 | E42: =IF($N42=0,0,ROUNDUP(MAX($O42*'02_Assumptions'!$C$6/100*(1+$P42*3),$Q42*4),0)) -> 0 | F42: Beli | G42: unit | H42: 0 | I42: =$D42*$H42 -> 0 | J42: =$E42*$H42 -> 0 | K42: 5 | L42: Isi jadwal | M42: Asumsi pengguna | N42: 0 | O42: 0 | P42: 0 | Q42: 0
A43: Tambahan | B43: Peralatan tambahan 2 | C43: Isi spesifikasi | D43: =IF($N43=0,0,ROUNDUP(MAX($O43*'02_Assumptions'!$C$6/100,$Q43),0)) -> 0 | E43: =IF($N43=0,0,ROUNDUP(MAX($O43*'02_Assumptions'!$C$6/100*(1+$P43*3),$Q43*4),0)) -> 0 | F43: Beli | G43: unit | H43: 0 | I43: =$D43*$H43 -> 0 | J43: =$E43*$H43 -> 0 | K43: 5 | L43: Isi jadwal | M43: Asumsi pengguna | N43: 0 | O43: 0 | P43: 0 | Q43: 0
A44: Tambahan | B44: Peralatan tambahan 3 | C44: Isi spesifikasi | D44: =IF($N44=0,0,ROUNDUP(MAX($O44*'02_Assumptions'!$C$6/100,$Q44),0)) -> 0 | E44: =IF($N44=0,0,ROUNDUP(MAX($O44*'02_Assumptions'!$C$6/100*(1+$P44*3),$Q44*4),0)) -> 0 | F44: Beli | G44: unit | H44: 0 | I44: =$D44*$H44 -> 0 | J44: =$E44*$H44 -> 0 | K44: 5 | L44: Isi jadwal | M44: Asumsi pengguna | N44: 0 | O44: 0 | P44: 0 | Q44: 0
A45: Tambahan | B45: Peralatan tambahan 4 | C45: Isi spesifikasi | D45: =IF($N45=0,0,ROUNDUP(MAX($O45*'02_Assumptions'!$C$6/100,$Q45),0)) -> 0 | E45: =IF($N45=0,0,ROUNDUP(MAX($O45*'02_Assumptions'!$C$6/100*(1+$P45*3),$Q45*4),0)) -> 0 | F45: Beli | G45: unit | H45: 0 | I45: =$D45*$H45 -> 0 | J45: =$E45*$H45 -> 0 | K45: 5 | L45: Isi jadwal | M45: Asumsi pengguna | N45: 0 | O45: 0 | P45: 0 | Q45: 0
A46: Tambahan | B46: Peralatan tambahan 5 | C46: Isi spesifikasi | D46: =IF($N46=0,0,ROUNDUP(MAX($O46*'02_Assumptions'!$C$6/100,$Q46),0)) -> 0 | E46: =IF($N46=0,0,ROUNDUP(MAX($O46*'02_Assumptions'!$C$6/100*(1+$P46*3),$Q46*4),0)) -> 0 | F46: Beli | G46: unit | H46: 0 | I46: =$D46*$H46 -> 0 | J46: =$E46*$H46 -> 0 | K46: 5 | L46: Isi jadwal | M46: Asumsi pengguna | N46: 0 | O46: 0 | P46: 0 | Q46: 0
A47: Tambahan | B47: Peralatan tambahan 6 | C47: Isi spesifikasi | D47: =IF($N47=0,0,ROUNDUP(MAX($O47*'02_Assumptions'!$C$6/100,$Q47),0)) -> 0 | E47: =IF($N47=0,0,ROUNDUP(MAX($O47*'02_Assumptions'!$C$6/100*(1+$P47*3),$Q47*4),0)) -> 0 | F47: Beli | G47: unit | H47: 0 | I47: =$D47*$H47 -> 0 | J47: =$E47*$H47 -> 0 | K47: 5 | L47: Isi jadwal | M47: Asumsi pengguna | N47: 0 | O47: 0 | P47: 0 | Q47: 0
A48: Tambahan | B48: Peralatan tambahan 7 | C48: Isi spesifikasi | D48: =IF($N48=0,0,ROUNDUP(MAX($O48*'02_Assumptions'!$C$6/100,$Q48),0)) -> 0 | E48: =IF($N48=0,0,ROUNDUP(MAX($O48*'02_Assumptions'!$C$6/100*(1+$P48*3),$Q48*4),0)) -> 0 | F48: Beli | G48: unit | H48: 0 | I48: =$D48*$H48 -> 0 | J48: =$E48*$H48 -> 0 | K48: 5 | L48: Isi jadwal | M48: Asumsi pengguna | N48: 0 | O48: 0 | P48: 0 | Q48: 0
A49: Tambahan | B49: Peralatan tambahan 8 | C49: Isi spesifikasi | D49: =IF($N49=0,0,ROUNDUP(MAX($O49*'02_Assumptions'!$C$6/100,$Q49),0)) -> 0 | E49: =IF($N49=0,0,ROUNDUP(MAX($O49*'02_Assumptions'!$C$6/100*(1+$P49*3),$Q49*4),0)) -> 0 | F49: Beli | G49: unit | H49: 0 | I49: =$D49*$H49 -> 0 | J49: =$E49*$H49 -> 0 | K49: 5 | L49: Isi jadwal | M49: Asumsi pengguna | N49: 0 | O49: 0 | P49: 0 | Q49: 0
A50: Tambahan | B50: Peralatan tambahan 9 | C50: Isi spesifikasi | D50: =IF($N50=0,0,ROUNDUP(MAX($O50*'02_Assumptions'!$C$6/100,$Q50),0)) -> 0 | E50: =IF($N50=0,0,ROUNDUP(MAX($O50*'02_Assumptions'!$C$6/100*(1+$P50*3),$Q50*4),0)) -> 0 | F50: Beli | G50: unit | H50: 0 | I50: =$D50*$H50 -> 0 | J50: =$E50*$H50 -> 0 | K50: 5 | L50: Isi jadwal | M50: Asumsi pengguna | N50: 0 | O50: 0 | P50: 0 | Q50: 0
A51: Tambahan | B51: Peralatan tambahan 10 | C51: Isi spesifikasi | D51: =IF($N51=0,0,ROUNDUP(MAX($O51*'02_Assumptions'!$C$6/100,$Q51),0)) -> 0 | E51: =IF($N51=0,0,ROUNDUP(MAX($O51*'02_Assumptions'!$C$6/100*(1+$P51*3),$Q51*4),0)) -> 0 | F51: Beli | G51: unit | H51: 0 | I51: =$D51*$H51 -> 0 | J51: =$E51*$H51 -> 0 | K51: 5 | L51: Isi jadwal | M51: Asumsi pengguna | N51: 0 | O51: 0 | P51: 0 | Q51: 0

Sheet 07_Agri_Inputs
A1: Rencana Input Pertanian 10 Tahun
A2: Volume dolomit, kompos, pupuk, pembenah, benih penutup tanah, serta bahan PHT dihitung otomatis dari luas/populasi dan umur tanaman. Harga satuan tetap dapat diedit.
A4: Kelompok | B4: Input | C4: Tujuan | D4: Satuan | E4: Harga satuan | F4: Status organik | G4: Aturan aplikasi | H4: T1 | I4: T2 | J4: T3 | K4: T4 | L4: T5 | M4: T6 | N4: T7 | O4: T8 | P4: T9 | Q4: T10 | R4: Jumlah 10 tahun | S4: Biaya nominal 10 tahun | T4: Aktif
A5: Synthetic fertilizer | B5: Urea | C5: Vegetative N: banana, coconut, durian | D5: kg | E5: ='02_Assumptions'!$C$68 -> 8000 | F5: Prohibited organic | G5: 3 splits for new banana; 2 splits trees | H5: =IF(1<='02_Assumptions'!$C$17,'04_Planting_Design'!$D$26*'02_Assumptions'!$B$123*'02_Assumptions'!$B$131+'04_Planting_Design'!$D$24*'02_Assumptions'!$B$134+'04_Planting_Design'!$D$25*'02_Assumptions'!$B$139,0) -> 11641.74 | I5: =IF(2<='02_Assumptions'!$C$17,'04_Planting_Design'!$D$26*'02_Assumptions'!$C$123*'02_Assumptions'!$C$131+'04_Planting_Design'!$D$24*'02_Assumptions'!$C$134+'04_Planting_Design'!$D$25*'02_Assumptions'!$C$139,0) -> 11630.036 | J5: =IF(3<='02_Assumptions'!$C$17,'04_Planting_Design'!$D$26*'02_Assumptions'!$D$123*'02_Assumptions'!$D$131+'04_Planting_Design'!$D$24*'02_Assumptions'!$D$134+'04_Planting_Design'!$D$25*'02_Assumptions'!$D$139,0) -> 0 | K5: =IF(4<='02_Assumptions'!$C$17,'04_Planting_Design'!$D$26*'02_Assumptions'!$E$123*'02_Assumptions'!$E$131+'04_Planting_Design'!$D$24*'02_Assumptions'!$E$134+'04_Planting_Design'!$D$25*'02_Assumptions'!$E$139,0) -> 0 | L5: =IF(5<='02_Assumptions'!$C$17,'04_Planting_Design'!$D$26*'02_Assumptions'!$F$123*'02_Assumptions'!$F$131+'04_Planting_Design'!$D$24*'02_Assumptions'!$F$134+'04_Planting_Design'!$D$25*'02_Assumptions'!$F$139,0) -> 0 | M5: =IF(6<='02_Assumptions'!$C$17,'04_Planting_Design'!$D$26*'02_Assumptions'!$G$123*'02_Assumptions'!$G$131+'04_Planting_Design'!$D$24*'02_Assumptions'!$G$134+'04_Planting_Design'!$D$25*'02_Assumptions'!$G$139,0) -> 0 | N5: =IF(7<='02_Assumptions'!$C$17,'04_Planting_Design'!$D$26*'02_Assumptions'!$H$123*'02_Assumptions'!$H$131+'04_Planting_Design'!$D$24*'02_Assumptions'!$H$134+'04_Planting_Design'!$D$25*'02_Assumptions'!$H$139,0) -> 0 | O5: =IF(8<='02_Assumptions'!$C$17,'04_Planting_Design'!$D$26*'02_Assumptions'!$I$123*'02_Assumptions'!$I$131+'04_Planting_Design'!$D$24*'02_Assumptions'!$I$134+'04_Planting_Design'!$D$25*'02_Assumptions'!$I$139,0) -> 0 | P5: =IF(9<='02_Assumptions'!$C$17,'04_Planting_Design'!$D$26*'02_Assumptions'!$J$123*'02_Assumptions'!$J$131+'04_Planting_Design'!$D$24*'02_Assumptions'!$J$134+'04_Planting_Design'!$D$25*'02_Assumptions'!$J$139,0) -> 0 | Q5: =IF(10<='02_Assumptions'!$C$17,'04_Planting_Design'!$D$26*'02_Assumptions'!$K$123*'02_Assumptions'!$K$131+'04_Planting_Design'!$D$24*'02_Assumptions'!$K$134+'04_Planting_Design'!$D$25*'02_Assumptions'!$K$139,0) -> 0 | R5: =SUM(H5:Q5) -> 23271.776 | S5: =H5*$E5*(1+'02_Assumptions'!$C$11)^0+I5*$E5*(1+'02_Assumptions'!$C$11)^1+J5*$E5*(1+'02_Assumptions'!$C$11)^2+K5*$E5*(1+'02_Assumptions'!$C$11)^3+L5*$E5*(1+'02_Assumptions'!$C$11)^4+M5*$E5*(1+'02_Assumptions'!$C$11)^5+N5*$E5*(1+'02_Assumptions'!$C$11)^6+O5*$E5*(1+'02_Assumptions'!$C$11)^7+P5*$E5*(1+'02_Assumptions'!$C$11)^8+Q5*$E5*(1+'02_Assumptions'!$C$11)^9 -> 1.8989582e+08 | T5: 1
A6: Synthetic fertilizer | B6: ZA | C6: N + S for young trees | D6: kg | E6: ='02_Assumptions'!$C$69 -> 5000 | F6: Prohibited organic | G6: Soil/leaf-test adjusted | H6: =IF(1<='02_Assumptions'!$C$17,'04_Planting_Design'!$D$24*'02_Assumptions'!$B$135+'04_Planting_Design'!$D$25*'02_Assumptions'!$B$140,0) -> 1278.42 | I6: =IF(2<='02_Assumptions'!$C$17,'04_Planting_Design'!$D$24*'02_Assumptions'!$C$135+'04_Planting_Design'!$D$25*'02_Assumptions'!$C$140,0) -> 1744.16 | J6: =IF(3<='02_Assumptions'!$C$17,'04_Planting_Design'!$D$24*'02_Assumptions'!$D$135+'04_Planting_Design'!$D$25*'02_Assumptions'!$D$140,0) -> 0 | K6: =IF(4<='02_Assumptions'!$C$17,'04_Planting_Design'!$D$24*'02_Assumptions'!$E$135+'04_Planting_Design'!$D$25*'02_Assumptions'!$E$140,0) -> 0 | L6: =IF(5<='02_Assumptions'!$C$17,'04_Planting_Design'!$D$24*'02_Assumptions'!$F$135+'04_Planting_Design'!$D$25*'02_Assumptions'!$F$140,0) -> 0 | M6: =IF(6<='02_Assumptions'!$C$17,'04_Planting_Design'!$D$24*'02_Assumptions'!$G$135+'04_Planting_Design'!$D$25*'02_Assumptions'!$G$140,0) -> 0 | N6: =IF(7<='02_Assumptions'!$C$17,'04_Planting_Design'!$D$24*'02_Assumptions'!$H$135+'04_Planting_Design'!$D$25*'02_Assumptions'!$H$140,0) -> 0 | O6: =IF(8<='02_Assumptions'!$C$17,'04_Planting_Design'!$D$24*'02_Assumptions'!$I$135+'04_Planting_Design'!$D$25*'02_Assumptions'!$I$140,0) -> 0 | P6: =IF(9<='02_Assumptions'!$C$17,'04_Planting_Design'!$D$24*'02_Assumptions'!$J$135+'04_Planting_Design'!$D$25*'02_Assumptions'!$J$140,0) -> 0 | Q6: =IF(10<='02_Assumptions'!$C$17,'04_Planting_Design'!$D$24*'02_Assumptions'!$K$135+'04_Planting_Design'!$D$25*'02_Assumptions'!$K$140,0) -> 0 | R6: =SUM(H6:Q6) -> 3022.58 | S6: =H6*$E6*(1+'02_Assumptions'!$C$11)^0+I6*$E6*(1+'02_Assumptions'!$C$11)^1+J6*$E6*(1+'02_Assumptions'!$C$11)^2+K6*$E6*(1+'02_Assumptions'!$C$11)^3+L6*$E6*(1+'02_Assumptions'!$C$11)^4+M6*$E6*(1+'02_Assumptions'!$C$11)^5+N6*$E6*(1+'02_Assumptions'!$C$11)^6+O6*$E6*(1+'02_Assumptions'!$C$11)^7+P6*$E6*(1+'02_Assumptions'!$C$11)^8+Q6*$E6*(1+'02_Assumptions'!$C$11)^9 -> 15461732 | T6: 1
A7: Synthetic fertilizer | B7: SP-36 | C7: P for root establishment | D7: kg | E7: ='02_Assumptions'!$C$70 -> 10000 | F7: Prohibited organic | G7: Do not blanket apply without P test | H7: =IF(1<='02_Assumptions'!$C$17,'04_Planting_Design'!$D$26*'02_Assumptions'!$B$123*'02_Assumptions'!$B$132+'04_Planting_Design'!$D$24*'02_Assumptions'!$B$136+'04_Planting_Design'!$D$25*'02_Assumptions'!$B$141,0) -> 6029.76 | I7: =IF(2<='02_Assumptions'!$C$17,'04_Planting_Design'!$D$26*'02_Assumptions'!$C$123*'02_Assumptions'!$C$132+'04_Planting_Design'!$D$24*'02_Assumptions'!$C$136+'04_Planting_Design'!$D$25*'02_Assumptions'!$C$141,0) -> 6209.5 | J7: =IF(3<='02_Assumptions'!$C$17,'04_Planting_Design'!$D$26*'02_Assumptions'!$D$123*'02_Assumptions'!$D$132+'04_Planting_Design'!$D$24*'02_Assumptions'!$D$136+'04_Planting_Design'!$D$25*'02_Assumptions'!$D$141,0) -> 0 | K7: =IF(4<='02_Assumptions'!$C$17,'04_Planting_Design'!$D$26*'02_Assumptions'!$E$123*'02_Assumptions'!$E$132+'04_Planting_Design'!$D$24*'02_Assumptions'!$E$136+'04_Planting_Design'!$D$25*'02_Assumptions'!$E$141,0) -> 0 | L7: =IF(5<='02_Assumptions'!$C$17,'04_Planting_Design'!$D$26*'02_Assumptions'!$F$123*'02_Assumptions'!$F$132+'04_Planting_Design'!$D$24*'02_Assumptions'!$F$136+'04_Planting_Design'!$D$25*'02_Assumptions'!$F$141,0) -> 0 | M7: =IF(6<='02_Assumptions'!$C$17,'04_Planting_Design'!$D$26*'02_Assumptions'!$G$123*'02_Assumptions'!$G$132+'04_Planting_Design'!$D$24*'02_Assumptions'!$G$136+'04_Planting_Design'!$D$25*'02_Assumptions'!$G$141,0) -> 0 | N7: =IF(7<='02_Assumptions'!$C$17,'04_Planting_Design'!$D$26*'02_Assumptions'!$H$123*'02_Assumptions'!$H$132+'04_Planting_Design'!$D$24*'02_Assumptions'!$H$136+'04_Planting_Design'!$D$25*'02_Assumptions'!$H$141,0) -> 0 | O7: =IF(8<='02_Assumptions'!$C$17,'04_Planting_Design'!$D$26*'02_Assumptions'!$I$123*'02_Assumptions'!$I$132+'04_Planting_Design'!$D$24*'02_Assumptions'!$I$136+'04_Planting_Design'!$D$25*'02_Assumptions'!$I$141,0) -> 0 | P7: =IF(9<='02_Assumptions'!$C$17,'04_Planting_Design'!$D$26*'02_Assumptions'!$J$123*'02_Assumptions'!$J$132+'04_Planting_Design'!$D$24*'02_Assumptions'!$J$136+'04_Planting_Design'!$D$25*'02_Assumptions'!$J$141,0) -> 0 | Q7: =IF(10<='02_Assumptions'!$C$17,'04_Planting_Design'!$D$26*'02_Assumptions'!$K$123*'02_Assumptions'!$K$132+'04_Planting_Design'!$D$24*'02_Assumptions'!$K$136+'04_Planting_Design'!$D$25*'02_Assumptions'!$K$141,0) -> 0 | R7: =SUM(H7:Q7) -> 12239.26 | S7: =H7*$E7*(1+'02_Assumptions'!$C$11)^0+I7*$E7*(1+'02_Assumptions'!$C$11)^1+J7*$E7*(1+'02_Assumptions'!$C$11)^2+K7*$E7*(1+'02_Assumptions'!$C$11)^3+L7*$E7*(1+'02_Assumptions'!$C$11)^4+M7*$E7*(1+'02_Assumptions'!$C$11)^5+N7*$E7*(1+'02_Assumptions'!$C$11)^6+O7*$E7*(1+'02_Assumptions'!$C$11)^7+P7*$E7*(1+'02_Assumptions'!$C$11)^8+Q7*$E7*(1+'02_Assumptions'!$C$11)^9 -> 124876400 | T7: 1
A8: Synthetic fertilizer | B8: KCl/MOP | C8: K for banana and young trees | D8: kg | E8: ='02_Assumptions'!$C$71 -> 8000 | F8: Prohibited/restricted | G8: Split, avoid salt injury | H8: =IF(1<='02_Assumptions'!$C$17,'04_Planting_Design'!$D$26*'02_Assumptions'!$B$123*'02_Assumptions'!$B$133+'04_Planting_Design'!$D$24*'02_Assumptions'!$B$137+'04_Planting_Design'!$D$25*'02_Assumptions'!$B$142,0) -> 6376.7 | I8: =IF(2<='02_Assumptions'!$C$17,'04_Planting_Design'!$D$26*'02_Assumptions'!$C$123*'02_Assumptions'!$C$133+'04_Planting_Design'!$D$24*'02_Assumptions'!$C$137+'04_Planting_Design'!$D$25*'02_Assumptions'!$C$142,0) -> 7022.18 | J8: =IF(3<='02_Assumptions'!$C$17,'04_Planting_Design'!$D$26*'02_Assumptions'!$D$123*'02_Assumptions'!$D$133+'04_Planting_Design'!$D$24*'02_Assumptions'!$D$137+'04_Planting_Design'!$D$25*'02_Assumptions'!$D$142,0) -> 0 | K8: =IF(4<='02_Assumptions'!$C$17,'04_Planting_Design'!$D$26*'02_Assumptions'!$E$123*'02_Assumptions'!$E$133+'04_Planting_Design'!$D$24*'02_Assumptions'!$E$137+'04_Planting_Design'!$D$25*'02_Assumptions'!$E$142,0) -> 0 | L8: =IF(5<='02_Assumptions'!$C$17,'04_Planting_Design'!$D$26*'02_Assumptions'!$F$123*'02_Assumptions'!$F$133+'04_Planting_Design'!$D$24*'02_Assumptions'!$F$137+'04_Planting_Design'!$D$25*'02_Assumptions'!$F$142,0) -> 0 | M8: =IF(6<='02_Assumptions'!$C$17,'04_Planting_Design'!$D$26*'02_Assumptions'!$G$123*'02_Assumptions'!$G$133+'04_Planting_Design'!$D$24*'02_Assumptions'!$G$137+'04_Planting_Design'!$D$25*'02_Assumptions'!$G$142,0) -> 0 | N8: =IF(7<='02_Assumptions'!$C$17,'04_Planting_Design'!$D$26*'02_Assumptions'!$H$123*'02_Assumptions'!$H$133+'04_Planting_Design'!$D$24*'02_Assumptions'!$H$137+'04_Planting_Design'!$D$25*'02_Assumptions'!$H$142,0) -> 0 | O8: =IF(8<='02_Assumptions'!$C$17,'04_Planting_Design'!$D$26*'02_Assumptions'!$I$123*'02_Assumptions'!$I$133+'04_Planting_Design'!$D$24*'02_Assumptions'!$I$137+'04_Planting_Design'!$D$25*'02_Assumptions'!$I$142,0) -> 0 | P8: =IF(9<='02_Assumptions'!$C$17,'04_Planting_Design'!$D$26*'02_Assumptions'!$J$123*'02_Assumptions'!$J$133+'04_Planting_Design'!$D$24*'02_Assumptions'!$J$137+'04_Planting_Design'!$D$25*'02_Assumptions'!$J$142,0) -> 0 | Q8: =IF(10<='02_Assumptions'!$C$17,'04_Planting_Design'!$D$26*'02_Assumptions'!$K$123*'02_Assumptions'!$K$133+'04_Planting_Design'!$D$24*'02_Assumptions'!$K$137+'04_Planting_Design'!$D$25*'02_Assumptions'!$K$142,0) -> 0 | R8: =SUM(H8:Q8) -> 13398.88 | S8: =H8*$E8*(1+'02_Assumptions'!$C$11)^0+I8*$E8*(1+'02_Assumptions'!$C$11)^1+J8*$E8*(1+'02_Assumptions'!$C$11)^2+K8*$E8*(1+'02_Assumptions'!$C$11)^3+L8*$E8*(1+'02_Assumptions'!$C$11)^4+M8*$E8*(1+'02_Assumptions'!$C$11)^5+N8*$E8*(1+'02_Assumptions'!$C$11)^6+O8*$E8*(1+'02_Assumptions'!$C$11)^7+P8*$E8*(1+'02_Assumptions'!$C$11)^8+Q8*$E8*(1+'02_Assumptions'!$C$11)^9 -> 1.0943814e+08 | T8: 1
A9: Synthetic fertilizer | B9: Phonska/NPK | C9: Compound fertilizer after vegetative stage | D9: kg | E9: ='02_Assumptions'!$C$72 -> 10000 | F9: Prohibited organic | G9: Only if synthetic phase extends beyond Y2 | H9: =IF(1<='02_Assumptions'!$C$17,'04_Planting_Design'!$D$24*'02_Assumptions'!$B$138+'04_Planting_Design'!$D$25*'02_Assumptions'!$B$143,0) -> 0 | I9: =IF(2<='02_Assumptions'!$C$17,'04_Planting_Design'!$D$24*'02_Assumptions'!$C$138+'04_Planting_Design'!$D$25*'02_Assumptions'!$C$143,0) -> 0 | J9: =IF(3<='02_Assumptions'!$C$17,'04_Planting_Design'!$D$24*'02_Assumptions'!$D$138+'04_Planting_Design'!$D$25*'02_Assumptions'!$D$143,0) -> 0 | K9: =IF(4<='02_Assumptions'!$C$17,'04_Planting_Design'!$D$24*'02_Assumptions'!$E$138+'04_Planting_Design'!$D$25*'02_Assumptions'!$E$143,0) -> 0 | L9: =IF(5<='02_Assumptions'!$C$17,'04_Planting_Design'!$D$24*'02_Assumptions'!$F$138+'04_Planting_Design'!$D$25*'02_Assumptions'!$F$143,0) -> 0 | M9: =IF(6<='02_Assumptions'!$C$17,'04_Planting_Design'!$D$24*'02_Assumptions'!$G$138+'04_Planting_Design'!$D$25*'02_Assumptions'!$G$143,0) -> 0 | N9: =IF(7<='02_Assumptions'!$C$17,'04_Planting_Design'!$D$24*'02_Assumptions'!$H$138+'04_Planting_Design'!$D$25*'02_Assumptions'!$H$143,0) -> 0 | O9: =IF(8<='02_Assumptions'!$C$17,'04_Planting_Design'!$D$24*'02_Assumptions'!$I$138+'04_Planting_Design'!$D$25*'02_Assumptions'!$I$143,0) -> 0 | P9: =IF(9<='02_Assumptions'!$C$17,'04_Planting_Design'!$D$24*'02_Assumptions'!$J$138+'04_Planting_Design'!$D$25*'02_Assumptions'!$J$143,0) -> 0 | Q9: =IF(10<='02_Assumptions'!$C$17,'04_Planting_Design'!$D$24*'02_Assumptions'!$K$138+'04_Planting_Design'!$D$25*'02_Assumptions'!$K$143,0) -> 0 | R9: =SUM(H9:Q9) -> 0 | S9: =H9*$E9*(1+'02_Assumptions'!$C$11)^0+I9*$E9*(1+'02_Assumptions'!$C$11)^1+J9*$E9*(1+'02_Assumptions'!$C$11)^2+K9*$E9*(1+'02_Assumptions'!$C$11)^3+L9*$E9*(1+'02_Assumptions'!$C$11)^4+M9*$E9*(1+'02_Assumptions'!$C$11)^5+N9*$E9*(1+'02_Assumptions'!$C$11)^6+O9*$E9*(1+'02_Assumptions'!$C$11)^7+P9*$E9*(1+'02_Assumptions'!$C$11)^8+Q9*$E9*(1+'02_Assumptions'!$C$11)^9 -> 0 | T9: 1
A10: Organic matter | B10: Kompos matang | C10: Soil C, structure, microbial activity | D10: kg | E10: ='02_Assumptions'!$C$73 -> 1000 | F10: Permitted if compliant | G10: 50% of annual organic matter plan | H10: =0.5*(('04_Planting_Design'!$D$24+'04_Planting_Design'!$D$25)*'02_Assumptions'!$B$144+'04_Planting_Design'!$D$26*'02_Assumptions'!$B$123*'02_Assumptions'!$B$145) -> 124487 | I10: =0.5*(('04_Planting_Design'!$D$24+'04_Planting_Design'!$D$25)*'02_Assumptions'!$C$144+'04_Planting_Design'!$D$26*'02_Assumptions'!$C$123*'02_Assumptions'!$C$145) -> 137654 | J10: =0.5*(('04_Planting_Design'!$D$24+'04_Planting_Design'!$D$25)*'02_Assumptions'!$D$144+'04_Planting_Design'!$D$26*'02_Assumptions'!$D$123*'02_Assumptions'!$D$145) -> 140701 | K10: =0.5*(('04_Planting_Design'!$D$24+'04_Planting_Design'!$D$25)*'02_Assumptions'!$E$144+'04_Planting_Design'!$D$26*'02_Assumptions'!$E$123*'02_Assumptions'!$E$145) -> 106293 | L10: =0.5*(('04_Planting_Design'!$D$24+'04_Planting_Design'!$D$25)*'02_Assumptions'!$F$144+'04_Planting_Design'!$D$26*'02_Assumptions'!$F$123*'02_Assumptions'!$F$145) -> 113388 | M10: =0.5*(('04_Planting_Design'!$D$24+'04_Planting_Design'!$D$25)*'02_Assumptions'!$G$144+'04_Planting_Design'!$D$26*'02_Assumptions'!$G$123*'02_Assumptions'!$G$145) -> 102256 | N10: =0.5*(('04_Planting_Design'!$D$24+'04_Planting_Design'!$D$25)*'02_Assumptions'!$H$144+'04_Planting_Design'!$D$26*'02_Assumptions'!$H$123*'02_Assumptions'!$H$145) -> 122507 | O10: =0.5*(('04_Planting_Design'!$D$24+'04_Planting_Design'!$D$25)*'02_Assumptions'!$I$144+'04_Planting_Design'!$D$26*'02_Assumptions'!$I$123*'02_Assumptions'!$I$145) -> 122507 | P10: =0.5*(('04_Planting_Design'!$D$24+'04_Planting_Design'!$D$25)*'02_Assumptions'!$J$144+'04_Planting_Design'!$D$26*'02_Assumptions'!$J$123*'02_Assumptions'!$J$145) -> 122507 | Q10: =0.5*(('04_Planting_Design'!$D$24+'04_Planting_Design'!$D$25)*'02_Assumptions'!$K$144+'04_Planting_Design'!$D$26*'02_Assumptions'!$K$123*'02_Assumptions'!$K$145) -> 122507 | R10: =SUM(H10:Q10) -> 1214807 | S10: =H10*$E10*(1+'02_Assumptions'!$C$11)^0+I10*$E10*(1+'02_Assumptions'!$C$11)^1+J10*$E10*(1+'02_Assumptions'!$C$11)^2+K10*$E10*(1+'02_Assumptions'!$C$11)^3+L10*$E10*(1+'02_Assumptions'!$C$11)^4+M10*$E10*(1+'02_Assumptions'!$C$11)^5+N10*$E10*(1+'02_Assumptions'!$C$11)^6+O10*$E10*(1+'02_Assumptions'!$C$11)^7+P10*$E10*(1+'02_Assumptions'!$C$11)^8+Q10*$E10*(1+'02_Assumptions'!$C$11)^9 -> 1.4546988e+09 | T10: 1
A11: Organic matter | B11: Pupuk kandang fermented | C11: Organic nutrient & biology | D11: kg | E11: ='02_Assumptions'!$C$74 -> 900 | F11: Permitted if compliant | G11: 50%; verify maturity/pathogens/metals | H11: =0.5*(('04_Planting_Design'!$D$24+'04_Planting_Design'!$D$25)*'02_Assumptions'!$B$144+'04_Planting_Design'!$D$26*'02_Assumptions'!$B$123*'02_Assumptions'!$B$145) -> 124487 | I11: =0.5*(('04_Planting_Design'!$D$24+'04_Planting_Design'!$D$25)*'02_Assumptions'!$C$144+'04_Planting_Design'!$D$26*'02_Assumptions'!$C$123*'02_Assumptions'!$C$145) -> 137654 | J11: =0.5*(('04_Planting_Design'!$D$24+'04_Planting_Design'!$D$25)*'02_Assumptions'!$D$144+'04_Planting_Design'!$D$26*'02_Assumptions'!$D$123*'02_Assumptions'!$D$145) -> 140701 | K11: =0.5*(('04_Planting_Design'!$D$24+'04_Planting_Design'!$D$25)*'02_Assumptions'!$E$144+'04_Planting_Design'!$D$26*'02_Assumptions'!$E$123*'02_Assumptions'!$E$145) -> 106293 | L11: =0.5*(('04_Planting_Design'!$D$24+'04_Planting_Design'!$D$25)*'02_Assumptions'!$F$144+'04_Planting_Design'!$D$26*'02_Assumptions'!$F$123*'02_Assumptions'!$F$145) -> 113388 | M11: =0.5*(('04_Planting_Design'!$D$24+'04_Planting_Design'!$D$25)*'02_Assumptions'!$G$144+'04_Planting_Design'!$D$26*'02_Assumptions'!$G$123*'02_Assumptions'!$G$145) -> 102256 | N11: =0.5*(('04_Planting_Design'!$D$24+'04_Planting_Design'!$D$25)*'02_Assumptions'!$H$144+'04_Planting_Design'!$D$26*'02_Assumptions'!$H$123*'02_Assumptions'!$H$145) -> 122507 | O11: =0.5*(('04_Planting_Design'!$D$24+'04_Planting_Design'!$D$25)*'02_Assumptions'!$I$144+'04_Planting_Design'!$D$26*'02_Assumptions'!$I$123*'02_Assumptions'!$I$145) -> 122507 | P11: =0.5*(('04_Planting_Design'!$D$24+'04_Planting_Design'!$D$25)*'02_Assumptions'!$J$144+'04_Planting_Design'!$D$26*'02_Assumptions'!$J$123*'02_Assumptions'!$J$145) -> 122507 | Q11: =0.5*(('04_Planting_Design'!$D$24+'04_Planting_Design'!$D$25)*'02_Assumptions'!$K$144+'04_Planting_Design'!$D$26*'02_Assumptions'!$K$123*'02_Assumptions'!$K$145) -> 122507 | R11: =SUM(H11:Q11) -> 1214807 | S11: =H11*$E11*(1+'02_Assumptions'!$C$11)^0+I11*$E11*(1+'02_Assumptions'!$C$11)^1+J11*$E11*(1+'02_Assumptions'!$C$11)^2+K11*$E11*(1+'02_Assumptions'!$C$11)^3+L11*$E11*(1+'02_Assumptions'!$C$11)^4+M11*$E11*(1+'02_Assumptions'!$C$11)^5+N11*$E11*(1+'02_Assumptions'!$C$11)^6+O11*$E11*(1+'02_Assumptions'!$C$11)^7+P11*$E11*(1+'02_Assumptions'!$C$11)^8+Q11*$E11*(1+'02_Assumptions'!$C$11)^9 -> 1.3092289e+09 | T11: 1
A12: Amendment | B12: Dolomite maintenance | C12: pH, Ca, Mg | D12: kg | E12: ='02_Assumptions'!$C$75 -> 1500 | F12: Conditional | G12: Every 2y only if lime requirement supports | H12: =IF(MOD(1,2)=0,'02_Assumptions'!$C$6*'02_Assumptions'!$C$7*'02_Assumptions'!$C$110,0) -> 0 | I12: =IF(MOD(2,2)=0,'02_Assumptions'!$C$6*'02_Assumptions'!$C$7*'02_Assumptions'!$C$110,0) -> 44000 | J12: =IF(MOD(3,2)=0,'02_Assumptions'!$C$6*'02_Assumptions'!$C$7*'02_Assumptions'!$C$110,0) -> 0 | K12: =IF(MOD(4,2)=0,'02_Assumptions'!$C$6*'02_Assumptions'!$C$7*'02_Assumptions'!$C$110,0) -> 44000 | L12: =IF(MOD(5,2)=0,'02_Assumptions'!$C$6*'02_Assumptions'!$C$7*'02_Assumptions'!$C$110,0) -> 0 | M12: =IF(MOD(6,2)=0,'02_Assumptions'!$C$6*'02_Assumptions'!$C$7*'02_Assumptions'!$C$110,0) -> 44000 | N12: =IF(MOD(7,2)=0,'02_Assumptions'!$C$6*'02_Assumptions'!$C$7*'02_Assumptions'!$C$110,0) -> 0 | O12: =IF(MOD(8,2)=0,'02_Assumptions'!$C$6*'02_Assumptions'!$C$7*'02_Assumptions'!$C$110,0) -> 44000 | P12: =IF(MOD(9,2)=0,'02_Assumptions'!$C$6*'02_Assumptions'!$C$7*'02_Assumptions'!$C$110,0) -> 0 | Q12: =IF(MOD(10,2)=0,'02_Assumptions'!$C$6*'02_Assumptions'!$C$7*'02_Assumptions'!$C$110,0) -> 44000 | R12: =SUM(H12:Q12) -> 220000 | S12: =H12*$E12*(1+'02_Assumptions'!$C$11)^0+I12*$E12*(1+'02_Assumptions'!$C$11)^1+J12*$E12*(1+'02_Assumptions'!$C$11)^2+K12*$E12*(1+'02_Assumptions'!$C$11)^3+L12*$E12*(1+'02_Assumptions'!$C$11)^4+M12*$E12*(1+'02_Assumptions'!$C$11)^5+N12*$E12*(1+'02_Assumptions'!$C$11)^6+O12*$E12*(1+'02_Assumptions'!$C$11)^7+P12*$E12*(1+'02_Assumptions'!$C$11)^8+Q12*$E12*(1+'02_Assumptions'!$C$11)^9 -> 4.0397019e+08 | T12: 1
A13: Organic mineral | B13: Rock phosphate | C13: P in transition/organic phase | D13: kg | E13: ='02_Assumptions'!$C$76 -> 3000 | F13: LSO approval | G13: Starts after synthetic phase | H13: =IF(1>'02_Assumptions'!$C$17,('04_Planting_Design'!$D$24+'04_Planting_Design'!$D$25)*'02_Assumptions'!$C$111,0) -> 0 | I13: =IF(2>'02_Assumptions'!$C$17,('04_Planting_Design'!$D$24+'04_Planting_Design'!$D$25)*'02_Assumptions'!$C$111,0) -> 0 | J13: =IF(3>'02_Assumptions'!$C$17,('04_Planting_Design'!$D$24+'04_Planting_Design'!$D$25)*'02_Assumptions'!$C$111,0) -> 2794.44 | K13: =IF(4>'02_Assumptions'!$C$17,('04_Planting_Design'!$D$24+'04_Planting_Design'!$D$25)*'02_Assumptions'!$C$111,0) -> 2794.44 | L13: =IF(5>'02_Assumptions'!$C$17,('04_Planting_Design'!$D$24+'04_Planting_Design'!$D$25)*'02_Assumptions'!$C$111,0) -> 2794.44 | M13: =IF(6>'02_Assumptions'!$C$17,('04_Planting_Design'!$D$24+'04_Planting_Design'!$D$25)*'02_Assumptions'!$C$111,0) -> 2794.44 | N13: =IF(7>'02_Assumptions'!$C$17,('04_Planting_Design'!$D$24+'04_Planting_Design'!$D$25)*'02_Assumptions'!$C$111,0) -> 2794.44 | O13: =IF(8>'02_Assumptions'!$C$17,('04_Planting_Design'!$D$24+'04_Planting_Design'!$D$25)*'02_Assumptions'!$C$111,0) -> 2794.44 | P13: =IF(9>'02_Assumptions'!$C$17,('04_Planting_Design'!$D$24+'04_Planting_Design'!$D$25)*'02_Assumptions'!$C$111,0) -> 2794.44 | Q13: =IF(10>'02_Assumptions'!$C$17,('04_Planting_Design'!$D$24+'04_Planting_Design'!$D$25)*'02_Assumptions'!$C$111,0) -> 2794.44 | R13: =SUM(H13:Q13) -> 22355.52 | S13: =H13*$E13*(1+'02_Assumptions'!$C$11)^0+I13*$E13*(1+'02_Assumptions'!$C$11)^1+J13*$E13*(1+'02_Assumptions'!$C$11)^2+K13*$E13*(1+'02_Assumptions'!$C$11)^3+L13*$E13*(1+'02_Assumptions'!$C$11)^4+M13*$E13*(1+'02_Assumptions'!$C$11)^5+N13*$E13*(1+'02_Assumptions'!$C$11)^6+O13*$E13*(1+'02_Assumptions'!$C$11)^7+P13*$E13*(1+'02_Assumptions'!$C$11)^8+Q13*$E13*(1+'02_Assumptions'!$C$11)^9 -> 83549065 | T13: 1
A14: Organic mineral | B14: Approved K/Mg input | C14: K/Mg in transition/organic phase | D14: kg | E14: ='02_Assumptions'!$C$77 -> 8000 | F14: LSO approval | G14: Leaf-test driven | H14: =IF(1>'02_Assumptions'!$C$17,('04_Planting_Design'!$D$24+'04_Planting_Design'!$D$25)*'02_Assumptions'!$C$112,0) -> 0 | I14: =IF(2>'02_Assumptions'!$C$17,('04_Planting_Design'!$D$24+'04_Planting_Design'!$D$25)*'02_Assumptions'!$C$112,0) -> 0 | J14: =IF(3>'02_Assumptions'!$C$17,('04_Planting_Design'!$D$24+'04_Planting_Design'!$D$25)*'02_Assumptions'!$C$112,0) -> 4657.4 | K14: =IF(4>'02_Assumptions'!$C$17,('04_Planting_Design'!$D$24+'04_Planting_Design'!$D$25)*'02_Assumptions'!$C$112,0) -> 4657.4 | L14: =IF(5>'02_Assumptions'!$C$17,('04_Planting_Design'!$D$24+'04_Planting_Design'!$D$25)*'02_Assumptions'!$C$112,0) -> 4657.4 | M14: =IF(6>'02_Assumptions'!$C$17,('04_Planting_Design'!$D$24+'04_Planting_Design'!$D$25)*'02_Assumptions'!$C$112,0) -> 4657.4 | N14: =IF(7>'02_Assumptions'!$C$17,('04_Planting_Design'!$D$24+'04_Planting_Design'!$D$25)*'02_Assumptions'!$C$112,0) -> 4657.4 | O14: =IF(8>'02_Assumptions'!$C$17,('04_Planting_Design'!$D$24+'04_Planting_Design'!$D$25)*'02_Assumptions'!$C$112,0) -> 4657.4 | P14: =IF(9>'02_Assumptions'!$C$17,('04_Planting_Design'!$D$24+'04_Planting_Design'!$D$25)*'02_Assumptions'!$C$112,0) -> 4657.4 | Q14: =IF(10>'02_Assumptions'!$C$17,('04_Planting_Design'!$D$24+'04_Planting_Design'!$D$25)*'02_Assumptions'!$C$112,0) -> 4657.4 | R14: =SUM(H14:Q14) -> 37259.2 | S14: =H14*$E14*(1+'02_Assumptions'!$C$11)^0+I14*$E14*(1+'02_Assumptions'!$C$11)^1+J14*$E14*(1+'02_Assumptions'!$C$11)^2+K14*$E14*(1+'02_Assumptions'!$C$11)^3+L14*$E14*(1+'02_Assumptions'!$C$11)^4+M14*$E14*(1+'02_Assumptions'!$C$11)^5+N14*$E14*(1+'02_Assumptions'!$C$11)^6+O14*$E14*(1+'02_Assumptions'!$C$11)^7+P14*$E14*(1+'02_Assumptions'!$C$11)^8+Q14*$E14*(1+'02_Assumptions'!$C$11)^9 -> 3.7132918e+08 | T14: 1
A15: Biological | B15: Trichoderma/Gliocladium | C15: Soil-borne disease suppression | D15: kg | E15: ='02_Assumptions'!$C$78 -> 35000 | F15: Generally permitted | G15: 2 applications; carrier quality critical | H15: ='02_Assumptions'!$C$6*'02_Assumptions'!$C$7*10 -> 880 | I15: ='02_Assumptions'!$C$6*'02_Assumptions'!$C$7*10 -> 880 | J15: ='02_Assumptions'!$C$6*'02_Assumptions'!$C$7*10 -> 880 | K15: ='02_Assumptions'!$C$6*'02_Assumptions'!$C$7*10 -> 880 | L15: ='02_Assumptions'!$C$6*'02_Assumptions'!$C$7*10 -> 880 | M15: ='02_Assumptions'!$C$6*'02_Assumptions'!$C$7*10 -> 880 | N15: ='02_Assumptions'!$C$6*'02_Assumptions'!$C$7*10 -> 880 | O15: ='02_Assumptions'!$C$6*'02_Assumptions'!$C$7*10 -> 880 | ... Q15: ='02_Assumptions'!$C$6*'02_Assumptions'!$C$7*10 -> 880 | R15: =SUM(H15:Q15) -> 8800 | S15: =H15*$E15*(1+'02_Assumptions'!$C$11)^0+I15*$E15*(1+'02_Assumptions'!$C$11)^1+J15*$E15*(1+'02_Assumptions'!$C$11)^2+K15*$E15*(1+'02_Assumptions'!$C$11)^3+L15*$E15*(1+'02_Assumptions'!$C$11)^4+M15*$E15*(1+'02_Assumptions'!$C$11)^5+N15*$E15*(1+'02_Assumptions'!$C$11)^6+O15*$E15*(1+'02_Assumptions'!$C$11)^7+P15*$E15*(1+'02_Assumptions'!$C$11)^8+Q15*$E15*(1+'02_Assumptions'!$C$11)^9 -> 3.697881e+08 | T15: 1
A16: Bioinsecticide | B16: Beauveria/Metarhizium | C16: Banana weevil/coconut beetle IPM | D16: kg | E16: ='02_Assumptions'!$C$79 -> 120000 | F16: Generally permitted | G16: 2 targeted rounds; humidity/viability matter | H16: ='02_Assumptions'!$C$6*'02_Assumptions'!$C$7*4 -> 352 | I16: ='02_Assumptions'!$C$6*'02_Assumptions'!$C$7*4 -> 352 | J16: ='02_Assumptions'!$C$6*'02_Assumptions'!$C$7*4 -> 352 | K16: ='02_Assumptions'!$C$6*'02_Assumptions'!$C$7*4 -> 352 | L16: ='02_Assumptions'!$C$6*'02_Assumptions'!$C$7*4 -> 352 | M16: ='02_Assumptions'!$C$6*'02_Assumptions'!$C$7*4 -> 352 | N16: ='02_Assumptions'!$C$6*'02_Assumptions'!$C$7*4 -> 352 | O16: ='02_Assumptions'!$C$6*'02_Assumptions'!$C$7*4 -> 352 | ... Q16: ='02_Assumptions'!$C$6*'02_Assumptions'!$C$7*4 -> 352 | R16: =SUM(H16:Q16) -> 3520 | S16: =H16*$E16*(1+'02_Assumptions'!$C$11)^0+I16*$E16*(1+'02_Assumptions'!$C$11)^1+J16*$E16*(1+'02_Assumptions'!$C$11)^2+K16*$E16*(1+'02_Assumptions'!$C$11)^3+L16*$E16*(1+'02_Assumptions'!$C$11)^4+M16*$E16*(1+'02_Assumptions'!$C$11)^5+N16*$E16*(1+'02_Assumptions'!$C$11)^6+O16*$E16*(1+'02_Assumptions'!$C$11)^7+P16*$E16*(1+'02_Assumptions'!$C$11)^8+Q16*$E16*(1+'02_Assumptions'!$C$11)^9 -> 5.0713796e+08 | T16: 1
A17: Bioinsecticide | B17: Bacillus thuringiensis | C17: Caterpillars only | D17: kg | E17: ='02_Assumptions'!$C$80 -> 180000 | F17: Generally permitted | G17: 2 rounds allowance, threshold-based | H17: ='02_Assumptions'!$C$6*'02_Assumptions'!$C$7*2 -> 176 | I17: ='02_Assumptions'!$C$6*'02_Assumptions'!$C$7*2 -> 176 | J17: ='02_Assumptions'!$C$6*'02_Assumptions'!$C$7*2 -> 176 | K17: ='02_Assumptions'!$C$6*'02_Assumptions'!$C$7*2 -> 176 | L17: ='02_Assumptions'!$C$6*'02_Assumptions'!$C$7*2 -> 176 | M17: ='02_Assumptions'!$C$6*'02_Assumptions'!$C$7*2 -> 176 | N17: ='02_Assumptions'!$C$6*'02_Assumptions'!$C$7*2 -> 176 | O17: ='02_Assumptions'!$C$6*'02_Assumptions'!$C$7*2 -> 176 | ... Q17: ='02_Assumptions'!$C$6*'02_Assumptions'!$C$7*2 -> 176 | R17: =SUM(H17:Q17) -> 1760 | S17: =H17*$E17*(1+'02_Assumptions'!$C$11)^0+I17*$E17*(1+'02_Assumptions'!$C$11)^1+J17*$E17*(1+'02_Assumptions'!$C$11)^2+K17*$E17*(1+'02_Assumptions'!$C$11)^3+L17*$E17*(1+'02_Assumptions'!$C$11)^4+M17*$E17*(1+'02_Assumptions'!$C$11)^5+N17*$E17*(1+'02_Assumptions'!$C$11)^6+O17*$E17*(1+'02_Assumptions'!$C$11)^7+P17*$E17*(1+'02_Assumptions'!$C$11)^8+Q17*$E17*(1+'02_Assumptions'!$C$11)^9 -> 3.8035347e+08 | T17: 1
A18: Botanical | B18: Neem/azadirachtin | C18: Sucking/chewing pest suppression | D18: L | E18: ='02_Assumptions'!$C$81 -> 120000 | F18: Check product | G18: 3 targeted rounds; not calendar spraying | H18: ='02_Assumptions'!$C$6*'02_Assumptions'!$C$7*9 -> 792 | I18: ='02_Assumptions'!$C$6*'02_Assumptions'!$C$7*9 -> 792 | J18: ='02_Assumptions'!$C$6*'02_Assumptions'!$C$7*9 -> 792 | K18: ='02_Assumptions'!$C$6*'02_Assumptions'!$C$7*9 -> 792 | L18: ='02_Assumptions'!$C$6*'02_Assumptions'!$C$7*9 -> 792 | M18: ='02_Assumptions'!$C$6*'02_Assumptions'!$C$7*9 -> 792 | N18: ='02_Assumptions'!$C$6*'02_Assumptions'!$C$7*9 -> 792 | O18: ='02_Assumptions'!$C$6*'02_Assumptions'!$C$7*9 -> 792 | ... Q18: ='02_Assumptions'!$C$6*'02_Assumptions'!$C$7*9 -> 792 | R18: =SUM(H18:Q18) -> 7920 | S18: =H18*$E18*(1+'02_Assumptions'!$C$11)^0+I18*$E18*(1+'02_Assumptions'!$C$11)^1+J18*$E18*(1+'02_Assumptions'!$C$11)^2+K18*$E18*(1+'02_Assumptions'!$C$11)^3+L18*$E18*(1+'02_Assumptions'!$C$11)^4+M18*$E18*(1+'02_Assumptions'!$C$11)^5+N18*$E18*(1+'02_Assumptions'!$C$11)^6+O18*$E18*(1+'02_Assumptions'!$C$11)^7+P18*$E18*(1+'02_Assumptions'!$C$11)^8+Q18*$E18*(1+'02_Assumptions'!$C$11)^9 -> 1.1410604e+09 | T18: 1
A19: Fungicide | B19: Copper-based input | C19: Diagnosed fungal/bacterial hotspots | D19: kg | E19: ='02_Assumptions'!$C$82 -> 150000 | F19: Restricted/LSO approval | G19: 50% area x 2 rounds allowance | H19: ='02_Assumptions'!$C$6*'02_Assumptions'!$C$7*2 -> 176 | I19: ='02_Assumptions'!$C$6*'02_Assumptions'!$C$7*2 -> 176 | J19: ='02_Assumptions'!$C$6*'02_Assumptions'!$C$7*2 -> 176 | K19: ='02_Assumptions'!$C$6*'02_Assumptions'!$C$7*2 -> 176 | L19: ='02_Assumptions'!$C$6*'02_Assumptions'!$C$7*2 -> 176 | M19: ='02_Assumptions'!$C$6*'02_Assumptions'!$C$7*2 -> 176 | N19: ='02_Assumptions'!$C$6*'02_Assumptions'!$C$7*2 -> 176 | O19: ='02_Assumptions'!$C$6*'02_Assumptions'!$C$7*2 -> 176 | ... Q19: ='02_Assumptions'!$C$6*'02_Assumptions'!$C$7*2 -> 176 | R19: =SUM(H19:Q19) -> 1760 | S19: =H19*$E19*(1+'02_Assumptions'!$C$11)^0+I19*$E19*(1+'02_Assumptions'!$C$11)^1+J19*$E19*(1+'02_Assumptions'!$C$11)^2+K19*$E19*(1+'02_Assumptions'!$C$11)^3+L19*$E19*(1+'02_Assumptions'!$C$11)^4+M19*$E19*(1+'02_Assumptions'!$C$11)^5+N19*$E19*(1+'02_Assumptions'!$C$11)^6+O19*$E19*(1+'02_Assumptions'!$C$11)^7+P19*$E19*(1+'02_Assumptions'!$C$11)^8+Q19*$E19*(1+'02_Assumptions'!$C$11)^9 -> 3.1696123e+08 | T19: 1
A20: Monitoring | B20: Pheromone lure | C20: Oryctes/Rhynchophorus surveillance | D20: lure | E20: ='02_Assumptions'!$C$84 -> 200000 | F20: Permitted | G20: 1 trap/2 ha, lure quarterly | H20: ='02_Assumptions'!$C$6*'02_Assumptions'!$C$7/2*4 -> 176 | I20: ='02_Assumptions'!$C$6*'02_Assumptions'!$C$7/2*4 -> 176 | J20: ='02_Assumptions'!$C$6*'02_Assumptions'!$C$7/2*4 -> 176 | K20: ='02_Assumptions'!$C$6*'02_Assumptions'!$C$7/2*4 -> 176 | L20: ='02_Assumptions'!$C$6*'02_Assumptions'!$C$7/2*4 -> 176 | M20: ='02_Assumptions'!$C$6*'02_Assumptions'!$C$7/2*4 -> 176 | N20: ='02_Assumptions'!$C$6*'02_Assumptions'!$C$7/2*4 -> 176 | O20: ='02_Assumptions'!$C$6*'02_Assumptions'!$C$7/2*4 -> 176 | ... Q20: ='02_Assumptions'!$C$6*'02_Assumptions'!$C$7/2*4 -> 176 | R20: =SUM(H20:Q20) -> 1760 | S20: =H20*$E20*(1+'02_Assumptions'!$C$11)^0+I20*$E20*(1+'02_Assumptions'!$C$11)^1+J20*$E20*(1+'02_Assumptions'!$C$11)^2+K20*$E20*(1+'02_Assumptions'!$C$11)^3+L20*$E20*(1+'02_Assumptions'!$C$11)^4+M20*$E20*(1+'02_Assumptions'!$C$11)^5+N20*$E20*(1+'02_Assumptions'!$C$11)^6+O20*$E20*(1+'02_Assumptions'!$C$11)^7+P20*$E20*(1+'02_Assumptions'!$C$11)^8+Q20*$E20*(1+'02_Assumptions'!$C$11)^9 -> 4.2261497e+08 | T20: 1
A21: Monitoring | B21: Sticky trap | C21: Monitoring flying insects | D21: unit | E21: ='02_Assumptions'!$C$85 -> 5000 | F21: Permitted | G21: 10/ha x 2 replacements | H21: ='02_Assumptions'!$C$6*'02_Assumptions'!$C$7*20 -> 1760 | I21: ='02_Assumptions'!$C$6*'02_Assumptions'!$C$7*20 -> 1760 | J21: ='02_Assumptions'!$C$6*'02_Assumptions'!$C$7*20 -> 1760 | K21: ='02_Assumptions'!$C$6*'02_Assumptions'!$C$7*20 -> 1760 | L21: ='02_Assumptions'!$C$6*'02_Assumptions'!$C$7*20 -> 1760 | M21: ='02_Assumptions'!$C$6*'02_Assumptions'!$C$7*20 -> 1760 | N21: ='02_Assumptions'!$C$6*'02_Assumptions'!$C$7*20 -> 1760 | O21: ='02_Assumptions'!$C$6*'02_Assumptions'!$C$7*20 -> 1760 | ... Q21: ='02_Assumptions'!$C$6*'02_Assumptions'!$C$7*20 -> 1760 | R21: =SUM(H21:Q21) -> 17600 | S21: =H21*$E21*(1+'02_Assumptions'!$C$11)^0+I21*$E21*(1+'02_Assumptions'!$C$11)^1+J21*$E21*(1+'02_Assumptions'!$C$11)^2+K21*$E21*(1+'02_Assumptions'!$C$11)^3+L21*$E21*(1+'02_Assumptions'!$C$11)^4+M21*$E21*(1+'02_Assumptions'!$C$11)^5+N21*$E21*(1+'02_Assumptions'!$C$11)^6+O21*$E21*(1+'02_Assumptions'!$C$11)^7+P21*$E21*(1+'02_Assumptions'!$C$11)^8+Q21*$E21*(1+'02_Assumptions'!$C$11)^9 -> 1.0565374e+08 | T21: 1
A22: Biosecurity | B22: Disinfectant | C22: Tools, footwear, nursery | D22: L | E22: ='02_Assumptions'!$C$86 -> 50000 | F22: Check product | G22: Dedicated banana tools/footbath | H22: ='02_Assumptions'!$C$6*'02_Assumptions'!$C$7*2 -> 176 | I22: ='02_Assumptions'!$C$6*'02_Assumptions'!$C$7*2 -> 176 | J22: ='02_Assumptions'!$C$6*'02_Assumptions'!$C$7*2 -> 176 | K22: ='02_Assumptions'!$C$6*'02_Assumptions'!$C$7*2 -> 176 | L22: ='02_Assumptions'!$C$6*'02_Assumptions'!$C$7*2 -> 176 | M22: ='02_Assumptions'!$C$6*'02_Assumptions'!$C$7*2 -> 176 | N22: ='02_Assumptions'!$C$6*'02_Assumptions'!$C$7*2 -> 176 | O22: ='02_Assumptions'!$C$6*'02_Assumptions'!$C$7*2 -> 176 | ... Q22: ='02_Assumptions'!$C$6*'02_Assumptions'!$C$7*2 -> 176 | R22: =SUM(H22:Q22) -> 1760 | S22: =H22*$E22*(1+'02_Assumptions'!$C$11)^0+I22*$E22*(1+'02_Assumptions'!$C$11)^1+J22*$E22*(1+'02_Assumptions'!$C$11)^2+K22*$E22*(1+'02_Assumptions'!$C$11)^3+L22*$E22*(1+'02_Assumptions'!$C$11)^4+M22*$E22*(1+'02_Assumptions'!$C$11)^5+N22*$E22*(1+'02_Assumptions'!$C$11)^6+O22*$E22*(1+'02_Assumptions'!$C$11)^7+P22*$E22*(1+'02_Assumptions'!$C$11)^8+Q22*$E22*(1+'02_Assumptions'!$C$11)^9 -> 1.0565374e+08 | T22: 1
A23: Herbicide | B23: Glyphosate spot only | C23: Hard-to-control weeds | D23: L | E23: ='02_Assumptions'!$C$83 -> 65000 | F23: Prohibited organic | G23: Transition years only; no paraquat; spot, not blanket | H23: =IF(1<='02_Assumptions'!$C$17,'02_Assumptions'!$C$6*'02_Assumptions'!$C$7*2,0) -> 176 | I23: =IF(2<='02_Assumptions'!$C$17,'02_Assumptions'!$C$6*'02_Assumptions'!$C$7*2,0) -> 176 | J23: =IF(3<='02_Assumptions'!$C$17,'02_Assumptions'!$C$6*'02_Assumptions'!$C$7*2,0) -> 0 | K23: =IF(4<='02_Assumptions'!$C$17,'02_Assumptions'!$C$6*'02_Assumptions'!$C$7*2,0) -> 0 | L23: =IF(5<='02_Assumptions'!$C$17,'02_Assumptions'!$C$6*'02_Assumptions'!$C$7*2,0) -> 0 | M23: =IF(6<='02_Assumptions'!$C$17,'02_Assumptions'!$C$6*'02_Assumptions'!$C$7*2,0) -> 0 | N23: =IF(7<='02_Assumptions'!$C$17,'02_Assumptions'!$C$6*'02_Assumptions'!$C$7*2,0) -> 0 | O23: =IF(8<='02_Assumptions'!$C$17,'02_Assumptions'!$C$6*'02_Assumptions'!$C$7*2,0) -> 0 | P23: =IF(9<='02_Assumptions'!$C$17,'02_Assumptions'!$C$6*'02_Assumptions'!$C$7*2,0) -> 0 | Q23: =IF(10<='02_Assumptions'!$C$17,'02_Assumptions'!$C$6*'02_Assumptions'!$C$7*2,0) -> 0 | R23: =SUM(H23:Q23) -> 352 | S23: =H23*$E23*(1+'02_Assumptions'!$C$11)^0+I23*$E23*(1+'02_Assumptions'!$C$11)^1+J23*$E23*(1+'02_Assumptions'!$C$11)^2+K23*$E23*(1+'02_Assumptions'!$C$11)^3+L23*$E23*(1+'02_Assumptions'!$C$11)^4+M23*$E23*(1+'02_Assumptions'!$C$11)^5+N23*$E23*(1+'02_Assumptions'!$C$11)^6+O23*$E23*(1+'02_Assumptions'!$C$11)^7+P23*$E23*(1+'02_Assumptions'!$C$11)^8+Q23*$E23*(1+'02_Assumptions'!$C$11)^9 -> 23337600 | T23: 1
A24: Chemical contingency | B24: Registered fungicide | C24: Only laboratory/field diagnosis | D24: kg | E24: ='02_Assumptions'!$C$87 -> 250000 | F24: Prohibited organic | G24: 25% hotspot allowance in transition | H24: =IF(1<='02_Assumptions'!$C$17,'02_Assumptions'!$C$6*'02_Assumptions'!$C$7*0.5,0) -> 44 | I24: =IF(2<='02_Assumptions'!$C$17,'02_Assumptions'!$C$6*'02_Assumptions'!$C$7*0.5,0) -> 44 | J24: =IF(3<='02_Assumptions'!$C$17,'02_Assumptions'!$C$6*'02_Assumptions'!$C$7*0.5,0) -> 0 | K24: =IF(4<='02_Assumptions'!$C$17,'02_Assumptions'!$C$6*'02_Assumptions'!$C$7*0.5,0) -> 0 | L24: =IF(5<='02_Assumptions'!$C$17,'02_Assumptions'!$C$6*'02_Assumptions'!$C$7*0.5,0) -> 0 | M24: =IF(6<='02_Assumptions'!$C$17,'02_Assumptions'!$C$6*'02_Assumptions'!$C$7*0.5,0) -> 0 | N24: =IF(7<='02_Assumptions'!$C$17,'02_Assumptions'!$C$6*'02_Assumptions'!$C$7*0.5,0) -> 0 | O24: =IF(8<='02_Assumptions'!$C$17,'02_Assumptions'!$C$6*'02_Assumptions'!$C$7*0.5,0) -> 0 | P24: =IF(9<='02_Assumptions'!$C$17,'02_Assumptions'!$C$6*'02_Assumptions'!$C$7*0.5,0) -> 0 | Q24: =IF(10<='02_Assumptions'!$C$17,'02_Assumptions'!$C$6*'02_Assumptions'!$C$7*0.5,0) -> 0 | R24: =SUM(H24:Q24) -> 88 | S24: =H24*$E24*(1+'02_Assumptions'!$C$11)^0+I24*$E24*(1+'02_Assumptions'!$C$11)^1+J24*$E24*(1+'02_Assumptions'!$C$11)^2+K24*$E24*(1+'02_Assumptions'!$C$11)^3+L24*$E24*(1+'02_Assumptions'!$C$11)^4+M24*$E24*(1+'02_Assumptions'!$C$11)^5+N24*$E24*(1+'02_Assumptions'!$C$11)^6+O24*$E24*(1+'02_Assumptions'!$C$11)^7+P24*$E24*(1+'02_Assumptions'!$C$11)^8+Q24*$E24*(1+'02_Assumptions'!$C$11)^9 -> 22440000 | T24: 1
A25: Chemical contingency | B25: Registered insecticide | C25: Only threshold & registered label | D25: L | E25: ='02_Assumptions'!$C$88 -> 300000 | F25: Prohibited organic | G25: 25% hotspot allowance in transition | H25: =IF(1<='02_Assumptions'!$C$17,'02_Assumptions'!$C$6*'02_Assumptions'!$C$7*0.25,0) -> 22 | I25: =IF(2<='02_Assumptions'!$C$17,'02_Assumptions'!$C$6*'02_Assumptions'!$C$7*0.25,0) -> 22 | J25: =IF(3<='02_Assumptions'!$C$17,'02_Assumptions'!$C$6*'02_Assumptions'!$C$7*0.25,0) -> 0 | K25: =IF(4<='02_Assumptions'!$C$17,'02_Assumptions'!$C$6*'02_Assumptions'!$C$7*0.25,0) -> 0 | L25: =IF(5<='02_Assumptions'!$C$17,'02_Assumptions'!$C$6*'02_Assumptions'!$C$7*0.25,0) -> 0 | M25: =IF(6<='02_Assumptions'!$C$17,'02_Assumptions'!$C$6*'02_Assumptions'!$C$7*0.25,0) -> 0 | N25: =IF(7<='02_Assumptions'!$C$17,'02_Assumptions'!$C$6*'02_Assumptions'!$C$7*0.25,0) -> 0 | O25: =IF(8<='02_Assumptions'!$C$17,'02_Assumptions'!$C$6*'02_Assumptions'!$C$7*0.25,0) -> 0 | P25: =IF(9<='02_Assumptions'!$C$17,'02_Assumptions'!$C$6*'02_Assumptions'!$C$7*0.25,0) -> 0 | Q25: =IF(10<='02_Assumptions'!$C$17,'02_Assumptions'!$C$6*'02_Assumptions'!$C$7*0.25,0) -> 0 | R25: =SUM(H25:Q25) -> 44 | S25: =H25*$E25*(1+'02_Assumptions'!$C$11)^0+I25*$E25*(1+'02_Assumptions'!$C$11)^1+J25*$E25*(1+'02_Assumptions'!$C$11)^2+K25*$E25*(1+'02_Assumptions'!$C$11)^3+L25*$E25*(1+'02_Assumptions'!$C$11)^4+M25*$E25*(1+'02_Assumptions'!$C$11)^5+N25*$E25*(1+'02_Assumptions'!$C$11)^6+O25*$E25*(1+'02_Assumptions'!$C$11)^7+P25*$E25*(1+'02_Assumptions'!$C$11)^8+Q25*$E25*(1+'02_Assumptions'!$C$11)^9 -> 13464000 | T25: 1
A28: B. Ringkasan biaya input pertanian tahunan
A29: Kelompok biaya | B29: T1 | C29: T2 | D29: T3 | E29: T4 | F29: T5 | G29: T6 | H29: T7 | I29: T8 | J29: T9 | K29: T10
A30: Pupuk sintetis | B30: =SUMPRODUCT(H$5:H$9,$E$5:$E$9,$T$5:$T$9)*(1+'02_Assumptions'!$C$11)^0 -> 210837220 | C30: =SUMPRODUCT(I$5:I$9,$E$5:$E$9,$T$5:$T$9)*(1+'02_Assumptions'!$C$11)^1 -> 2.2883487e+08 | D30: =SUMPRODUCT(J$5:J$9,$E$5:$E$9,$T$5:$T$9)*(1+'02_Assumptions'!$C$11)^2 -> 0 | E30: =SUMPRODUCT(K$5:K$9,$E$5:$E$9,$T$5:$T$9)*(1+'02_Assumptions'!$C$11)^3 -> 0 | F30: =SUMPRODUCT(L$5:L$9,$E$5:$E$9,$T$5:$T$9)*(1+'02_Assumptions'!$C$11)^4 -> 0 | G30: =SUMPRODUCT(M$5:M$9,$E$5:$E$9,$T$5:$T$9)*(1+'02_Assumptions'!$C$11)^5 -> 0 | H30: =SUMPRODUCT(N$5:N$9,$E$5:$E$9,$T$5:$T$9)*(1+'02_Assumptions'!$C$11)^6 -> 0 | I30: =SUMPRODUCT(O$5:O$9,$E$5:$E$9,$T$5:$T$9)*(1+'02_Assumptions'!$C$11)^7 -> 0 | J30: =SUMPRODUCT(P$5:P$9,$E$5:$E$9,$T$5:$T$9)*(1+'02_Assumptions'!$C$11)^8 -> 0 | K30: =SUMPRODUCT(Q$5:Q$9,$E$5:$E$9,$T$5:$T$9)*(1+'02_Assumptions'!$C$11)^9 -> 0
A31: Bahan organik dan tanah | B31: =SUMPRODUCT(H$10:H$14,$E$10:$E$14,$T$10:$T$14)*(1+'02_Assumptions'!$C$11)^0 -> 236525300 | C31: =SUMPRODUCT(I$10:I$14,$E$10:$E$14,$T$10:$T$14)*(1+'02_Assumptions'!$C$11)^1 -> 340644304 | D31: =SUMPRODUCT(J$10:J$14,$E$10:$E$14,$T$10:$T$14)*(1+'02_Assumptions'!$C$11)^2 -> 3.3851313e+08 | E31: =SUMPRODUCT(K$10:K$14,$E$10:$E$14,$T$10:$T$14)*(1+'02_Assumptions'!$C$11)^3 -> 3.5275647e+08 | F31: =SUMPRODUCT(L$10:L$14,$E$10:$E$14,$T$10:$T$14)*(1+'02_Assumptions'!$C$11)^4 -> 3.0542635e+08 | G31: =SUMPRODUCT(M$10:M$14,$E$10:$E$14,$T$10:$T$14)*(1+'02_Assumptions'!$C$11)^5 -> 3.7220931e+08 | H31: =SUMPRODUCT(N$10:N$14,$E$10:$E$14,$T$10:$T$14)*(1+'02_Assumptions'!$C$11)^6 -> 3.5227218e+08 | I31: =SUMPRODUCT(O$10:O$14,$E$10:$E$14,$T$10:$T$14)*(1+'02_Assumptions'!$C$11)^7 -> 4.5321456e+08 | J31: =SUMPRODUCT(P$10:P$14,$E$10:$E$14,$T$10:$T$14)*(1+'02_Assumptions'!$C$11)^8 -> 3.8101759e+08 | K31: =SUMPRODUCT(Q$10:Q$14,$E$10:$E$14,$T$10:$T$14)*(1+'02_Assumptions'!$C$11)^9 -> 4.9019687e+08
A32: Biologi dan PHT | B32: =SUMPRODUCT(H$15:H$22,$E$15:$E$22,$T$15:$T$22)*(1+'02_Assumptions'!$C$11)^0 -> 278960000 | C32: =SUMPRODUCT(I$15:I$22,$E$15:$E$22,$T$15:$T$22)*(1+'02_Assumptions'!$C$11)^1 -> 290118400 | D32: =SUMPRODUCT(J$15:J$22,$E$15:$E$22,$T$15:$T$22)*(1+'02_Assumptions'!$C$11)^2 -> 3.0172314e+08 | E32: =SUMPRODUCT(K$15:K$22,$E$15:$E$22,$T$15:$T$22)*(1+'02_Assumptions'!$C$11)^3 -> 3.1379206e+08 | F32: =SUMPRODUCT(L$15:L$22,$E$15:$E$22,$T$15:$T$22)*(1+'02_Assumptions'!$C$11)^4 -> 3.2634374e+08 | G32: =SUMPRODUCT(M$15:M$22,$E$15:$E$22,$T$15:$T$22)*(1+'02_Assumptions'!$C$11)^5 -> 3.3939749e+08 | H32: =SUMPRODUCT(N$15:N$22,$E$15:$E$22,$T$15:$T$22)*(1+'02_Assumptions'!$C$11)^6 -> 3.5297339e+08 | I32: =SUMPRODUCT(O$15:O$22,$E$15:$E$22,$T$15:$T$22)*(1+'02_Assumptions'!$C$11)^7 -> 3.6709233e+08 | J32: =SUMPRODUCT(P$15:P$22,$E$15:$E$22,$T$15:$T$22)*(1+'02_Assumptions'!$C$11)^8 -> 3.8177602e+08 | K32: =SUMPRODUCT(Q$15:Q$22,$E$15:$E$22,$T$15:$T$22)*(1+'02_Assumptions'!$C$11)^9 -> 3.9704706e+08
A33: Proteksi konvensional | B33: =SUMPRODUCT(H$23:H$25,$E$23:$E$25,$T$23:$T$25)*(1+'02_Assumptions'!$C$11)^0 -> 29040000 | C33: =SUMPRODUCT(I$23:I$25,$E$23:$E$25,$T$23:$T$25)*(1+'02_Assumptions'!$C$11)^1 -> 30201600 | D33: =SUMPRODUCT(J$23:J$25,$E$23:$E$25,$T$23:$T$25)*(1+'02_Assumptions'!$C$11)^2 -> 0 | E33: =SUMPRODUCT(K$23:K$25,$E$23:$E$25,$T$23:$T$25)*(1+'02_Assumptions'!$C$11)^3 -> 0 | F33: =SUMPRODUCT(L$23:L$25,$E$23:$E$25,$T$23:$T$25)*(1+'02_Assumptions'!$C$11)^4 -> 0 | G33: =SUMPRODUCT(M$23:M$25,$E$23:$E$25,$T$23:$T$25)*(1+'02_Assumptions'!$C$11)^5 -> 0 | H33: =SUMPRODUCT(N$23:N$25,$E$23:$E$25,$T$23:$T$25)*(1+'02_Assumptions'!$C$11)^6 -> 0 | I33: =SUMPRODUCT(O$23:O$25,$E$23:$E$25,$T$23:$T$25)*(1+'02_Assumptions'!$C$11)^7 -> 0 | J33: =SUMPRODUCT(P$23:P$25,$E$23:$E$25,$T$23:$T$25)*(1+'02_Assumptions'!$C$11)^8 -> 0 | K33: =SUMPRODUCT(Q$23:Q$25,$E$23:$E$25,$T$23:$T$25)*(1+'02_Assumptions'!$C$11)^9 -> 0
A34: TOTAL BIAYA INPUT PERTANIAN | B34: =SUM(B30:B33)+'17_Model_Fleksibel'!$O$52 -> 904962520 | C34: =SUM(C30:C33)+'17_Model_Fleksibel'!$P$52 -> 9.8703917e+08 | D34: =SUM(D30:D33)+'17_Model_Fleksibel'!$Q$52 -> 6.9080107e+08 | E34: =SUM(E30:E33)+'17_Model_Fleksibel'!$R$52 -> 6.6654853e+08 | F34: =SUM(F30:F33)+'17_Model_Fleksibel'!$S$52 -> 6.3177009e+08 | G34: =SUM(G30:G33)+'17_Model_Fleksibel'!$T$52 -> 7.116068e+08 | H34: =SUM(H30:H33)+'17_Model_Fleksibel'!$U$52 -> 7.0524557e+08 | I34: =SUM(I30:I33)+'17_Model_Fleksibel'!$V$52 -> 8.2030689e+08 | J34: =SUM(J30:J33)+'17_Model_Fleksibel'!$W$52 -> 7.6279361e+08 | K34: =SUM(K30:K33)+'17_Model_Fleksibel'!$X$52 -> 8.8724394e+08

Sheet 08_CAPEX_RAB
A1: RAB CAPEX Rinci: 1 Lokasi dan 4 Lokasi
A2: Rincian investasi awal dari kajian lahan, persiapan, infrastruktur, bibit, penanaman, alat, pemetaan, dan cadangan. Bandingkan satu dan empat lokasi serta periksa agar biaya kontraktor tidak menghitung tenaga atau alat yang sama dua kali.
A4: Tahap | B4: Uraian | C4: Penggerak | D4: Jumlah 1 lokasi | E4: Jumlah 4 lokasi | F4: Satuan | G4: Harga satuan | H4: Total 1 lokasi | I4: Total 4 lokasi | J4: Terpilih | K4: Dasar/sumber/pengecualian
A5: A Land | B5: Land acquisition/lease | C5: Gross ha | D5: ='02_Assumptions'!$C$6 -> 100 | E5: ='02_Assumptions'!$C$6 -> 100 | F5: ha | G5: ='02_Assumptions'!$C$16 -> 0 | H5: =$D5*$G5 -> 0 | I5: =$E5*$G5 -> 0 | J5: =($H5+($I5-$H5)*('02_Assumptions'!$C$8-1)/3) -> 0 | K5: OPEN: zero until title/valuation DD
A6: A Assessment | B6: Desktop GIS shortlist | C6: lot | D6: =1 -> 1 | E6: =1 -> 1 | F6: lot | G6: 35000000 | H6: =$D6*$G6 -> 35000000 | I6: =$E6*$G6 -> 35000000 | J6: =($H6+($I6-$H6)*('02_Assumptions'!$C$8-1)/3) -> 35000000 | K6: Public data screening; 2-3 weeks
A7: A Assessment | B7: Legal/title/overlap due diligence | C7: site | D7: =1 -> 1 | E7: =4 -> 4 | F7: site | G7: 75000000 | H7: =$D7*$G7 -> 75000000 | I7: =$E7*$G7 -> 300000000 | J7: =($H7+($I7-$H7)*('02_Assumptions'!$C$8-1)/3) -> 75000000 | K7: No-go if unresolved tenure/community conflict
A8: A Assessment | B8: Reconnaissance/community verification | C8: site | D8: =1 -> 1 | E8: =4 -> 4 | F8: site | G8: 25000000 | H8: =$D8*$G8 -> 25000000 | I8: =$E8*$G8 -> 100000000 | J8: =($H8+($I8-$H8)*('02_Assumptions'!$C$8-1)/3) -> 25000000 | K8: 3-person team, travel allowance
A9: A Survey | B9: Drone orthomosaic | C9: gross ha | D9: ='02_Assumptions'!$C$6 -> 100 | E9: ='02_Assumptions'!$C$6 -> 100 | F9: ha | G9: ='02_Assumptions'!$C$93 -> 250000 | H9: =$D9*$G9 -> 25000000 | I9: =$E9*$G9 -> 25000000 | J9: =($H9+($I9-$H9)*('02_Assumptions'!$C$8-1)/3) -> 25000000 | K9: S08
A10: A Survey | B10: Boundary/topo/hydrology survey | C10: gross ha | D10: ='02_Assumptions'!$C$6 -> 100 | E10: ='02_Assumptions'!$C$6 -> 100 | F10: ha | G10: ='02_Assumptions'!$C$94 -> 350000 | H10: =$D10*$G10 -> 35000000 | I10: =$E10*$G10 -> 35000000 | J10: =($H10+($I10-$H10)*('02_Assumptions'!$C$8-1)/3) -> 35000000 | K10: Quote after accuracy specification
A11: A Survey | B11: Soil composite laboratory | C11: sample | D11: =ROUNDUP('02_Assumptions'!$C$6/'02_Assumptions'!$C$96,0) -> 40 | E11: =ROUNDUP('02_Assumptions'!$C$6/'02_Assumptions'!$C$96+'02_Assumptions'!$C$168*3,0) -> 52 | F11: sample | G11: ='02_Assumptions'!$C$95 -> 800000 | H11: =$D11*$G11 -> 32000000 | I11: =$E11*$G11 -> 41600000 | J11: =($H11+($I11-$H11)*('02_Assumptions'!$C$8-1)/3) -> 32000000 | K11: Field heterogeneity increases samples for split sites
A12: A Survey | B12: Soil profile/infiltration pits | C12: pit | D12: =ROUNDUP('02_Assumptions'!$C$6*'02_Assumptions'!$C$166,0) -> 10 | E12: =ROUNDUP('02_Assumptions'!$C$6*'02_Assumptions'!$C$166+'02_Assumptions'!$C$167*3,0) -> 16 | F12: pit | G12: 2000000 | H12: =$D12*$G12 -> 20000000 | I12: =$E12*$G12 -> 32000000 | J12: =($H12+($I12-$H12)*('02_Assumptions'!$C$8-1)/3) -> 20000000 | K12: 1 per ~10 ha plus site minimum
A13: A Survey | B13: Water quality tests | C13: sample | D13: ='02_Assumptions'!$C$169 -> 8 | E13: =ROUNDUP('02_Assumptions'!$C$169+'02_Assumptions'!$C$170*3,0) -> 17 | F13: sample | G13: 1500000 | H13: =$D13*$G13 -> 12000000 | I13: =$E13*$G13 -> 25500000 | J13: =($H13+($I13-$H13)*('02_Assumptions'!$C$8-1)/3) -> 12000000 | K13: Dry/wet season sources
A14: A Safeguard | B14: E&S, HCV and community baseline | C14: site | D14: =1 -> 1 | E14: =4 -> 4 | F14: site | G14: 30000000 | H14: =$D14*$G14 -> 30000000 | I14: =$E14*$G14 -> 120000000 | J14: =($H14+($I14-$H14)*('02_Assumptions'!$C$8-1)/3) -> 30000000 | K14: Natural forest/protected/HCV = no-go
A15: A Design | B15: Farm master plan & BOQ design | C15: lot | D15: =1 -> 1 | E15: =1 -> 1 | F15: lot | G15: 100000000 | H15: =$D15*$G15 -> 100000000 | I15: =$E15*$G15 -> 100000000 | J15: =($H15+($I15-$H15)*('02_Assumptions'!$C$8-1)/3) -> 100000000 | K15: Road, drain, water, planting plan
A16: B Land prep | B16: Selective clearing contractor/equipment | C16: gross ha | D16: ='02_Assumptions'!$C$6 -> 100 | E16: ='02_Assumptions'!$C$6 -> 100 | F16: ha | G16: ='02_Assumptions'!$C$97 -> 6000000 | H16: =$D16*$G16 -> 600000000 | I16: =$E16*$G16 -> 600000000 | J16: =($H16+($I16-$H16)*('02_Assumptions'!$C$8-1)/3) -> 600000000 | K16: Zero burning; excludes direct HOK
A17: B Land prep | B17: Direct field HOK from Workplan | C17: calculated | D17: ='05_Workplan_Labor'!$K$26 -> 1170489600 | E17: ='05_Workplan_Labor'!$L$26 -> 1213689600 | F17: Rp | G17: 1 | H17: =$D17*$G17 -> 1170489600 | I17: =$E17*$G17 -> 1213689600 | J17: =($H17+($I17-$H17)*('02_Assumptions'!$C$8-1)/3) -> 1170489600 | K17: Only Cost flag=1 tasks
A18: B Land prep | B18: Deep ripping/spot cultivation | C18: net ha | D18: ='02_Assumptions'!$C$24 -> 88 | E18: ='02_Assumptions'!$C$24 -> 88 | F18: ha | G18: 2000000 | H18: =$D18*$G18 -> 176000000 | I18: =$E18*$G18 -> 176000000 | J18: =($H18+($I18-$H18)*('02_Assumptions'!$C$8-1)/3) -> 176000000 | K18: After compaction assessment
A19: B Land prep | B19: Contour/erosion control earthworks | C19: net ha | D19: ='02_Assumptions'!$C$24 -> 88 | E19: ='02_Assumptions'!$C$24 -> 88 | F19: ha | G19: 1000000 | H19: =$D19*$G19 -> 88000000 | I19: =$E19*$G19 -> 88000000 | J19: =($H19+($I19-$H19)*('02_Assumptions'!$C$8-1)/3) -> 88000000 | K19: Vetiver/check dams not blanket terracing
A20: B Soil | B20: Initial compost (50%) | C20: ton | D20: ='02_Assumptions'!$C$24*'02_Assumptions'!$C$107/2 -> 352 | E20: ='02_Assumptions'!$C$24*'02_Assumptions'!$C$107/2 -> 352 | F20: ton | G20: ='02_Assumptions'!$C$73*1000 -> 1000000 | H20: =$D20*$G20 -> 352000000 | I20: =$E20*$G20 -> 352000000 | J20: =($H20+($I20-$H20)*('02_Assumptions'!$C$8-1)/3) -> 352000000 | K20: Mature bulk compost
A21: B Soil | B21: Initial fermented manure (50%) | C21: ton | D21: ='02_Assumptions'!$C$24*'02_Assumptions'!$C$107/2 -> 352 | E21: ='02_Assumptions'!$C$24*'02_Assumptions'!$C$107/2 -> 352 | F21: ton | G21: ='02_Assumptions'!$C$74*1000 -> 900000 | H21: =$D21*$G21 -> 316800000 | I21: =$E21*$G21 -> 316800000 | J21: =($H21+($I21-$H21)*('02_Assumptions'!$C$8-1)/3) -> 316800000 | K21: Verify quality before spreading
A22: B Soil | B22: Initial dolomite | C22: ton | D22: ='02_Assumptions'!$C$24*'02_Assumptions'!$C$108*'02_Assumptions'!$C$109 -> 92.4 | E22: ='02_Assumptions'!$C$24*'02_Assumptions'!$C$108*'02_Assumptions'!$C$109 -> 92.4 | F22: ton | G22: ='02_Assumptions'!$C$75*1000 -> 1500000 | H22: =$D22*$G22 -> 138600000 | I22: =$E22*$G22 -> 138600000 | J22: =($H22+($I22-$H22)*('02_Assumptions'!$C$8-1)/3) -> 138600000 | K22: Conditional on lime requirement
A23: C Road | B23: Main/collection roads | C23: m | D23: ='02_Assumptions'!$C$6*'02_Assumptions'!$C$158 -> 4000 | E23: ='02_Assumptions'!$C$6*'02_Assumptions'!$C$158*(1+'02_Assumptions'!$C$159*3) -> 4500 | F23: m | G23: ='02_Assumptions'!$C$98 -> 350000 | H23: =$D23*$G23 -> 1400000000 | I23: =$E23*$G23 -> 1.575e+09 | J23: =($H23+($I23-$H23)*('02_Assumptions'!$C$8-1)/3) -> 1400000000 | K23: One-site grid vs split access
A24: C Road | B24: Field tracks | C24: m | D24: ='02_Assumptions'!$C$6*'02_Assumptions'!$C$160 -> 6000 | E24: ='02_Assumptions'!$C$6*'02_Assumptions'!$C$160*(1+'02_Assumptions'!$C$161*3) -> 7000 | F24: m | G24: ='02_Assumptions'!$C$99 -> 120000 | H24: =$D24*$G24 -> 720000000 | I24: =$E24*$G24 -> 8.4e+08 | J24: =($H24+($I24-$H24)*('02_Assumptions'!$C$8-1)/3) -> 720000000 | K24: Design after slope/topo
A25: C Drain | B25: Field drains | C25: m | D25: ='02_Assumptions'!$C$6*'02_Assumptions'!$C$162 -> 8000 | E25: ='02_Assumptions'!$C$6*'02_Assumptions'!$C$162*(1+'02_Assumptions'!$C$163*3) -> 9000 | F25: m | G25: ='02_Assumptions'!$C$100 -> 45000 | H25: =$D25*$G25 -> 360000000 | I25: =$E25*$G25 -> 4.05e+08 | J25: =($H25+($I25-$H25)*('02_Assumptions'!$C$8-1)/3) -> 360000000 | K25: Durian and banana require drainage
A26: C Drain | B26: Culverts/cross drains | C26: unit | D26: ='02_Assumptions'!$C$6*'02_Assumptions'!$C$164 -> 20 | E26: ='02_Assumptions'!$C$6*'02_Assumptions'!$C$164+'02_Assumptions'!$C$165*3 -> 32 | F26: unit | G26: ='02_Assumptions'!$C$102 -> 12000000 | H26: =$D26*$G26 -> 240000000 | I26: =$E26*$G26 -> 384000000 | J26: =($H26+($I26-$H26)*('02_Assumptions'!$C$8-1)/3) -> 240000000 | K26: Hydrology design required
A27: C Boundary | B27: Fence/live boundary | C27: m | D27: =400*SQRT('02_Assumptions'!$C$6) -> 4000 | E27: =400*SQRT('02_Assumptions'!$C$6*4) -> 8000 | F27: m | G27: ='02_Assumptions'!$C$101 -> 75000 | H27: =$D27*$G27 -> 300000000 | I27: =$E27*$G27 -> 600000000 | J27: =($H27+($I27-$H27)*('02_Assumptions'!$C$8-1)/3) -> 300000000 | K27: Square geometry: split sites double perimeter
A28: C Facility | B28: Basecamp/office | C28: site | D28: =1 -> 1 | E28: =4 -> 4 | F28: site | G28: ='02_Assumptions'!$C$103 -> 350000000 | H28: =$D28*$G28 -> 350000000 | I28: =$E28*$G28 -> 1400000000 | J28: =($H28+($I28-$H28)*('02_Assumptions'!$C$8-1)/3) -> 350000000 | K28: Satellite version may be smaller; conservative duplication
A29: C Facility | B29: Nursery/warehouse | C29: site | D29: =1 -> 1 | E29: =4 -> 4 | F29: site | G29: ='02_Assumptions'!$C$104 -> 250000000 | H29: =$D29*$G29 -> 250000000 | I29: =$E29*$G29 -> 1000000000 | J29: =($H29+($I29-$H29)*('02_Assumptions'!$C$8-1)/3) -> 250000000 | K29: Acclimatization, quarantine, input store
A30: C Water | B30: Reservoir/pump/tank/mainline | C30: site | D30: =1 -> 1 | E30: =4 -> 4 | F30: site | G30: ='02_Assumptions'!$C$105 -> 350000000 | H30: =$D30*$G30 -> 350000000 | I30: =$E30*$G30 -> 1400000000 | J30: =($H30+($I30-$H30)*('02_Assumptions'!$C$8-1)/3) -> 350000000 | K30: Supplemental only; borehole not assumed
A31: C Power | B31: Power/comms/security infrastructure | C31: site | D31: =1 -> 1 | E31: =4 -> 4 | F31: site | G31: 100000000 | H31: =$D31*$G31 -> 100000000 | I31: =$E31*$G31 -> 400000000 | J31: =($H31+($I31-$H31)*('02_Assumptions'!$C$8-1)/3) -> 100000000 | K31: Solar/backup/CCTV allowance
A32: C Mobilization | B32: Heavy equipment mobilization | C32: site | D32: =1 -> 1 | E32: =4 -> 4 | F32: site | G32: ='02_Assumptions'!$C$106 -> 75000000 | H32: =$D32*$G32 -> 75000000 | I32: =$E32*$G32 -> 300000000 | J32: =($H32+($I32-$H32)*('02_Assumptions'!$C$8-1)/3) -> 75000000 | K32: Distance-dependent
A33: D Planting | B33: All planting stock | C33: calculated | D33: ='04_Planting_Design'!$G$19+'17_Model_Fleksibel'!$M$18 -> 2.330768e+09 | E33: ='04_Planting_Design'!$G$19+'17_Model_Fleksibel'!$M$18 -> 2.330768e+09 | F33: Rp | G33: 1 | H33: =$D33*$G33 -> 2.330768e+09 | I33: =$E33*$G33 -> 2.330768e+09 | J33: =($H33+($I33-$H33)*('02_Assumptions'!$C$8-1)/3) -> 2.330768e+09 | K33: Procurement incl. 10% reserve
A34: D Planting | B34: Seedling freight/handling | C34: % stock | D34: =$D$33*'02_Assumptions'!$C$171 -> 2.330768e+08 | E34: =$E$33*('02_Assumptions'!$C$171+'02_Assumptions'!$C$172*3) -> 3.2630752e+08 | F34: Rp | G34: 1 | H34: =$D34*$G34 -> 2.330768e+08 | I34: =$E34*$G34 -> 3.2630752e+08 | J34: =($H34+($I34-$H34)*('02_Assumptions'!$C$8-1)/3) -> 2.330768e+08 | K34: Higher logistics for split sites
A35: D Planting | B35: Quarantine/acclimatization/QC | C35: % stock | D35: =$D$33*'02_Assumptions'!$C$173 -> 1.165384e+08 | E35: =$E$33*('02_Assumptions'!$C$173+'02_Assumptions'!$C$174*3) -> 1.6315376e+08 | F35: Rp | G35: 1 | H35: =$D35*$G35 -> 1.165384e+08 | I35: =$E35*$G35 -> 1.6315376e+08 | J35: =($H35+($I35-$H35)*('02_Assumptions'!$C$8-1)/3) -> 1.165384e+08 | K35: Critical for banana tissue culture
A36: D Planting | B36: Mycorrhiza/root inoculant | C36: tree kg | D36: =('04_Planting_Design'!$D$8+'04_Planting_Design'!$F$8)*'02_Assumptions'!$C$175 -> 497.2 | E36: =('04_Planting_Design'!$D$8+'04_Planting_Design'!$F$8)*'02_Assumptions'!$C$175 -> 497.2 | F36: kg | G36: 120000 | H36: =$D36*$G36 -> 59664000 | I36: =$E36*$G36 -> 59664000 | J36: =($H36+($I36-$H36)*('02_Assumptions'!$C$8-1)/3) -> 59664000 | K36: Product quality/spec to verify
A37: D Ecology | B37: Cover crop/insectary establishment | C37: net ha | D37: =0 -> 0 | E37: =0 -> 0 | F37: ha | G37: ='02_Assumptions'!$C$59 -> 1200000 | H37: =$D37*$G37 -> 0 | I37: =$E37*$G37 -> 0 | J37: =($H37+($I37-$H37)*('02_Assumptions'!$C$8-1)/3) -> 0 | K37: Biaya penutup tanah dan strip pendukung sudah dihitung pada 17_Model_Fleksibel agar tidak dihitung ganda
A38: E Equipment | B38: Tools, machines, vehicles, PPE | C38: equipment | D38: ='06_Equipment_Tools'!$I$39 -> 2287100000 | E38: ='06_Equipment_Tools'!$J$39 -> 4365600000 | F38: Rp | G38: 1 | H38: =$D38*$G38 -> 2287100000 | I38: =$E38*$G38 -> 4365600000 | J38: =($H38+($I38-$H38)*('02_Assumptions'!$C$8-1)/3) -> 2287100000 | K38: Detailed in 06_Equipment_Tools
A39: F Systems | B39: Certification/ESG/traceability Y0 | C39: system | D39: ='14_Certification_ESG'!$C$15 -> 380000000 | E39: ='14_Certification_ESG'!$C$15+'02_Assumptions'!$C$176*3 -> 455000000 | F39: Rp | G39: 1 | H39: =$D39*$G39 -> 380000000 | I39: =$E39*$G39 -> 455000000 | J39: =($H39+($I39-$H39)*('02_Assumptions'!$C$8-1)/3) -> 380000000 | K39: Split-site system/training uplift
A40: F Payroll | B40: Development-year permanent payroll | C40: annual | D40: ='09_OPEX_10Y'!$F$34 -> 1097100000 | E40: ='09_OPEX_10Y'!$G$34 -> 2001000000 | F40: Rp | G40: 1 | H40: =$D40*$G40 -> 1097100000 | I40: =$E40*$G40 -> 2001000000 | J40: =($H40+($I40-$H40)*('02_Assumptions'!$C$8-1)/3) -> 1097100000 | K40: Management staff only; direct field crew elsewhere
A41: SUBTOTAL SEBELUM CADANGAN | H41: =SUM(H5:H40)+'17_Model_Fleksibel'!$I$84 -> 13880136800 | I41: =SUM(I5:I40)+'17_Model_Fleksibel'!$J$84 -> 2.1704683e+10 | J41: =(H41+(I41-H41)*('02_Assumptions'!$C$8-1)/3) -> 13880136800
A42: CADANGAN (tidak termasuk akuisisi lahan) | H42: =(H41-H5)*'02_Assumptions'!$C$14 -> 1388013680 | I42: =(I41-I5)*'02_Assumptions'!$C$14 -> 2.1704683e+09 | J42: =(H42+(I42-H42)*('02_Assumptions'!$C$8-1)/3) -> 1388013680
A43: TOTAL INVESTASI AWAL | H43: =H41+H42 -> 15268150480 | I43: =I41+I42 -> 2.3875151e+10 | J43: =(H43+(I43-H43)*('02_Assumptions'!$C$8-1)/3) -> 15268150480

Sheet 09_OPEX_10Y
A1: Rencana Biaya Operasional 10 Tahun
A2: Proyeksi biaya operasional nominal Tahun 1–10: staf, HOK, input, perawatan, penggantian alat, panen, sertifikasi, dan biaya tambahan aktif. Perubahan upah, inflasi, luas, lokasi, dosis, atau aktivitas akan mengalir ke total tahunan.
A4: A. Biaya operasi tahunan
A5: Uraian biaya | B5: T1 | C5: T2 | D5: T3 | E5: T4 | F5: T5 | G5: T6 | H5: T7 | I5: T8 | J5: T9 | K5: T10
A6: Gaji staf tetap | B6: =($F$34+($G$34-$F$34)*('02_Assumptions'!$C$8-1)/3)*(1+'02_Assumptions'!$C$11)^0 -> 1097100000 | C6: =($F$34+($G$34-$F$34)*('02_Assumptions'!$C$8-1)/3)*(1+'02_Assumptions'!$C$11)^1 -> 1140984000 | D6: =($F$34+($G$34-$F$34)*('02_Assumptions'!$C$8-1)/3)*(1+'02_Assumptions'!$C$11)^2 -> 1.1866234e+09 | E6: =($F$34+($G$34-$F$34)*('02_Assumptions'!$C$8-1)/3)*(1+'02_Assumptions'!$C$11)^3 -> 1.2340883e+09 | F6: =($F$34+($G$34-$F$34)*('02_Assumptions'!$C$8-1)/3)*(1+'02_Assumptions'!$C$11)^4 -> 1.2834518e+09 | G6: =($F$34+($G$34-$F$34)*('02_Assumptions'!$C$8-1)/3)*(1+'02_Assumptions'!$C$11)^5 -> 1.3347899e+09 | H6: =($F$34+($G$34-$F$34)*('02_Assumptions'!$C$8-1)/3)*(1+'02_Assumptions'!$C$11)^6 -> 1.3881815e+09 | I6: =($F$34+($G$34-$F$34)*('02_Assumptions'!$C$8-1)/3)*(1+'02_Assumptions'!$C$11)^7 -> 1.4437088e+09 | J6: =($F$34+($G$34-$F$34)*('02_Assumptions'!$C$8-1)/3)*(1+'02_Assumptions'!$C$11)^8 -> 1.5014571e+09 | K6: =($F$34+($G$34-$F$34)*('02_Assumptions'!$C$8-1)/3)*(1+'02_Assumptions'!$C$11)^9 -> 1.5615154e+09
A7: HOK pemeliharaan langsung | B7: =('05_Workplan_Labor'!$B$41+'17_Model_Fleksibel'!$N$68)*'02_Assumptions'!$C$60*(1+'02_Assumptions'!$C$11)^0*(1+'02_Assumptions'!$C$177*('02_Assumptions'!$C$8-1)) -> 1165296000 | C7: =('05_Workplan_Labor'!$C$41+'17_Model_Fleksibel'!$O$68)*'02_Assumptions'!$C$60*(1+'02_Assumptions'!$C$11)^1*(1+'02_Assumptions'!$C$177*('02_Assumptions'!$C$8-1)) -> 1176764160 | D7: =('05_Workplan_Labor'!$D$41+'17_Model_Fleksibel'!$P$68)*'02_Assumptions'!$C$60*(1+'02_Assumptions'!$C$11)^2*(1+'02_Assumptions'!$C$177*('02_Assumptions'!$C$8-1)) -> 1.0553647e+09 | E7: =('05_Workplan_Labor'!$E$41+'17_Model_Fleksibel'!$Q$68)*'02_Assumptions'!$C$60*(1+'02_Assumptions'!$C$11)^3*(1+'02_Assumptions'!$C$177*('02_Assumptions'!$C$8-1)) -> 9.1940084e+08 | F7: =('05_Workplan_Labor'!$F$41+'17_Model_Fleksibel'!$R$68)*'02_Assumptions'!$C$60*(1+'02_Assumptions'!$C$11)^4*(1+'02_Assumptions'!$C$177*('02_Assumptions'!$C$8-1)) -> 8.9934983e+08 | G7: =('05_Workplan_Labor'!$G$41+'17_Model_Fleksibel'!$S$68)*'02_Assumptions'!$C$60*(1+'02_Assumptions'!$C$11)^5*(1+'02_Assumptions'!$C$177*('02_Assumptions'!$C$8-1)) -> 8.9934983e+08 | H7: =('05_Workplan_Labor'!$H$41+'17_Model_Fleksibel'!$T$68)*'02_Assumptions'!$C$60*(1+'02_Assumptions'!$C$11)^6*(1+'02_Assumptions'!$C$177*('02_Assumptions'!$C$8-1)) -> 9.2329823e+08 | I7: =('05_Workplan_Labor'!$I$41+'17_Model_Fleksibel'!$U$68)*'02_Assumptions'!$C$60*(1+'02_Assumptions'!$C$11)^7*(1+'02_Assumptions'!$C$177*('02_Assumptions'!$C$8-1)) -> 9.6023016e+08 | J7: =('05_Workplan_Labor'!$J$41+'17_Model_Fleksibel'!$V$68)*'02_Assumptions'!$C$60*(1+'02_Assumptions'!$C$11)^8*(1+'02_Assumptions'!$C$177*('02_Assumptions'!$C$8-1)) -> 9.9863936e+08 | K7: =('05_Workplan_Labor'!$K$41+'17_Model_Fleksibel'!$W$68)*'02_Assumptions'!$C$60*(1+'02_Assumptions'!$C$11)^9*(1+'02_Assumptions'!$C$177*('02_Assumptions'!$C$8-1)) -> 1.0385849e+09
A8: Input pertanian | B8: ='07_Agri_Inputs'!$B$34 -> 904962520 | C8: ='07_Agri_Inputs'!$C$34 -> 9.8703917e+08 | D8: ='07_Agri_Inputs'!$D$34 -> 6.9080107e+08 | E8: ='07_Agri_Inputs'!$E$34 -> 6.6654853e+08 | F8: ='07_Agri_Inputs'!$F$34 -> 6.3177009e+08 | G8: ='07_Agri_Inputs'!$G$34 -> 7.116068e+08 | H8: ='07_Agri_Inputs'!$H$34 -> 7.0524557e+08 | I8: ='07_Agri_Inputs'!$I$34 -> 8.2030689e+08 | J8: ='07_Agri_Inputs'!$J$34 -> 7.6279361e+08 | K8: ='07_Agri_Inputs'!$K$34 -> 8.8724394e+08
A9: Cadangan perbaikan peralatan | B9: =IF('02_Assumptions'!$C$8=4,'06_Equipment_Tools'!$J$39,'06_Equipment_Tools'!$I$39)*'02_Assumptions'!$C$113*(1+'02_Assumptions'!$C$11)^0 -> 114355000 | C9: =IF('02_Assumptions'!$C$8=4,'06_Equipment_Tools'!$J$39,'06_Equipment_Tools'!$I$39)*'02_Assumptions'!$C$113*(1+'02_Assumptions'!$C$11)^1 -> 118929200 | D9: =IF('02_Assumptions'!$C$8=4,'06_Equipment_Tools'!$J$39,'06_Equipment_Tools'!$I$39)*'02_Assumptions'!$C$113*(1+'02_Assumptions'!$C$11)^2 -> 1.2368637e+08 | E9: =IF('02_Assumptions'!$C$8=4,'06_Equipment_Tools'!$J$39,'06_Equipment_Tools'!$I$39)*'02_Assumptions'!$C$113*(1+'02_Assumptions'!$C$11)^3 -> 1.2863382e+08 | F9: =IF('02_Assumptions'!$C$8=4,'06_Equipment_Tools'!$J$39,'06_Equipment_Tools'!$I$39)*'02_Assumptions'!$C$113*(1+'02_Assumptions'!$C$11)^4 -> 1.3377918e+08 | G9: =IF('02_Assumptions'!$C$8=4,'06_Equipment_Tools'!$J$39,'06_Equipment_Tools'!$I$39)*'02_Assumptions'!$C$113*(1+'02_Assumptions'!$C$11)^5 -> 1.3913034e+08 | H9: =IF('02_Assumptions'!$C$8=4,'06_Equipment_Tools'!$J$39,'06_Equipment_Tools'!$I$39)*'02_Assumptions'!$C$113*(1+'02_Assumptions'!$C$11)^6 -> 1.4469556e+08 | I9: =IF('02_Assumptions'!$C$8=4,'06_Equipment_Tools'!$J$39,'06_Equipment_Tools'!$I$39)*'02_Assumptions'!$C$113*(1+'02_Assumptions'!$C$11)^7 -> 1.5048338e+08 | J9: =IF('02_Assumptions'!$C$8=4,'06_Equipment_Tools'!$J$39,'06_Equipment_Tools'!$I$39)*'02_Assumptions'!$C$113*(1+'02_Assumptions'!$C$11)^8 -> 1.5650271e+08 | K9: =IF('02_Assumptions'!$C$8=4,'06_Equipment_Tools'!$J$39,'06_Equipment_Tools'!$I$39)*'02_Assumptions'!$C$113*(1+'02_Assumptions'!$C$11)^9 -> 1.6276282e+08
A10: BBM, listrik, dan air | B10: ='02_Assumptions'!$C$179*(1+'02_Assumptions'!$C$11)^0*(1+'02_Assumptions'!$C$178*('02_Assumptions'!$C$8-1)) -> 250000000 | C10: ='02_Assumptions'!$C$179*(1+'02_Assumptions'!$C$11)^1*(1+'02_Assumptions'!$C$178*('02_Assumptions'!$C$8-1)) -> 260000000 | D10: ='02_Assumptions'!$C$179*(1+'02_Assumptions'!$C$11)^2*(1+'02_Assumptions'!$C$178*('02_Assumptions'!$C$8-1)) -> 270400000 | E10: ='02_Assumptions'!$C$179*(1+'02_Assumptions'!$C$11)^3*(1+'02_Assumptions'!$C$178*('02_Assumptions'!$C$8-1)) -> 281216000 | F10: ='02_Assumptions'!$C$179*(1+'02_Assumptions'!$C$11)^4*(1+'02_Assumptions'!$C$178*('02_Assumptions'!$C$8-1)) -> 2.9246464e+08 | G10: ='02_Assumptions'!$C$179*(1+'02_Assumptions'!$C$11)^5*(1+'02_Assumptions'!$C$178*('02_Assumptions'!$C$8-1)) -> 3.0416323e+08 | H10: ='02_Assumptions'!$C$179*(1+'02_Assumptions'!$C$11)^6*(1+'02_Assumptions'!$C$178*('02_Assumptions'!$C$8-1)) -> 3.1632975e+08 | I10: ='02_Assumptions'!$C$179*(1+'02_Assumptions'!$C$11)^7*(1+'02_Assumptions'!$C$178*('02_Assumptions'!$C$8-1)) -> 3.2898294e+08 | J10: ='02_Assumptions'!$C$179*(1+'02_Assumptions'!$C$11)^8*(1+'02_Assumptions'!$C$178*('02_Assumptions'!$C$8-1)) -> 3.4214226e+08 | K10: ='02_Assumptions'!$C$179*(1+'02_Assumptions'!$C$11)^9*(1+'02_Assumptions'!$C$178*('02_Assumptions'!$C$8-1)) -> 3.5582795e+08
A11: Perawatan jalan dan drainase | B11: =SUM('08_CAPEX_RAB'!$J$23:$J$26)*'02_Assumptions'!$C$114*(1+'02_Assumptions'!$C$11)^0 -> 54400000 | C11: =SUM('08_CAPEX_RAB'!$J$23:$J$26)*'02_Assumptions'!$C$114*(1+'02_Assumptions'!$C$11)^1 -> 56576000 | D11: =SUM('08_CAPEX_RAB'!$J$23:$J$26)*'02_Assumptions'!$C$114*(1+'02_Assumptions'!$C$11)^2 -> 58839040 | E11: =SUM('08_CAPEX_RAB'!$J$23:$J$26)*'02_Assumptions'!$C$114*(1+'02_Assumptions'!$C$11)^3 -> 61192602 | F11: =SUM('08_CAPEX_RAB'!$J$23:$J$26)*'02_Assumptions'!$C$114*(1+'02_Assumptions'!$C$11)^4 -> 63640306 | G11: =SUM('08_CAPEX_RAB'!$J$23:$J$26)*'02_Assumptions'!$C$114*(1+'02_Assumptions'!$C$11)^5 -> 66185918 | H11: =SUM('08_CAPEX_RAB'!$J$23:$J$26)*'02_Assumptions'!$C$114*(1+'02_Assumptions'!$C$11)^6 -> 68833355 | I11: =SUM('08_CAPEX_RAB'!$J$23:$J$26)*'02_Assumptions'!$C$114*(1+'02_Assumptions'!$C$11)^7 -> 71586689 | J11: =SUM('08_CAPEX_RAB'!$J$23:$J$26)*'02_Assumptions'!$C$114*(1+'02_Assumptions'!$C$11)^8 -> 74450156 | K11: =SUM('08_CAPEX_RAB'!$J$23:$J$26)*'02_Assumptions'!$C$114*(1+'02_Assumptions'!$C$11)^9 -> 77428163
A12: Stok pembibitan dan sulaman | B12: ='04_Planting_Design'!$G$19*IF(1<=3,'02_Assumptions'!$C$181,'02_Assumptions'!$C$182)*(1+'02_Assumptions'!$C$11)^0 -> 64553280 | C12: ='04_Planting_Design'!$G$19*IF(2<=3,'02_Assumptions'!$C$181,'02_Assumptions'!$C$182)*(1+'02_Assumptions'!$C$11)^1 -> 67135411 | D12: ='04_Planting_Design'!$G$19*IF(3<=3,'02_Assumptions'!$C$181,'02_Assumptions'!$C$182)*(1+'02_Assumptions'!$C$11)^2 -> 69820828 | E12: ='04_Planting_Design'!$G$19*IF(4<=3,'02_Assumptions'!$C$181,'02_Assumptions'!$C$182)*(1+'02_Assumptions'!$C$11)^3 -> 24204554 | F12: ='04_Planting_Design'!$G$19*IF(5<=3,'02_Assumptions'!$C$181,'02_Assumptions'!$C$182)*(1+'02_Assumptions'!$C$11)^4 -> 25172736 | G12: ='04_Planting_Design'!$G$19*IF(6<=3,'02_Assumptions'!$C$181,'02_Assumptions'!$C$182)*(1+'02_Assumptions'!$C$11)^5 -> 26179645 | H12: ='04_Planting_Design'!$G$19*IF(7<=3,'02_Assumptions'!$C$181,'02_Assumptions'!$C$182)*(1+'02_Assumptions'!$C$11)^6 -> 27226831 | I12: ='04_Planting_Design'!$G$19*IF(8<=3,'02_Assumptions'!$C$181,'02_Assumptions'!$C$182)*(1+'02_Assumptions'!$C$11)^7 -> 28315904 | J12: ='04_Planting_Design'!$G$19*IF(9<=3,'02_Assumptions'!$C$181,'02_Assumptions'!$C$182)*(1+'02_Assumptions'!$C$11)^8 -> 29448540 | K12: ='04_Planting_Design'!$G$19*IF(10<=3,'02_Assumptions'!$C$181,'02_Assumptions'!$C$182)*(1+'02_Assumptions'!$C$11)^9 -> 30626482
A13: Sertifikasi, ESG, dan pemetaan | B13: ='14_Certification_ESG'!$D$15+'02_Assumptions'!$C$6*'02_Assumptions'!$C$118*(1+'02_Assumptions'!$C$11)^0 -> 145000000 | C13: ='14_Certification_ESG'!$E$15+'02_Assumptions'!$C$6*'02_Assumptions'!$C$118*(1+'02_Assumptions'!$C$11)^1 -> 150800000 | D13: ='14_Certification_ESG'!$F$15+'02_Assumptions'!$C$6*'02_Assumptions'!$C$118*(1+'02_Assumptions'!$C$11)^2 -> 1.56832e+08 | E13: ='14_Certification_ESG'!$G$15+'02_Assumptions'!$C$6*'02_Assumptions'!$C$118*(1+'02_Assumptions'!$C$11)^3 -> 163105280 | F13: ='14_Certification_ESG'!$H$15+'02_Assumptions'!$C$6*'02_Assumptions'!$C$118*(1+'02_Assumptions'!$C$11)^4 -> 1.9887596e+08 | G13: ='14_Certification_ESG'!$I$15+'02_Assumptions'!$C$6*'02_Assumptions'!$C$118*(1+'02_Assumptions'!$C$11)^5 -> 2.4333058e+08 | H13: ='14_Certification_ESG'!$J$15+'02_Assumptions'!$C$6*'02_Assumptions'!$C$118*(1+'02_Assumptions'!$C$11)^6 -> 2.2775742e+08 | I13: ='14_Certification_ESG'!$K$15+'02_Assumptions'!$C$6*'02_Assumptions'!$C$118*(1+'02_Assumptions'!$C$11)^7 -> 2.3686772e+08 | J13: ='14_Certification_ESG'!$L$15+'02_Assumptions'!$C$6*'02_Assumptions'!$C$118*(1+'02_Assumptions'!$C$11)^8 -> 2.4634243e+08 | K13: ='14_Certification_ESG'!$M$15+'02_Assumptions'!$C$6*'02_Assumptions'!$C$118*(1+'02_Assumptions'!$C$11)^9 -> 2.5619613e+08
A14: Administrasi, keamanan, bahan habis pakai, dan OPEX tambahan | B14: =('02_Assumptions'!$C$180*(1+'02_Assumptions'!$C$11)^0*(1+'02_Assumptions'!$C$178*('02_Assumptions'!$C$8-1)))+'17_Model_Fleksibel'!$H$100 -> 120000000 | C14: =('02_Assumptions'!$C$180*(1+'02_Assumptions'!$C$11)^1*(1+'02_Assumptions'!$C$178*('02_Assumptions'!$C$8-1)))+'17_Model_Fleksibel'!$I$100 -> 124800000 | D14: =('02_Assumptions'!$C$180*(1+'02_Assumptions'!$C$11)^2*(1+'02_Assumptions'!$C$178*('02_Assumptions'!$C$8-1)))+'17_Model_Fleksibel'!$J$100 -> 1.29792e+08 | E14: =('02_Assumptions'!$C$180*(1+'02_Assumptions'!$C$11)^3*(1+'02_Assumptions'!$C$178*('02_Assumptions'!$C$8-1)))+'17_Model_Fleksibel'!$K$100 -> 134983680 | F14: =('02_Assumptions'!$C$180*(1+'02_Assumptions'!$C$11)^4*(1+'02_Assumptions'!$C$178*('02_Assumptions'!$C$8-1)))+'17_Model_Fleksibel'!$L$100 -> 1.4038303e+08 | G14: =('02_Assumptions'!$C$180*(1+'02_Assumptions'!$C$11)^5*(1+'02_Assumptions'!$C$178*('02_Assumptions'!$C$8-1)))+'17_Model_Fleksibel'!$M$100 -> 1.4599835e+08 | H14: =('02_Assumptions'!$C$180*(1+'02_Assumptions'!$C$11)^6*(1+'02_Assumptions'!$C$178*('02_Assumptions'!$C$8-1)))+'17_Model_Fleksibel'!$N$100 -> 1.5183828e+08 | I14: =('02_Assumptions'!$C$180*(1+'02_Assumptions'!$C$11)^7*(1+'02_Assumptions'!$C$178*('02_Assumptions'!$C$8-1)))+'17_Model_Fleksibel'!$O$100 -> 1.5791181e+08 | J14: =('02_Assumptions'!$C$180*(1+'02_Assumptions'!$C$11)^8*(1+'02_Assumptions'!$C$178*('02_Assumptions'!$C$8-1)))+'17_Model_Fleksibel'!$P$100 -> 1.6422829e+08 | K14: =('02_Assumptions'!$C$180*(1+'02_Assumptions'!$C$11)^9*(1+'02_Assumptions'!$C$178*('02_Assumptions'!$C$8-1)))+'17_Model_Fleksibel'!$Q$100 -> 1.7079742e+08
A15: Panen, pengemasan, dan angkut kebun | B15: ='10_Production_Revenue'!$B$25 -> 738575200 | C15: ='10_Production_Revenue'!$C$25 -> 670878208 | D15: ='10_Production_Revenue'!$D$25 -> 4.6747455e+08 | E15: ='10_Production_Revenue'!$E$25 -> 3.8766955e+08 | F15: ='10_Production_Revenue'!$F$25 -> 3.9951886e+08 | G15: ='10_Production_Revenue'!$G$25 -> 4.8648241e+08 | H15: ='10_Production_Revenue'!$H$25 -> 6.3027631e+08 | I15: ='10_Production_Revenue'!$I$25 -> 7.7630648e+08 | J15: ='10_Production_Revenue'!$J$25 -> 8.902776e+08 | K15: ='10_Production_Revenue'!$K$25 -> 9.9056541e+08
A16: Cadangan OPEX | B16: =SUM(B6:B15)*'02_Assumptions'!$C$15 -> 232712100 | C16: =SUM(C6:C15)*'02_Assumptions'!$C$15 -> 2.3769531e+08 | D16: =SUM(D6:D15)*'02_Assumptions'!$C$15 -> 2.104817e+08 | E16: =SUM(E6:E15)*'02_Assumptions'!$C$15 -> 2.0005216e+08 | F16: =SUM(F6:F15)*'02_Assumptions'!$C$15 -> 2.0342032e+08 | G16: =SUM(G6:G15)*'02_Assumptions'!$C$15 -> 2.1786085e+08 | H16: =SUM(H6:H15)*'02_Assumptions'!$C$15 -> 2.2918414e+08 | I16: =SUM(I6:I15)*'02_Assumptions'!$C$15 -> 2.4873504e+08 | ... K16: =SUM(K6:K15)*'02_Assumptions'!$C$15 -> 2.7657743e+08
A17: TOTAL OPEX | B17: =SUM(B6:B16) -> 4886954100 | C17: =SUM(C6:C16) -> 4.9916015e+09 | D17: =SUM(D6:D16) -> 4.4201156e+09 | E17: =SUM(E6:E16) -> 4.2010953e+09 | F17: =SUM(F6:F16) -> 4.2718268e+09 | G17: =SUM(G6:G16) -> 4.5750778e+09 | H17: =SUM(H6:H16) -> 4.8128669e+09 | I17: =SUM(I6:I16) -> 5.2234358e+09 | ... K17: =SUM(K6:K16) -> 5.8081261e+09
A24: B. Staf tetap dan dasar gaji bulanan
A25: Jabatan | B25: Jumlah 1 lokasi | C25: Jumlah 4 lokasi | D25: Gaji bulanan | E25: Beban | F25: Tahunan 1 lokasi | G25: Tahunan 4 lokasi | H25: Aktif | I25: Dasar per 100 ha | J25: Kenaikan per lokasi ekstra | K25: Minimum per lokasi
A26: Manajer kebun | B26: =IF($H26=0,0,ROUNDUP(MAX($I26*'02_Assumptions'!$C$6/100,$K26),0)) -> 1 | C26: =IF($H26=0,0,ROUNDUP(MAX($I26*'02_Assumptions'!$C$6/100*(1+$J26*3),$K26*4),0)) -> 1 | D26: 15000000 | E26: ='02_Assumptions'!$C$63 -> 0.15 | F26: =$B26*$D26*12*(1+$E26) -> 2.07e+08 | G26: =$C26*$D26*12*(1+$E26) -> 2.07e+08 | H26: 1 | I26: 1 | J26: 0 | K26: 0
A27: Agronomis/ketua kesehatan tanaman | B27: =IF($H27=0,0,ROUNDUP(MAX($I27*'02_Assumptions'!$C$6/100,$K27),0)) -> 1 | C27: =IF($H27=0,0,ROUNDUP(MAX($I27*'02_Assumptions'!$C$6/100*(1+$J27*3),$K27*4),0)) -> 1 | D27: 12000000 | E27: ='02_Assumptions'!$C$63 -> 0.15 | F27: =$B27*$D27*12*(1+$E27) -> 165600000 | G27: =$C27*$D27*12*(1+$E27) -> 165600000 | H27: 1 | I27: 1 | J27: 0 | K27: 0
A28: Administrasi/keuangan | B28: =IF($H28=0,0,ROUNDUP(MAX($I28*'02_Assumptions'!$C$6/100,$K28),0)) -> 1 | C28: =IF($H28=0,0,ROUNDUP(MAX($I28*'02_Assumptions'!$C$6/100*(1+$J28*3),$K28*4),0)) -> 1 | D28: 6000000 | E28: ='02_Assumptions'!$C$63 -> 0.15 | F28: =$B28*$D28*12*(1+$E28) -> 82800000 | G28: =$C28*$D28*12*(1+$E28) -> 82800000 | H28: 1 | I28: 1 | J28: 0 | K28: 0
A29: Pengawas lokasi | B29: =IF($H29=0,0,ROUNDUP(MAX($I29*'02_Assumptions'!$C$6/100,$K29),0)) -> 1 | C29: =IF($H29=0,0,ROUNDUP(MAX($I29*'02_Assumptions'!$C$6/100*(1+$J29*3),$K29*4),0)) -> 4 | D29: 7000000 | E29: ='02_Assumptions'!$C$63 -> 0.15 | F29: =$B29*$D29*12*(1+$E29) -> 96600000 | G29: =$C29*$D29*12*(1+$E29) -> 3.864e+08 | H29: 1 | I29: 1 | J29: 1 | K29: 0
A30: Mandor | B30: =IF($H30=0,0,ROUNDUP(MAX($I30*'02_Assumptions'!$C$6/100,$K30),0)) -> 4 | C30: =IF($H30=0,0,ROUNDUP(MAX($I30*'02_Assumptions'!$C$6/100*(1+$J30*3),$K30*4),0)) -> 4 | D30: 4500000 | E30: ='02_Assumptions'!$C$63 -> 0.15 | F30: =$B30*$D30*12*(1+$E30) -> 2.484e+08 | G30: =$C30*$D30*12*(1+$E30) -> 2.484e+08 | H30: 1 | I30: 4 | J30: 0 | K30: 0
A31: Keamanan | B31: =IF($H31=0,0,ROUNDUP(MAX($I31*'02_Assumptions'!$C$6/100,$K31),0)) -> 2 | C31: =IF($H31=0,0,ROUNDUP(MAX($I31*'02_Assumptions'!$C$6/100*(1+$J31*3),$K31*4),0)) -> 8 | D31: 3500000 | E31: ='02_Assumptions'!$C$63 -> 0.15 | F31: =$B31*$D31*12*(1+$E31) -> 96600000 | G31: =$C31*$D31*12*(1+$E31) -> 3.864e+08 | H31: 1 | I31: 2 | J31: 1 | K31: 0
A32: Penanggung jawab gudang/pembibitan | B32: =IF($H32=0,0,ROUNDUP(MAX($I32*'02_Assumptions'!$C$6/100,$K32),0)) -> 1 | C32: =IF($H32=0,0,ROUNDUP(MAX($I32*'02_Assumptions'!$C$6/100*(1+$J32*3),$K32*4),0)) -> 4 | D32: 4500000 | E32: ='02_Assumptions'!$C$63 -> 0.15 | F32: =$B32*$D32*12*(1+$E32) -> 62100000 | G32: =$C32*$D32*12*(1+$E32) -> 2.484e+08 | H32: 1 | I32: 1 | J32: 1 | K32: 0
A33: Mekanik/pengemudi | B33: =IF($H33=0,0,ROUNDUP(MAX($I33*'02_Assumptions'!$C$6/100,$K33),0)) -> 2 | C33: =IF($H33=0,0,ROUNDUP(MAX($I33*'02_Assumptions'!$C$6/100*(1+$J33*3),$K33*4),0)) -> 4 | D33: 5000000 | E33: ='02_Assumptions'!$C$63 -> 0.15 | F33: =$B33*$D33*12*(1+$E33) -> 138000000 | G33: =$C33*$D33*12*(1+$E33) -> 276000000 | H33: 1 | I33: 2 | J33: 0.33333333 | K33: 0
A34: TOTAL GAJI TAHUNAN STAF TETAP | F34: =SUM(F26:F33)+SUM(F44:F49) -> 1097100000 | G34: =SUM(G26:G33)+SUM(G44:G49) -> 2001000000
A37: C. Scenario helper totals
A38: Pembantu skenario | B38: T1 | C38: T2 | D38: T3 | E38: T4 | F38: T5 | G38: T6 | H38: T7 | I38: T8 | J38: T9 | K38: T10
A39: OPEX 1 lokasi | B39: =($F$34*(1+'02_Assumptions'!$C$11)^0+('05_Workplan_Labor'!$B$41+'17_Model_Fleksibel'!$N$68)*'02_Assumptions'!$C$60*(1+'02_Assumptions'!$C$11)^0+'07_Agri_Inputs'!$B$34+'06_Equipment_Tools'!$I$39*'02_Assumptions'!$C$113*(1+'02_Assumptions'!$C$11)^0+'02_Assumptions'!$C$179*(1+'02_Assumptions'!$C$11)^0+SUM('08_CAPEX_RAB'!$H$23:$H$26)*'02_Assumptions'!$C$114*(1+'02_Assumptions'!$C$11)^0+'04_Planting_Design'!$G$19*IF(1<=3,'02_Assumptions'!$C$181,'02_Assumptions'!$C$182)*(1+'02_Assumptions'!$C$11)^0+'14_Certification_ESG'!$D$15+'02_Assumptions'!$C$6*'02_Assumptions'!$C$118*(1+'02_Assumptions'!$C$11)^0+'02_Assumptions'!$C$180*(1+'02_Assumptions'!$C$11)^0+'17_Model_Fleksibel'!$H$100+'10_Production_Revenue'!$B$25)*(1+'02_Assumptions'!$C$15) -> 4886954100 | C39: =($F$34*(1+'02_Assumptions'!$C$11)^1+('05_Workplan_Labor'!$C$41+'17_Model_Fleksibel'!$O$68)*'02_Assumptions'!$C$60*(1+'02_Assumptions'!$C$11)^1+'07_Agri_Inputs'!$C$34+'06_Equipment_Tools'!$I$39*'02_Assumptions'!$C$113*(1+'02_Assumptions'!$C$11)^1+'02_Assumptions'!$C$179*(1+'02_Assumptions'!$C$11)^1+SUM('08_CAPEX_RAB'!$H$23:$H$26)*'02_Assumptions'!$C$114*(1+'02_Assumptions'!$C$11)^1+'04_Planting_Design'!$G$19*IF(2<=3,'02_Assumptions'!$C$181,'02_Assumptions'!$C$182)*(1+'02_Assumptions'!$C$11)^1+'14_Certification_ESG'!$E$15+'02_Assumptions'!$C$6*'02_Assumptions'!$C$118*(1+'02_Assumptions'!$C$11)^1+'02_Assumptions'!$C$180*(1+'02_Assumptions'!$C$11)^1+'17_Model_Fleksibel'!$I$100+'10_Production_Revenue'!$C$25)*(1+'02_Assumptions'!$C$15) -> 4.9916015e+09 | D39: =($F$34*(1+'02_Assumptions'!$C$11)^2+('05_Workplan_Labor'!$D$41+'17_Model_Fleksibel'!$P$68)*'02_Assumptions'!$C$60*(1+'02_Assumptions'!$C$11)^2+'07_Agri_Inputs'!$D$34+'06_Equipment_Tools'!$I$39*'02_Assumptions'!$C$113*(1+'02_Assumptions'!$C$11)^2+'02_Assumptions'!$C$179*(1+'02_Assumptions'!$C$11)^2+SUM('08_CAPEX_RAB'!$H$23:$H$26)*'02_Assumptions'!$C$114*(1+'02_Assumptions'!$C$11)^2+'04_Planting_Design'!$G$19*IF(3<=3,'02_Assumptions'!$C$181,'02_Assumptions'!$C$182)*(1+'02_Assumptions'!$C$11)^2+'14_Certification_ESG'!$F$15+'02_Assumptions'!$C$6*'02_Assumptions'!$C$118*(1+'02_Assumptions'!$C$11)^2+'02_Assumptions'!$C$180*(1+'02_Assumptions'!$C$11)^2+'17_Model_Fleksibel'!$J$100+'10_Production_Revenue'!$D$25)*(1+'02_Assumptions'!$C$15) -> 4.4201156e+09 | E39: =($F$34*(1+'02_Assumptions'!$C$11)^3+('05_Workplan_Labor'!$E$41+'17_Model_Fleksibel'!$Q$68)*'02_Assumptions'!$C$60*(1+'02_Assumptions'!$C$11)^3+'07_Agri_Inputs'!$E$34+'06_Equipment_Tools'!$I$39*'02_Assumptions'!$C$113*(1+'02_Assumptions'!$C$11)^3+'02_Assumptions'!$C$179*(1+'02_Assumptions'!$C$11)^3+SUM('08_CAPEX_RAB'!$H$23:$H$26)*'02_Assumptions'!$C$114*(1+'02_Assumptions'!$C$11)^3+'04_Planting_Design'!$G$19*IF(4<=3,'02_Assumptions'!$C$181,'02_Assumptions'!$C$182)*(1+'02_Assumptions'!$C$11)^3+'14_Certification_ESG'!$G$15+'02_Assumptions'!$C$6*'02_Assumptions'!$C$118*(1+'02_Assumptions'!$C$11)^3+'02_Assumptions'!$C$180*(1+'02_Assumptions'!$C$11)^3+'17_Model_Fleksibel'!$K$100+'10_Production_Revenue'!$E$25)*(1+'02_Assumptions'!$C$15) -> 4.2010953e+09 | F39: =($F$34*(1+'02_Assumptions'!$C$11)^4+('05_Workplan_Labor'!$F$41+'17_Model_Fleksibel'!$R$68)*'02_Assumptions'!$C$60*(1+'02_Assumptions'!$C$11)^4+'07_Agri_Inputs'!$F$34+'06_Equipment_Tools'!$I$39*'02_Assumptions'!$C$113*(1+'02_Assumptions'!$C$11)^4+'02_Assumptions'!$C$179*(1+'02_Assumptions'!$C$11)^4+SUM('08_CAPEX_RAB'!$H$23:$H$26)*'02_Assumptions'!$C$114*(1+'02_Assumptions'!$C$11)^4+'04_Planting_Design'!$G$19*IF(5<=3,'02_Assumptions'!$C$181,'02_Assumptions'!$C$182)*(1+'02_Assumptions'!$C$11)^4+'14_Certification_ESG'!$H$15+'02_Assumptions'!$C$6*'02_Assumptions'!$C$118*(1+'02_Assumptions'!$C$11)^4+'02_Assumptions'!$C$180*(1+'02_Assumptions'!$C$11)^4+'17_Model_Fleksibel'!$L$100+'10_Production_Revenue'!$F$25)*(1+'02_Assumptions'!$C$15) -> 4.2718268e+09 | G39: =($F$34*(1+'02_Assumptions'!$C$11)^5+('05_Workplan_Labor'!$G$41+'17_Model_Fleksibel'!$S$68)*'02_Assumptions'!$C$60*(1+'02_Assumptions'!$C$11)^5+'07_Agri_Inputs'!$G$34+'06_Equipment_Tools'!$I$39*'02_Assumptions'!$C$113*(1+'02_Assumptions'!$C$11)^5+'02_Assumptions'!$C$179*(1+'02_Assumptions'!$C$11)^5+SUM('08_CAPEX_RAB'!$H$23:$H$26)*'02_Assumptions'!$C$114*(1+'02_Assumptions'!$C$11)^5+'04_Planting_Design'!$G$19*IF(6<=3,'02_Assumptions'!$C$181,'02_Assumptions'!$C$182)*(1+'02_Assumptions'!$C$11)^5+'14_Certification_ESG'!$I$15+'02_Assumptions'!$C$6*'02_Assumptions'!$C$118*(1+'02_Assumptions'!$C$11)^5+'02_Assumptions'!$C$180*(1+'02_Assumptions'!$C$11)^5+'17_Model_Fleksibel'!$M$100+'10_Production_Revenue'!$G$25)*(1+'02_Assumptions'!$C$15) -> 4.5750778e+09 | H39: =($F$34*(1+'02_Assumptions'!$C$11)^6+('05_Workplan_Labor'!$H$41+'17_Model_Fleksibel'!$T$68)*'02_Assumptions'!$C$60*(1+'02_Assumptions'!$C$11)^6+'07_Agri_Inputs'!$H$34+'06_Equipment_Tools'!$I$39*'02_Assumptions'!$C$113*(1+'02_Assumptions'!$C$11)^6+'02_Assumptions'!$C$179*(1+'02_Assumptions'!$C$11)^6+SUM('08_CAPEX_RAB'!$H$23:$H$26)*'02_Assumptions'!$C$114*(1+'02_Assumptions'!$C$11)^6+'04_Planting_Design'!$G$19*IF(7<=3,'02_Assumptions'!$C$181,'02_Assumptions'!$C$182)*(1+'02_Assumptions'!$C$11)^6+'14_Certification_ESG'!$J$15+'02_Assumptions'!$C$6*'02_Assumptions'!$C$118*(1+'02_Assumptions'!$C$11)^6+'02_Assumptions'!$C$180*(1+'02_Assumptions'!$C$11)^6+'17_Model_Fleksibel'!$N$100+'10_Production_Revenue'!$H$25)*(1+'02_Assumptions'!$C$15) -> 4.8128669e+09 | I39: =($F$34*(1+'02_Assumptions'!$C$11)^7+('05_Workplan_Labor'!$I$41+'17_Model_Fleksibel'!$U$68)*'02_Assumptions'!$C$60*(1+'02_Assumptions'!$C$11)^7+'07_Agri_Inputs'!$I$34+'06_Equipment_Tools'!$I$39*'02_Assumptions'!$C$113*(1+'02_Assumptions'!$C$11)^7+'02_Assumptions'!$C$179*(1+'02_Assumptions'!$C$11)^7+SUM('08_CAPEX_RAB'!$H$23:$H$26)*'02_Assumptions'!$C$114*(1+'02_Assumptions'!$C$11)^7+'04_Planting_Design'!$G$19*IF(8<=3,'02_Assumptions'!$C$181,'02_Assumptions'!$C$182)*(1+'02_Assumptions'!$C$11)^7+'14_Certification_ESG'!$K$15+'02_Assumptions'!$C$6*'02_Assumptions'!$C$118*(1+'02_Assumptions'!$C$11)^7+'02_Assumptions'!$C$180*(1+'02_Assumptions'!$C$11)^7+'17_Model_Fleksibel'!$O$100+'10_Production_Revenue'!$I$25)*(1+'02_Assumptions'!$C$15) -> 5.2234358e+09 | J39: =($F$34*(1+'02_Assumptions'!$C$11)^8+('05_Workplan_Labor'!$J$41+'17_Model_Fleksibel'!$V$68)*'02_Assumptions'!$C$60*(1+'02_Assumptions'!$C$11)^8+'07_Agri_Inputs'!$J$34+'06_Equipment_Tools'!$I$39*'02_Assumptions'!$C$113*(1+'02_Assumptions'!$C$11)^8+'02_Assumptions'!$C$179*(1+'02_Assumptions'!$C$11)^8+SUM('08_CAPEX_RAB'!$H$23:$H$26)*'02_Assumptions'!$C$114*(1+'02_Assumptions'!$C$11)^8+'04_Planting_Design'!$G$19*IF(9<=3,'02_Assumptions'!$C$181,'02_Assumptions'!$C$182)*(1+'02_Assumptions'!$C$11)^8+'14_Certification_ESG'!$L$15+'02_Assumptions'!$C$6*'02_Assumptions'!$C$118*(1+'02_Assumptions'!$C$11)^8+'02_Assumptions'!$C$180*(1+'02_Assumptions'!$C$11)^8+'17_Model_Fleksibel'!$P$100+'10_Production_Revenue'!$J$25)*(1+'02_Assumptions'!$C$15) -> 5.4245962e+09 | K39: =($F$34*(1+'02_Assumptions'!$C$11)^9+('05_Workplan_Labor'!$K$41+'17_Model_Fleksibel'!$W$68)*'02_Assumptions'!$C$60*(1+'02_Assumptions'!$C$11)^9+'07_Agri_Inputs'!$K$34+'06_Equipment_Tools'!$I$39*'02_Assumptions'!$C$113*(1+'02_Assumptions'!$C$11)^9+'02_Assumptions'!$C$179*(1+'02_Assumptions'!$C$11)^9+SUM('08_CAPEX_RAB'!$H$23:$H$26)*'02_Assumptions'!$C$114*(1+'02_Assumptions'!$C$11)^9+'04_Planting_Design'!$G$19*IF(10<=3,'02_Assumptions'!$C$181,'02_Assumptions'!$C$182)*(1+'02_Assumptions'!$C$11)^9+'14_Certification_ESG'!$M$15+'02_Assumptions'!$C$6*'02_Assumptions'!$C$118*(1+'02_Assumptions'!$C$11)^9+'02_Assumptions'!$C$180*(1+'02_Assumptions'!$C$11)^9+'17_Model_Fleksibel'!$Q$100+'10_Production_Revenue'!$K$25)*(1+'02_Assumptions'!$C$15) -> 5.8081261e+09
A40: OPEX 4 lokasi | B40: =($G$34*(1+'02_Assumptions'!$C$11)^0+('05_Workplan_Labor'!$B$41+'17_Model_Fleksibel'!$N$68)*'02_Assumptions'!$C$60*(1+'02_Assumptions'!$C$11)^0*(1+'02_Assumptions'!$C$177*3)+'07_Agri_Inputs'!$B$34+'06_Equipment_Tools'!$J$39*'02_Assumptions'!$C$113*(1+'02_Assumptions'!$C$11)^0+'02_Assumptions'!$C$179*(1+'02_Assumptions'!$C$11)^0*(1+'02_Assumptions'!$C$178*3)+SUM('08_CAPEX_RAB'!$I$23:$I$26)*'02_Assumptions'!$C$114*(1+'02_Assumptions'!$C$11)^0+'04_Planting_Design'!$G$19*IF(1<=3,'02_Assumptions'!$C$181,'02_Assumptions'!$C$182)*(1+'02_Assumptions'!$C$11)^0+'14_Certification_ESG'!$D$15+'02_Assumptions'!$C$6*'02_Assumptions'!$C$118*(1+'02_Assumptions'!$C$11)^0+'02_Assumptions'!$C$180*(1+'02_Assumptions'!$C$11)^0*(1+'02_Assumptions'!$C$178*3)+'17_Model_Fleksibel'!$H$100+'10_Production_Revenue'!$B$25)*(1+'02_Assumptions'!$C$15) -> 6.0942124e+09 | C40: =($G$34*(1+'02_Assumptions'!$C$11)^1+('05_Workplan_Labor'!$C$41+'17_Model_Fleksibel'!$O$68)*'02_Assumptions'!$C$60*(1+'02_Assumptions'!$C$11)^1*(1+'02_Assumptions'!$C$177*3)+'07_Agri_Inputs'!$C$34+'06_Equipment_Tools'!$J$39*'02_Assumptions'!$C$113*(1+'02_Assumptions'!$C$11)^1+'02_Assumptions'!$C$179*(1+'02_Assumptions'!$C$11)^1*(1+'02_Assumptions'!$C$178*3)+SUM('08_CAPEX_RAB'!$I$23:$I$26)*'02_Assumptions'!$C$114*(1+'02_Assumptions'!$C$11)^1+'04_Planting_Design'!$G$19*IF(2<=3,'02_Assumptions'!$C$181,'02_Assumptions'!$C$182)*(1+'02_Assumptions'!$C$11)^1+'14_Certification_ESG'!$E$15+'02_Assumptions'!$C$6*'02_Assumptions'!$C$118*(1+'02_Assumptions'!$C$11)^1+'02_Assumptions'!$C$180*(1+'02_Assumptions'!$C$11)^1*(1+'02_Assumptions'!$C$178*3)+'17_Model_Fleksibel'!$I$100+'10_Production_Revenue'!$C$25)*(1+'02_Assumptions'!$C$15) -> 6.245305e+09 | D40: =($G$34*(1+'02_Assumptions'!$C$11)^2+('05_Workplan_Labor'!$D$41+'17_Model_Fleksibel'!$P$68)*'02_Assumptions'!$C$60*(1+'02_Assumptions'!$C$11)^2*(1+'02_Assumptions'!$C$177*3)+'07_Agri_Inputs'!$D$34+'06_Equipment_Tools'!$J$39*'02_Assumptions'!$C$113*(1+'02_Assumptions'!$C$11)^2+'02_Assumptions'!$C$179*(1+'02_Assumptions'!$C$11)^2*(1+'02_Assumptions'!$C$178*3)+SUM('08_CAPEX_RAB'!$I$23:$I$26)*'02_Assumptions'!$C$114*(1+'02_Assumptions'!$C$11)^2+'04_Planting_Design'!$G$19*IF(3<=3,'02_Assumptions'!$C$181,'02_Assumptions'!$C$182)*(1+'02_Assumptions'!$C$11)^2+'14_Certification_ESG'!$F$15+'02_Assumptions'!$C$6*'02_Assumptions'!$C$118*(1+'02_Assumptions'!$C$11)^2+'02_Assumptions'!$C$180*(1+'02_Assumptions'!$C$11)^2*(1+'02_Assumptions'!$C$178*3)+'17_Model_Fleksibel'!$J$100+'10_Production_Revenue'!$D$25)*(1+'02_Assumptions'!$C$15) -> 5.7151227e+09 | E40: =($G$34*(1+'02_Assumptions'!$C$11)^3+('05_Workplan_Labor'!$E$41+'17_Model_Fleksibel'!$Q$68)*'02_Assumptions'!$C$60*(1+'02_Assumptions'!$C$11)^3*(1+'02_Assumptions'!$C$177*3)+'07_Agri_Inputs'!$E$34+'06_Equipment_Tools'!$J$39*'02_Assumptions'!$C$113*(1+'02_Assumptions'!$C$11)^3+'02_Assumptions'!$C$179*(1+'02_Assumptions'!$C$11)^3*(1+'02_Assumptions'!$C$178*3)+SUM('08_CAPEX_RAB'!$I$23:$I$26)*'02_Assumptions'!$C$114*(1+'02_Assumptions'!$C$11)^3+'04_Planting_Design'!$G$19*IF(4<=3,'02_Assumptions'!$C$181,'02_Assumptions'!$C$182)*(1+'02_Assumptions'!$C$11)^3+'14_Certification_ESG'!$G$15+'02_Assumptions'!$C$6*'02_Assumptions'!$C$118*(1+'02_Assumptions'!$C$11)^3+'02_Assumptions'!$C$180*(1+'02_Assumptions'!$C$11)^3*(1+'02_Assumptions'!$C$178*3)+'17_Model_Fleksibel'!$K$100+'10_Production_Revenue'!$E$25)*(1+'02_Assumptions'!$C$15) -> 5.5385483e+09 | F40: =($G$34*(1+'02_Assumptions'!$C$11)^4+('05_Workplan_Labor'!$F$41+'17_Model_Fleksibel'!$R$68)*'02_Assumptions'!$C$60*(1+'02_Assumptions'!$C$11)^4*(1+'02_Assumptions'!$C$177*3)+'07_Agri_Inputs'!$F$34+'06_Equipment_Tools'!$J$39*'02_Assumptions'!$C$113*(1+'02_Assumptions'!$C$11)^4+'02_Assumptions'!$C$179*(1+'02_Assumptions'!$C$11)^4*(1+'02_Assumptions'!$C$178*3)+SUM('08_CAPEX_RAB'!$I$23:$I$26)*'02_Assumptions'!$C$114*(1+'02_Assumptions'!$C$11)^4+'04_Planting_Design'!$G$19*IF(5<=3,'02_Assumptions'!$C$181,'02_Assumptions'!$C$182)*(1+'02_Assumptions'!$C$11)^4+'14_Certification_ESG'!$H$15+'02_Assumptions'!$C$6*'02_Assumptions'!$C$118*(1+'02_Assumptions'!$C$11)^4+'02_Assumptions'!$C$180*(1+'02_Assumptions'!$C$11)^4*(1+'02_Assumptions'!$C$178*3)+'17_Model_Fleksibel'!$L$100+'10_Production_Revenue'!$F$25)*(1+'02_Assumptions'!$C$15) -> 5.6597944e+09 | G40: =($G$34*(1+'02_Assumptions'!$C$11)^5+('05_Workplan_Labor'!$G$41+'17_Model_Fleksibel'!$S$68)*'02_Assumptions'!$C$60*(1+'02_Assumptions'!$C$11)^5*(1+'02_Assumptions'!$C$177*3)+'07_Agri_Inputs'!$G$34+'06_Equipment_Tools'!$J$39*'02_Assumptions'!$C$113*(1+'02_Assumptions'!$C$11)^5+'02_Assumptions'!$C$179*(1+'02_Assumptions'!$C$11)^5*(1+'02_Assumptions'!$C$178*3)+SUM('08_CAPEX_RAB'!$I$23:$I$26)*'02_Assumptions'!$C$114*(1+'02_Assumptions'!$C$11)^5+'04_Planting_Design'!$G$19*IF(6<=3,'02_Assumptions'!$C$181,'02_Assumptions'!$C$182)*(1+'02_Assumptions'!$C$11)^5+'14_Certification_ESG'!$I$15+'02_Assumptions'!$C$6*'02_Assumptions'!$C$118*(1+'02_Assumptions'!$C$11)^5+'02_Assumptions'!$C$180*(1+'02_Assumptions'!$C$11)^5*(1+'02_Assumptions'!$C$178*3)+'17_Model_Fleksibel'!$M$100+'10_Production_Revenue'!$G$25)*(1+'02_Assumptions'!$C$15) -> 6.0166756e+09 | H40: =($G$34*(1+'02_Assumptions'!$C$11)^6+('05_Workplan_Labor'!$H$41+'17_Model_Fleksibel'!$T$68)*'02_Assumptions'!$C$60*(1+'02_Assumptions'!$C$11)^6*(1+'02_Assumptions'!$C$177*3)+'07_Agri_Inputs'!$H$34+'06_Equipment_Tools'!$J$39*'02_Assumptions'!$C$113*(1+'02_Assumptions'!$C$11)^6+'02_Assumptions'!$C$179*(1+'02_Assumptions'!$C$11)^6*(1+'02_Assumptions'!$C$178*3)+SUM('08_CAPEX_RAB'!$I$23:$I$26)*'02_Assumptions'!$C$114*(1+'02_Assumptions'!$C$11)^6+'04_Planting_Design'!$G$19*IF(7<=3,'02_Assumptions'!$C$181,'02_Assumptions'!$C$182)*(1+'02_Assumptions'!$C$11)^6+'14_Certification_ESG'!$J$15+'02_Assumptions'!$C$6*'02_Assumptions'!$C$118*(1+'02_Assumptions'!$C$11)^6+'02_Assumptions'!$C$180*(1+'02_Assumptions'!$C$11)^6*(1+'02_Assumptions'!$C$178*3)+'17_Model_Fleksibel'!$N$100+'10_Production_Revenue'!$H$25)*(1+'02_Assumptions'!$C$15) -> 6.3114972e+09 | I40: =($G$34*(1+'02_Assumptions'!$C$11)^7+('05_Workplan_Labor'!$I$41+'17_Model_Fleksibel'!$U$68)*'02_Assumptions'!$C$60*(1+'02_Assumptions'!$C$11)^7*(1+'02_Assumptions'!$C$177*3)+'07_Agri_Inputs'!$I$34+'06_Equipment_Tools'!$J$39*'02_Assumptions'!$C$113*(1+'02_Assumptions'!$C$11)^7+'02_Assumptions'!$C$179*(1+'02_Assumptions'!$C$11)^7*(1+'02_Assumptions'!$C$178*3)+SUM('08_CAPEX_RAB'!$I$23:$I$26)*'02_Assumptions'!$C$114*(1+'02_Assumptions'!$C$11)^7+'04_Planting_Design'!$G$19*IF(8<=3,'02_Assumptions'!$C$181,'02_Assumptions'!$C$182)*(1+'02_Assumptions'!$C$11)^7+'14_Certification_ESG'!$K$15+'02_Assumptions'!$C$6*'02_Assumptions'!$C$118*(1+'02_Assumptions'!$C$11)^7+'02_Assumptions'!$C$180*(1+'02_Assumptions'!$C$11)^7*(1+'02_Assumptions'!$C$178*3)+'17_Model_Fleksibel'!$O$100+'10_Production_Revenue'!$I$25)*(1+'02_Assumptions'!$C$15) -> 6.7820113e+09 | J40: =($G$34*(1+'02_Assumptions'!$C$11)^8+('05_Workplan_Labor'!$J$41+'17_Model_Fleksibel'!$V$68)*'02_Assumptions'!$C$60*(1+'02_Assumptions'!$C$11)^8*(1+'02_Assumptions'!$C$177*3)+'07_Agri_Inputs'!$J$34+'06_Equipment_Tools'!$J$39*'02_Assumptions'!$C$113*(1+'02_Assumptions'!$C$11)^8+'02_Assumptions'!$C$179*(1+'02_Assumptions'!$C$11)^8*(1+'02_Assumptions'!$C$178*3)+SUM('08_CAPEX_RAB'!$I$23:$I$26)*'02_Assumptions'!$C$114*(1+'02_Assumptions'!$C$11)^8+'04_Planting_Design'!$G$19*IF(9<=3,'02_Assumptions'!$C$181,'02_Assumptions'!$C$182)*(1+'02_Assumptions'!$C$11)^8+'14_Certification_ESG'!$L$15+'02_Assumptions'!$C$6*'02_Assumptions'!$C$118*(1+'02_Assumptions'!$C$11)^8+'02_Assumptions'!$C$180*(1+'02_Assumptions'!$C$11)^8*(1+'02_Assumptions'!$C$178*3)+'17_Model_Fleksibel'!$P$100+'10_Production_Revenue'!$J$25)*(1+'02_Assumptions'!$C$15) -> 7.0455147e+09 | K40: =($G$34*(1+'02_Assumptions'!$C$11)^9+('05_Workplan_Labor'!$K$41+'17_Model_Fleksibel'!$W$68)*'02_Assumptions'!$C$60*(1+'02_Assumptions'!$C$11)^9*(1+'02_Assumptions'!$C$177*3)+'07_Agri_Inputs'!$K$34+'06_Equipment_Tools'!$J$39*'02_Assumptions'!$C$113*(1+'02_Assumptions'!$C$11)^9+'02_Assumptions'!$C$179*(1+'02_Assumptions'!$C$11)^9*(1+'02_Assumptions'!$C$178*3)+SUM('08_CAPEX_RAB'!$I$23:$I$26)*'02_Assumptions'!$C$114*(1+'02_Assumptions'!$C$11)^9+'04_Planting_Design'!$G$19*IF(10<=3,'02_Assumptions'!$C$181,'02_Assumptions'!$C$182)*(1+'02_Assumptions'!$C$11)^9+'14_Certification_ESG'!$M$15+'02_Assumptions'!$C$6*'02_Assumptions'!$C$118*(1+'02_Assumptions'!$C$11)^9+'02_Assumptions'!$C$180*(1+'02_Assumptions'!$C$11)^9*(1+'02_Assumptions'!$C$178*3)+'17_Model_Fleksibel'!$Q$100+'10_Production_Revenue'!$K$25)*(1+'02_Assumptions'!$C$15) -> 7.4938813e+09
A42: Baris tambahan staf
A44: Staf tambahan 1 | B44: =IF($H44=0,0,ROUNDUP(MAX($I44*'02_Assumptions'!$C$6/100,$K44),0)) -> 0 | C44: =IF($H44=0,0,ROUNDUP(MAX($I44*'02_Assumptions'!$C$6/100*(1+$J44*3),$K44*4),0)) -> 0 | D44: 0 | E44: 0.15 | F44: =$B44*$D44*12*(1+$E44) -> 0 | G44: =$C44*$D44*12*(1+$E44) -> 0 | H44: 0 | I44: 0 | J44: 0 | K44: 0
A45: Staf tambahan 2 | B45: =IF($H45=0,0,ROUNDUP(MAX($I45*'02_Assumptions'!$C$6/100,$K45),0)) -> 0 | C45: =IF($H45=0,0,ROUNDUP(MAX($I45*'02_Assumptions'!$C$6/100*(1+$J45*3),$K45*4),0)) -> 0 | D45: 0 | E45: 0.15 | F45: =$B45*$D45*12*(1+$E45) -> 0 | G45: =$C45*$D45*12*(1+$E45) -> 0 | H45: 0 | I45: 0 | J45: 0 | K45: 0
A46: Staf tambahan 3 | B46: =IF($H46=0,0,ROUNDUP(MAX($I46*'02_Assumptions'!$C$6/100,$K46),0)) -> 0 | C46: =IF($H46=0,0,ROUNDUP(MAX($I46*'02_Assumptions'!$C$6/100*(1+$J46*3),$K46*4),0)) -> 0 | D46: 0 | E46: 0.15 | F46: =$B46*$D46*12*(1+$E46) -> 0 | G46: =$C46*$D46*12*(1+$E46) -> 0 | H46: 0 | I46: 0 | J46: 0 | K46: 0
A47: Staf tambahan 4 | B47: =IF($H47=0,0,ROUNDUP(MAX($I47*'02_Assumptions'!$C$6/100,$K47),0)) -> 0 | C47: =IF($H47=0,0,ROUNDUP(MAX($I47*'02_Assumptions'!$C$6/100*(1+$J47*3),$K47*4),0)) -> 0 | D47: 0 | E47: 0.15 | F47: =$B47*$D47*12*(1+$E47) -> 0 | G47: =$C47*$D47*12*(1+$E47) -> 0 | H47: 0 | I47: 0 | J47: 0 | K47: 0
A48: Staf tambahan 5 | B48: =IF($H48=0,0,ROUNDUP(MAX($I48*'02_Assumptions'!$C$6/100,$K48),0)) -> 0 | C48: =IF($H48=0,0,ROUNDUP(MAX($I48*'02_Assumptions'!$C$6/100*(1+$J48*3),$K48*4),0)) -> 0 | D48: 0 | E48: 0.15 | F48: =$B48*$D48*12*(1+$E48) -> 0 | G48: =$C48*$D48*12*(1+$E48) -> 0 | H48: 0 | I48: 0 | J48: 0 | K48: 0
A49: Staf tambahan 6 | B49: =IF($H49=0,0,ROUNDUP(MAX($I49*'02_Assumptions'!$C$6/100,$K49),0)) -> 0 | C49: =IF($H49=0,0,ROUNDUP(MAX($I49*'02_Assumptions'!$C$6/100*(1+$J49*3),$K49*4),0)) -> 0 | D49: 0 | E49: 0.15 | F49: =$B49*$D49*12*(1+$E49) -> 0 | G49: =$C49*$D49*12*(1+$E49) -> 0 | H49: 0 | I49: 0 | J49: 0 | K49: 0

Sheet 10_Production_Revenue
A1: Produksi dan Pendapatan 10 Tahun
A2: Menghitung produksi dan pendapatan per komoditas berdasarkan tanaman hidup, kurva hasil menurut umur, harga kebun, dan eskalasi harga. Pisang menopang kas awal, kelapa mulai ringan pada Tahun 3, dan durian dasar pada Tahun 5; opsi hanya masuk bila diaktifkan.
A4: Ukuran | B4: T1 | C4: T2 | D4: T3 | E4: T4 | F4: T5 | G4: T6 | H4: T7 | I4: T8 | J4: T9 | K4: T10
A5: Rumpun pisang dipertahankan | B5: ='04_Planting_Design'!$D$26*'02_Assumptions'!$B$123 -> 40480 | C5: ='04_Planting_Design'!$D$26*'02_Assumptions'!$C$123 -> 36432 | D5: ='04_Planting_Design'!$D$26*'02_Assumptions'!$D$123 -> 28336 | E5: ='04_Planting_Design'!$D$26*'02_Assumptions'!$E$123 -> 18216 | F5: ='04_Planting_Design'!$D$26*'02_Assumptions'!$F$123 -> 10120 | G5: ='04_Planting_Design'!$D$26*'02_Assumptions'!$G$123 -> 6072 | H5: ='04_Planting_Design'!$D$26*'02_Assumptions'!$H$123 -> 4048 | I5: ='04_Planting_Design'!$D$26*'02_Assumptions'!$I$123 -> 4048 | J5: ='04_Planting_Design'!$D$26*'02_Assumptions'!$J$123 -> 4048 | K5: ='04_Planting_Design'!$D$26*'02_Assumptions'!$K$123 -> 4048
A6: Hasil pisang kg/rumpun | B6: ='02_Assumptions'!$B$124 -> 18 | C6: ='02_Assumptions'!$C$124 -> 20 | D6: ='02_Assumptions'!$D$124 -> 20 | E6: ='02_Assumptions'!$E$124 -> 19 | F6: ='02_Assumptions'!$F$124 -> 18 | G6: ='02_Assumptions'!$G$124 -> 18 | H6: ='02_Assumptions'!$H$124 -> 18 | I6: ='02_Assumptions'!$I$124 -> 18 | J6: ='02_Assumptions'!$J$124 -> 18 | K6: ='02_Assumptions'!$K$124 -> 18
A7: Pisang layak jual kg | B7: =B5*B6*'02_Assumptions'!$C$45 -> 619344 | C7: =C5*C6*'02_Assumptions'!$C$45 -> 619344 | D7: =D5*D6*'02_Assumptions'!$C$45 -> 481712 | E7: =E5*E6*'02_Assumptions'!$C$45 -> 294188.4 | F7: =F5*F6*'02_Assumptions'!$C$45 -> 154836 | G7: =G5*G6*'02_Assumptions'!$C$45 -> 92901.6 | H7: =H5*H6*'02_Assumptions'!$C$45 -> 61934.4 | I7: =I5*I6*'02_Assumptions'!$C$45 -> 61934.4 | ... K7: =K5*K6*'02_Assumptions'!$C$45 -> 61934.4
A8: Harga pisang Rp/kg | B8: ='02_Assumptions'!$C$48*(1+'02_Assumptions'!$C$12)^0*(1+IF(1>='02_Assumptions'!$C$17+'02_Assumptions'!$C$18+1,'02_Assumptions'!$C$19,0)) -> 6000 | C8: ='02_Assumptions'!$C$48*(1+'02_Assumptions'!$C$12)^1*(1+IF(2>='02_Assumptions'!$C$17+'02_Assumptions'!$C$18+1,'02_Assumptions'!$C$19,0)) -> 6180 | D8: ='02_Assumptions'!$C$48*(1+'02_Assumptions'!$C$12)^2*(1+IF(3>='02_Assumptions'!$C$17+'02_Assumptions'!$C$18+1,'02_Assumptions'!$C$19,0)) -> 6365.4 | E8: ='02_Assumptions'!$C$48*(1+'02_Assumptions'!$C$12)^3*(1+IF(4>='02_Assumptions'!$C$17+'02_Assumptions'!$C$18+1,'02_Assumptions'!$C$19,0)) -> 6556.362 | F8: ='02_Assumptions'!$C$48*(1+'02_Assumptions'!$C$12)^4*(1+IF(5>='02_Assumptions'!$C$17+'02_Assumptions'!$C$18+1,'02_Assumptions'!$C$19,0)) -> 6753.0529 | G8: ='02_Assumptions'!$C$48*(1+'02_Assumptions'!$C$12)^5*(1+IF(6>='02_Assumptions'!$C$17+'02_Assumptions'!$C$18+1,'02_Assumptions'!$C$19,0)) -> 6955.6444 | H8: ='02_Assumptions'!$C$48*(1+'02_Assumptions'!$C$12)^6*(1+IF(7>='02_Assumptions'!$C$17+'02_Assumptions'!$C$18+1,'02_Assumptions'!$C$19,0)) -> 7164.3138 | I8: ='02_Assumptions'!$C$48*(1+'02_Assumptions'!$C$12)^7*(1+IF(8>='02_Assumptions'!$C$17+'02_Assumptions'!$C$18+1,'02_Assumptions'!$C$19,0)) -> 7379.2432 | J8: ='02_Assumptions'!$C$48*(1+'02_Assumptions'!$C$12)^8*(1+IF(9>='02_Assumptions'!$C$17+'02_Assumptions'!$C$18+1,'02_Assumptions'!$C$19,0)) -> 7600.6205 | K8: ='02_Assumptions'!$C$48*(1+'02_Assumptions'!$C$12)^9*(1+IF(10>='02_Assumptions'!$C$17+'02_Assumptions'!$C$18+1,'02_Assumptions'!$C$19,0)) -> 7828.6391
A9: PENDAPATAN PISANG | B9: =B7*B8 -> 3716064000 | C9: =C7*C8 -> 3827545920 | D9: =D7*D8 -> 3.0662896e+09 | E9: =E7*E8 -> 1.9288056e+09 | F9: =F7*F8 -> 1.0456157e+09 | G9: =G7*G8 -> 6.461905e+08 | H9: =H7*H8 -> 4.4371748e+08 | I9: =I7*I8 -> 4.57029e+08 | ... K9: =K7*K8 -> 4.8486207e+08
A10: Pohon kelapa hidup | B10: ='04_Planting_Design'!$D$24 -> 6938.8 | C10: ='04_Planting_Design'!$D$24 -> 6938.8 | D10: ='04_Planting_Design'!$D$24 -> 6938.8 | E10: ='04_Planting_Design'!$D$24 -> 6938.8 | F10: ='04_Planting_Design'!$D$24 -> 6938.8 | G10: ='04_Planting_Design'!$D$24 -> 6938.8 | H10: ='04_Planting_Design'!$D$24 -> 6938.8 | I10: ='04_Planting_Design'!$D$24 -> 6938.8 | ... K10: ='04_Planting_Design'!$D$24 -> 6938.8
A11: Butir kelapa/pohon | B11: ='02_Assumptions'!$B$125 -> 0 | C11: ='02_Assumptions'!$C$125 -> 0 | D11: ='02_Assumptions'!$D$125 -> 15 | E11: ='02_Assumptions'!$E$125 -> 35 | F11: ='02_Assumptions'!$F$125 -> 60 | G11: ='02_Assumptions'!$G$125 -> 80 | H11: ='02_Assumptions'!$H$125 -> 100 | I11: ='02_Assumptions'!$I$125 -> 110 | J11: ='02_Assumptions'!$J$125 -> 110 | K11: ='02_Assumptions'!$K$125 -> 110
A12: Kelapa layak jual (butir) | B12: =B10*B11*'02_Assumptions'!$C$43 -> 0 | C12: =C10*C11*'02_Assumptions'!$C$43 -> 0 | D12: =D10*D11*'02_Assumptions'!$C$43 -> 93673.8 | E12: =E10*E11*'02_Assumptions'!$C$43 -> 218572.2 | F12: =F10*F11*'02_Assumptions'!$C$43 -> 374695.2 | G12: =G10*G11*'02_Assumptions'!$C$43 -> 499593.6 | H12: =H10*H11*'02_Assumptions'!$C$43 -> 624492 | I12: =I10*I11*'02_Assumptions'!$C$43 -> 686941.2 | ... K12: =K10*K11*'02_Assumptions'!$C$43 -> 686941.2
A13: Harga kelapa Rp/butir | B13: ='02_Assumptions'!$C$46*(1+'02_Assumptions'!$C$12)^0*(1+IF(1>='02_Assumptions'!$C$17+'02_Assumptions'!$C$18+1,'02_Assumptions'!$C$19,0)) -> 3000 | C13: ='02_Assumptions'!$C$46*(1+'02_Assumptions'!$C$12)^1*(1+IF(2>='02_Assumptions'!$C$17+'02_Assumptions'!$C$18+1,'02_Assumptions'!$C$19,0)) -> 3090 | D13: ='02_Assumptions'!$C$46*(1+'02_Assumptions'!$C$12)^2*(1+IF(3>='02_Assumptions'!$C$17+'02_Assumptions'!$C$18+1,'02_Assumptions'!$C$19,0)) -> 3182.7 | E13: ='02_Assumptions'!$C$46*(1+'02_Assumptions'!$C$12)^3*(1+IF(4>='02_Assumptions'!$C$17+'02_Assumptions'!$C$18+1,'02_Assumptions'!$C$19,0)) -> 3278.181 | F13: ='02_Assumptions'!$C$46*(1+'02_Assumptions'!$C$12)^4*(1+IF(5>='02_Assumptions'!$C$17+'02_Assumptions'!$C$18+1,'02_Assumptions'!$C$19,0)) -> 3376.5264 | G13: ='02_Assumptions'!$C$46*(1+'02_Assumptions'!$C$12)^5*(1+IF(6>='02_Assumptions'!$C$17+'02_Assumptions'!$C$18+1,'02_Assumptions'!$C$19,0)) -> 3477.8222 | H13: ='02_Assumptions'!$C$46*(1+'02_Assumptions'!$C$12)^6*(1+IF(7>='02_Assumptions'!$C$17+'02_Assumptions'!$C$18+1,'02_Assumptions'!$C$19,0)) -> 3582.1569 | I13: ='02_Assumptions'!$C$46*(1+'02_Assumptions'!$C$12)^7*(1+IF(8>='02_Assumptions'!$C$17+'02_Assumptions'!$C$18+1,'02_Assumptions'!$C$19,0)) -> 3689.6216 | J13: ='02_Assumptions'!$C$46*(1+'02_Assumptions'!$C$12)^8*(1+IF(9>='02_Assumptions'!$C$17+'02_Assumptions'!$C$18+1,'02_Assumptions'!$C$19,0)) -> 3800.3102 | K13: ='02_Assumptions'!$C$46*(1+'02_Assumptions'!$C$12)^9*(1+IF(10>='02_Assumptions'!$C$17+'02_Assumptions'!$C$18+1,'02_Assumptions'!$C$19,0)) -> 3914.3196
A14: PENDAPATAN KELAPA | B14: =B12*B13 -> 0 | C14: =C12*C13 -> 0 | D14: =D12*D13 -> 2.981356e+08 | E14: =E12*E13 -> 7.1651923e+08 | F14: =F12*F13 -> 1.2651682e+09 | G14: =G12*G13 -> 1.7374977e+09 | H14: =H12*H13 -> 2.2370283e+09 | I14: =I12*I13 -> 2.5345531e+09 | ... K14: =K12*K13 -> 2.6889074e+09
A15: Pohon durian hidup | B15: ='04_Planting_Design'!$D$25 -> 2376 | C15: ='04_Planting_Design'!$D$25 -> 2376 | D15: ='04_Planting_Design'!$D$25 -> 2376 | E15: ='04_Planting_Design'!$D$25 -> 2376 | F15: ='04_Planting_Design'!$D$25 -> 2376 | G15: ='04_Planting_Design'!$D$25 -> 2376 | H15: ='04_Planting_Design'!$D$25 -> 2376 | I15: ='04_Planting_Design'!$D$25 -> 2376 | ... K15: ='04_Planting_Design'!$D$25 -> 2376
A16: Hasil durian kg/pohon | B16: ='02_Assumptions'!$B$126 -> 0 | C16: ='02_Assumptions'!$C$126 -> 0 | D16: ='02_Assumptions'!$D$126 -> 0 | E16: ='02_Assumptions'!$E$126 -> 0 | F16: ='02_Assumptions'!$F$126 -> 10 | G16: ='02_Assumptions'!$G$126 -> 25 | H16: ='02_Assumptions'!$H$126 -> 45 | I16: ='02_Assumptions'!$I$126 -> 65 | J16: ='02_Assumptions'!$J$126 -> 85 | K16: ='02_Assumptions'!$K$126 -> 100
A17: Durian layak jual kg | B17: =B15*B16*'02_Assumptions'!$C$44 -> 0 | C17: =C15*C16*'02_Assumptions'!$C$44 -> 0 | D17: =D15*D16*'02_Assumptions'!$C$44 -> 0 | E17: =E15*E16*'02_Assumptions'!$C$44 -> 0 | F17: =F15*F16*'02_Assumptions'!$C$44 -> 20196 | G17: =G15*G16*'02_Assumptions'!$C$44 -> 50490 | H17: =H15*H16*'02_Assumptions'!$C$44 -> 90882 | I17: =I15*I16*'02_Assumptions'!$C$44 -> 131274 | ... K17: =K15*K16*'02_Assumptions'!$C$44 -> 201960
A18: Harga durian Rp/kg | B18: ='02_Assumptions'!$C$47*(1+'02_Assumptions'!$C$12)^0*(1+IF(1>='02_Assumptions'!$C$17+'02_Assumptions'!$C$18+1,'02_Assumptions'!$C$19,0)) -> 35000 | C18: ='02_Assumptions'!$C$47*(1+'02_Assumptions'!$C$12)^1*(1+IF(2>='02_Assumptions'!$C$17+'02_Assumptions'!$C$18+1,'02_Assumptions'!$C$19,0)) -> 36050 | D18: ='02_Assumptions'!$C$47*(1+'02_Assumptions'!$C$12)^2*(1+IF(3>='02_Assumptions'!$C$17+'02_Assumptions'!$C$18+1,'02_Assumptions'!$C$19,0)) -> 37131.5 | E18: ='02_Assumptions'!$C$47*(1+'02_Assumptions'!$C$12)^3*(1+IF(4>='02_Assumptions'!$C$17+'02_Assumptions'!$C$18+1,'02_Assumptions'!$C$19,0)) -> 38245.445 | F18: ='02_Assumptions'!$C$47*(1+'02_Assumptions'!$C$12)^4*(1+IF(5>='02_Assumptions'!$C$17+'02_Assumptions'!$C$18+1,'02_Assumptions'!$C$19,0)) -> 39392.808 | G18: ='02_Assumptions'!$C$47*(1+'02_Assumptions'!$C$12)^5*(1+IF(6>='02_Assumptions'!$C$17+'02_Assumptions'!$C$18+1,'02_Assumptions'!$C$19,0)) -> 40574.593 | H18: ='02_Assumptions'!$C$47*(1+'02_Assumptions'!$C$12)^6*(1+IF(7>='02_Assumptions'!$C$17+'02_Assumptions'!$C$18+1,'02_Assumptions'!$C$19,0)) -> 41791.83 | I18: ='02_Assumptions'!$C$47*(1+'02_Assumptions'!$C$12)^7*(1+IF(8>='02_Assumptions'!$C$17+'02_Assumptions'!$C$18+1,'02_Assumptions'!$C$19,0)) -> 43045.585 | J18: ='02_Assumptions'!$C$47*(1+'02_Assumptions'!$C$12)^8*(1+IF(9>='02_Assumptions'!$C$17+'02_Assumptions'!$C$18+1,'02_Assumptions'!$C$19,0)) -> 44336.953 | K18: ='02_Assumptions'!$C$47*(1+'02_Assumptions'!$C$12)^9*(1+IF(10>='02_Assumptions'!$C$17+'02_Assumptions'!$C$18+1,'02_Assumptions'!$C$19,0)) -> 45667.061
A19: PENDAPATAN DURIAN | B19: =B17*B18 -> 0 | C19: =C17*C18 -> 0 | D19: =D17*D18 -> 0 | E19: =E17*E18 -> 0 | F19: =F17*F18 -> 7.9557716e+08 | G19: =G17*G18 -> 2.0486112e+09 | H19: =H17*H18 -> 3.7981251e+09 | I19: =I17*I18 -> 5.6507662e+09 | ... K19: =K17*K18 -> 9.2229197e+09
A20: PENDAPATAN OPSI DAN TAMBAHAN | B20: ='17_Model_Fleksibel'!$P$34+'17_Model_Fleksibel'!$H$116 -> 1458600000 | C20: ='17_Model_Fleksibel'!$Q$34+'17_Model_Fleksibel'!$I$116 -> 924528000 | D20: ='17_Model_Fleksibel'!$R$34+'17_Model_Fleksibel'!$J$116 -> 0 | E20: ='17_Model_Fleksibel'!$S$34+'17_Model_Fleksibel'!$K$116 -> 0 | F20: ='17_Model_Fleksibel'!$T$34+'17_Model_Fleksibel'!$L$116 -> 0 | G20: ='17_Model_Fleksibel'!$U$34+'17_Model_Fleksibel'!$M$116 -> 0 | H20: ='17_Model_Fleksibel'!$V$34+'17_Model_Fleksibel'!$N$116 -> 0 | I20: ='17_Model_Fleksibel'!$W$34+'17_Model_Fleksibel'!$O$116 -> 0 | J20: ='17_Model_Fleksibel'!$X$34+'17_Model_Fleksibel'!$P$116 -> 0 | K20: ='17_Model_Fleksibel'!$Y$34+'17_Model_Fleksibel'!$Q$116 -> 0
A21: TOTAL PENDAPATAN | B21: =SUM(B9,B14,B19,B20) -> 5174664000 | C21: =SUM(C9,C14,C19,C20) -> 4752073920 | D21: =SUM(D9,D14,D19,D20) -> 3.3644252e+09 | E21: =SUM(E9,E14,E19,E20) -> 2.6453249e+09 | F21: =SUM(F9,F14,F19,F20) -> 3.1063611e+09 | G21: =SUM(G9,G14,G19,G20) -> 4.4322994e+09 | H21: =SUM(H9,H14,H19,H20) -> 6.4788709e+09 | I21: =SUM(I9,I14,I19,I20) -> 8.6423482e+09 | ... K21: =SUM(K9,K14,K19,K20) -> 1.2396689e+10
A22: Biaya panen/pengemasan pisang | B22: =B7*'02_Assumptions'!$C$115*(1+'02_Assumptions'!$C$11)^0 -> 495475200 | C22: =C7*'02_Assumptions'!$C$115*(1+'02_Assumptions'!$C$11)^1 -> 515294208 | D22: =D7*'02_Assumptions'!$C$115*(1+'02_Assumptions'!$C$11)^2 -> 4.1681576e+08 | E22: =E7*'02_Assumptions'!$C$115*(1+'02_Assumptions'!$C$11)^3 -> 2.6473755e+08 | F22: =F7*'02_Assumptions'!$C$115*(1+'02_Assumptions'!$C$11)^4 -> 1.4490898e+08 | G22: =G7*'02_Assumptions'!$C$115*(1+'02_Assumptions'!$C$11)^5 -> 90423201 | H22: =H7*'02_Assumptions'!$C$115*(1+'02_Assumptions'!$C$11)^6 -> 62693419 | I22: =I7*'02_Assumptions'!$C$115*(1+'02_Assumptions'!$C$11)^7 -> 65201156 | J22: =J7*'02_Assumptions'!$C$115*(1+'02_Assumptions'!$C$11)^8 -> 67809202 | K22: =K7*'02_Assumptions'!$C$115*(1+'02_Assumptions'!$C$11)^9 -> 70521570
A23: Biaya panen/pengumpulan kelapa | B23: =B12*'02_Assumptions'!$C$116*(1+'02_Assumptions'!$C$11)^0 -> 0 | C23: =C12*'02_Assumptions'!$C$116*(1+'02_Assumptions'!$C$11)^1 -> 0 | D23: =D12*'02_Assumptions'!$C$116*(1+'02_Assumptions'!$C$11)^2 -> 50658791 | E23: =E12*'02_Assumptions'!$C$116*(1+'02_Assumptions'!$C$11)^3 -> 1.22932e+08 | F23: =F12*'02_Assumptions'!$C$116*(1+'02_Assumptions'!$C$11)^4 -> 2.1917019e+08 | G23: =G12*'02_Assumptions'!$C$116*(1+'02_Assumptions'!$C$11)^5 -> 3.03916e+08 | H23: =H12*'02_Assumptions'!$C$116*(1+'02_Assumptions'!$C$11)^6 -> 3.950908e+08 | I23: =I12*'02_Assumptions'!$C$116*(1+'02_Assumptions'!$C$11)^7 -> 4.5198388e+08 | J23: =J12*'02_Assumptions'!$C$116*(1+'02_Assumptions'!$C$11)^8 -> 4.7006323e+08 | K23: =K12*'02_Assumptions'!$C$116*(1+'02_Assumptions'!$C$11)^9 -> 4.8886576e+08
A24: Biaya panen/grading durian | B24: =B17*'02_Assumptions'!$C$117*(1+'02_Assumptions'!$C$11)^0 -> 0 | C24: =C17*'02_Assumptions'!$C$117*(1+'02_Assumptions'!$C$11)^1 -> 0 | D24: =D17*'02_Assumptions'!$C$117*(1+'02_Assumptions'!$C$11)^2 -> 0 | E24: =E17*'02_Assumptions'!$C$117*(1+'02_Assumptions'!$C$11)^3 -> 0 | F24: =F17*'02_Assumptions'!$C$117*(1+'02_Assumptions'!$C$11)^4 -> 35439695 | G24: =G17*'02_Assumptions'!$C$117*(1+'02_Assumptions'!$C$11)^5 -> 92143208 | H24: =H17*'02_Assumptions'!$C$117*(1+'02_Assumptions'!$C$11)^6 -> 1.7249208e+08 | I24: =I17*'02_Assumptions'!$C$117*(1+'02_Assumptions'!$C$11)^7 -> 2.5912144e+08 | J24: =J17*'02_Assumptions'!$C$117*(1+'02_Assumptions'!$C$11)^8 -> 3.5240516e+08 | K24: =K17*'02_Assumptions'!$C$117*(1+'02_Assumptions'!$C$11)^9 -> 4.3117808e+08
A25: TOTAL BIAYA PANEN VARIABEL | B25: =SUM(B22:B24)+'17_Model_Fleksibel'!$Z$35 -> 738575200 | C25: =SUM(C22:C24)+'17_Model_Fleksibel'!$AA$35 -> 670878208 | D25: =SUM(D22:D24)+'17_Model_Fleksibel'!$AB$35 -> 4.6747455e+08 | E25: =SUM(E22:E24)+'17_Model_Fleksibel'!$AC$35 -> 3.8766955e+08 | F25: =SUM(F22:F24)+'17_Model_Fleksibel'!$AD$35 -> 3.9951886e+08 | G25: =SUM(G22:G24)+'17_Model_Fleksibel'!$AE$35 -> 4.8648241e+08 | H25: =SUM(H22:H24)+'17_Model_Fleksibel'!$AF$35 -> 6.3027631e+08 | I25: =SUM(I22:I24)+'17_Model_Fleksibel'!$AG$35 -> 7.7630648e+08 | J25: =SUM(J22:J24)+'17_Model_Fleksibel'!$AH$35 -> 8.902776e+08 | K25: =SUM(K22:K24)+'17_Model_Fleksibel'!$AI$35 -> 9.9056541e+08

Sheet 11_Cash_Flow
A1: Arus Kas Proyek dan Hasil Investasi
A2: Menggabungkan pendapatan, OPEX, dan CAPEX menjadi arus kas proyek, arus kas kumulatif, NPV, IRR, tahun pengembalian, dan kebutuhan pendanaan puncak. Hasil negatif berarti desain komersial perlu diperbaiki sebelum investasi, bukan menghapus pengendalian teknis yang penting.
A4: Ukuran | B4: T0 | C4: T1 | D4: T2 | E4: T3 | F4: T4 | G4: T5 | H4: T6 | I4: T7 | J4: T8 | K4: T9 | L4: T10
A5: Pendapatan | B5: 0 | C5: ='10_Production_Revenue'!$B$21 -> 5174664000 | D5: ='10_Production_Revenue'!$C$21 -> 4752073920 | E5: ='10_Production_Revenue'!$D$21 -> 3.3644252e+09 | F5: ='10_Production_Revenue'!$E$21 -> 2.6453249e+09 | G5: ='10_Production_Revenue'!$F$21 -> 3.1063611e+09 | H5: ='10_Production_Revenue'!$G$21 -> 4.4322994e+09 | I5: ='10_Production_Revenue'!$H$21 -> 6.4788709e+09 | J5: ='10_Production_Revenue'!$I$21 -> 8.6423482e+09 | K5: ='10_Production_Revenue'!$J$21 -> 1.0692477e+10 | L5: ='10_Production_Revenue'!$K$21 -> 1.2396689e+10
A6: OPEX | B6: 0 | C6: =-'09_OPEX_10Y'!$B$17 -> -4886954100 | D6: =-'09_OPEX_10Y'!$C$17 -> -4.9916015e+09 | E6: =-'09_OPEX_10Y'!$D$17 -> -4.4201156e+09 | F6: =-'09_OPEX_10Y'!$E$17 -> -4.2010953e+09 | G6: =-'09_OPEX_10Y'!$F$17 -> -4.2718268e+09 | H6: =-'09_OPEX_10Y'!$G$17 -> -4.5750778e+09 | I6: =-'09_OPEX_10Y'!$H$17 -> -4.8128669e+09 | J6: =-'09_OPEX_10Y'!$I$17 -> -5.2234358e+09 | K6: =-'09_OPEX_10Y'!$J$17 -> -5.4245962e+09 | L6: =-'09_OPEX_10Y'!$K$17 -> -5.8081261e+09
A7: CAPEX awal/lanjutan | B7: =-'08_CAPEX_RAB'!$J$43 -> -15268150480 | C7: =0 -> 0 | D7: =0 -> 0 | E7: =0 -> 0 | F7: =0 -> 0 | G7: =-IF('02_Assumptions'!$C$8=4,'06_Equipment_Tools'!$J$39,'06_Equipment_Tools'!$I$39)*'02_Assumptions'!$C$183 -> -457420000 | H7: =0 -> 0 | I7: =0 -> 0 | J7: =-IF('02_Assumptions'!$C$8=4,'06_Equipment_Tools'!$J$39,'06_Equipment_Tools'!$I$39)*'02_Assumptions'!$C$184 -> -228710000 | K7: =0 -> 0 | L7: =0 -> 0
A8: ARUS KAS PROYEK | B8: =SUM(B5:B7) -> -15268150480 | C8: =SUM(C5:C7) -> 287709900 | D8: =SUM(D5:D7) -> -2.3952754e+08 | E8: =SUM(E5:E7) -> -1.0556905e+09 | F8: =SUM(F5:F7) -> -1.5557704e+09 | G8: =SUM(G5:G7) -> -1.6228857e+09 | H8: =SUM(H5:H7) -> -1.4277844e+08 | I8: =SUM(I5:I7) -> 1.666004e+09 | ... L8: =SUM(L5:L7) -> 6.5885631e+09
